Workbook

Sheet 总览
A1: 家庭5年财务规划（2026-2030）
A2: 制定日期：2026年2月 | 规划周期：2026年2月 - 2030年12月
A4: 📋 基本财务假设
A5: 参数名 | B5: 初始值 | C5: 备注 | D5: 变更1生效 (YYYYMM) | E5: 变更1值 | F5: 变更2生效 (YYYYMM) | G5: 变更2值 | H5: 变更3生效 (YYYYMM) | I5: 变更3值 | J5: 变更4生效 (YYYYMM) | K5: 变更4值 | L5: 变更5生效 (YYYYMM) | M5: 变更5值
A6: 双方月可支配收入合计 | B6: 26000 | C6: 每月税后可支配收入
A7: 年终奖（合计） | B7: 46000
A8: 当前存款 | B8: 380000 | C8: 截至2026年2月
A9: 婚前月租金 | B9: 2400 | C9: 生育前，含停车费
A10: 生育后月租金 | B10: 3900 | C10: 孩子出生后搬入更大住所，含停车费
A11: 月日常开销 | B11: 1500 | C11: 餐饮/交通/娱乐等
A12: 孩子月开销 | B12: 3000 | C12: 奶粉/纸尿裤/早教等（出生后）
A13: 年度旅游支出 | B13: 15000
A14: 存款年利率 | B14: 0.025 | C14: 按年初余额计算，保守型理财参考收益率
A16: 🏠 买房假设
A17: 参数名 | B17: 初始值 | C17: 备注 | D17: 变更1生效 (YYYYMM) | E17: 变更1值 | F17: 变更2生效 (YYYYMM) | G17: 变更2值 | H17: 变更3生效 (YYYYMM) | I17: 变更3值 | J17: 变更4生效 (YYYYMM) | K17: 变更4值 | L17: 变更5生效 (YYYYMM) | M17: 变更5值
A18: 计划买房时间 | B18: 202801 | C18: YYYYMM格式，如202801=2028年1月
A19: 总房价 | B19: 1500000
A20: 首付比例 | B20: 0.3
A21: 贷款年限 | B21: 30 | C21: 年
A22: 贷款年利率 | B22: 0.031 | C22: 商贷参考利率
A23: 首付金额 | B23: =B19*B20 | C23: 自动计算
A24: 贷款总额 | B24: =B19-B23 | C24: 自动计算
A25: 月供金额 | B25: =-PMT(B22/12,B21*12,B24) | C25: 等额本息，自动计算
A27: 📊 五年收支总览（2026—2030）
B28: 📋 不买房方案 | H28: 🏠 买房方案
A29: 项目 | B29: 2026年 | C29: 2027年 | D29: 2028年 | E29: 2029年 | F29: 2030年 | H29: 2026年 | I29: 2027年 | J29: 2028年 | K29: 2029年 | L29: 2030年
A30: 年初余额 | B30: =$B$8 | C30: =B50 | D30: =C50 | E30: =D50 | F30: =E50 | H30: =$B$8 | I30: =H50 | J30: =I50 | K30: =J50 | L30: =K50
A31: 【收入】
A32: 工资收入 | B32: =SUMIF(月度现金流!B:B,2026,月度现金流!D:D) | C32: =SUMIF(月度现金流!B:B,2027,月度现金流!D:D) | D32: =SUMIF(月度现金流!B:B,2028,月度现金流!D:D) | E32: =SUMIF(月度现金流!B:B,2029,月度现金流!D:D) | F32: =SUMIF(月度现金流!B:B,2030,月度现金流!D:D) | H32: =SUMIF('月度现金流（买房）'!B:B,2026,'月度现金流（买房）'!D:D) | I32: =SUMIF('月度现金流（买房）'!B:B,2027,'月度现金流（买房）'!D:D) | J32: =SUMIF('月度现金流（买房）'!B:B,2028,'月度现金流（买房）'!D:D) | K32: =SUMIF('月度现金流（买房）'!B:B,2029,'月度现金流（买房）'!D:D) | L32: =SUMIF('月度现金流（买房）'!B:B,2030,'月度现金流（买房）'!D:D)
A33: 年终奖 | B33: =SUMIF(月度现金流!B:B,2026,月度现金流!E:E) | C33: =SUMIF(月度现金流!B:B,2027,月度现金流!E:E) | D33: =SUMIF(月度现金流!B:B,2028,月度现金流!E:E) | E33: =SUMIF(月度现金流!B:B,2029,月度现金流!E:E) | F33: =SUMIF(月度现金流!B:B,2030,月度现金流!E:E) | H33: =SUMIF('月度现金流（买房）'!B:B,2026,'月度现金流（买房）'!E:E) | I33: =SUMIF('月度现金流（买房）'!B:B,2027,'月度现金流（买房）'!E:E) | J33: =SUMIF('月度现金流（买房）'!B:B,2028,'月度现金流（买房）'!E:E) | K33: =SUMIF('月度现金流（买房）'!B:B,2029,'月度现金流（买房）'!E:E) | L33: =SUMIF('月度现金流（买房）'!B:B,2030,'月度现金流（买房）'!E:E)
A34: 理财收益 | B34: =SUMIF(月度现金流!B:B,2026,月度现金流!F:F) | C34: =SUMIF(月度现金流!B:B,2027,月度现金流!F:F) | D34: =SUMIF(月度现金流!B:B,2028,月度现金流!F:F) | E34: =SUMIF(月度现金流!B:B,2029,月度现金流!F:F) | F34: =SUMIF(月度现金流!B:B,2030,月度现金流!F:F) | H34: =SUMIF('月度现金流（买房）'!B:B,2026,'月度现金流（买房）'!F:F) | I34: =SUMIF('月度现金流（买房）'!B:B,2027,'月度现金流（买房）'!F:F) | J34: =SUMIF('月度现金流（买房）'!B:B,2028,'月度现金流（买房）'!F:F) | K34: =SUMIF('月度现金流（买房）'!B:B,2029,'月度现金流（买房）'!F:F) | L34: =SUMIF('月度现金流（买房）'!B:B,2030,'月度现金流（买房）'!F:F)
A35: 收入小计 | B35: =SUM(B32:B34) | C35: =SUM(C32:C34) | D35: =SUM(D32:D34) | E35: =SUM(E32:E34) | F35: =SUM(F32:F34) | H35: =SUM(H32:H34) | I35: =SUM(I32:I34) | J35: =SUM(J32:J34) | K35: =SUM(K32:K34) | L35: =SUM(L32:L34)
A36: 【支出】
A37: 房租 | B37: =SUMIF(月度现金流!B:B,2026,月度现金流!H:H) | C37: =SUMIF(月度现金流!B:B,2027,月度现金流!H:H) | D37: =SUMIF(月度现金流!B:B,2028,月度现金流!H:H) | E37: =SUMIF(月度现金流!B:B,2029,月度现金流!H:H) | F37: =SUMIF(月度现金流!B:B,2030,月度现金流!H:H) | H37: =SUMIF('月度现金流（买房）'!B:B,2026,'月度现金流（买房）'!H:H) | I37: =SUMIF('月度现金流（买房）'!B:B,2027,'月度现金流（买房）'!H:H) | J37: =SUMIF('月度现金流（买房）'!B:B,2028,'月度现金流（买房）'!H:H) | K37: =SUMIF('月度现金流（买房）'!B:B,2029,'月度现金流（买房）'!H:H) | L37: =SUMIF('月度现金流（买房）'!B:B,2030,'月度现金流（买房）'!H:H)
A38: 日常开销 | B38: =SUMIF(月度现金流!B:B,2026,月度现金流!I:I) | C38: =SUMIF(月度现金流!B:B,2027,月度现金流!I:I) | D38: =SUMIF(月度现金流!B:B,2028,月度现金流!I:I) | E38: =SUMIF(月度现金流!B:B,2029,月度现金流!I:I) | F38: =SUMIF(月度现金流!B:B,2030,月度现金流!I:I) | H38: =SUMIF('月度现金流（买房）'!B:B,2026,'月度现金流（买房）'!I:I) | I38: =SUMIF('月度现金流（买房）'!B:B,2027,'月度现金流（买房）'!I:I) | J38: =SUMIF('月度现金流（买房）'!B:B,2028,'月度现金流（买房）'!I:I) | K38: =SUMIF('月度现金流（买房）'!B:B,2029,'月度现金流（买房）'!I:I) | L38: =SUMIF('月度现金流（买房）'!B:B,2030,'月度现金流（买房）'!I:I)
A39: 育儿开销 | B39: =SUMIF(月度现金流!B:B,2026,月度现金流!J:J) | C39: =SUMIF(月度现金流!B:B,2027,月度现金流!J:J) | D39: =SUMIF(月度现金流!B:B,2028,月度现金流!J:J) | E39: =SUMIF(月度现金流!B:B,2029,月度现金流!J:J) | F39: =SUMIF(月度现金流!B:B,2030,月度现金流!J:J) | H39: =SUMIF('月度现金流（买房）'!B:B,2026,'月度现金流（买房）'!J:J) | I39: =SUMIF('月度现金流（买房）'!B:B,2027,'月度现金流（买房）'!J:J) | J39: =SUMIF('月度现金流（买房）'!B:B,2028,'月度现金流（买房）'!J:J) | K39: =SUMIF('月度现金流（买房）'!B:B,2029,'月度现金流（买房）'!J:J) | L39: =SUMIF('月度现金流（买房）'!B:B,2030,'月度现金流（买房）'!J:J)
A40: 旅游支出 | B40: =SUMIFS(月度现金流!K:K,月度现金流!B:B,2026,月度现金流!L:L,"年度旅游") | C40: =SUMIFS(月度现金流!K:K,月度现金流!B:B,2027,月度现金流!L:L,"年度旅游") | D40: =SUMIFS(月度现金流!K:K,月度现金流!B:B,2028,月度现金流!L:L,"年度旅游") | E40: =SUMIFS(月度现金流!K:K,月度现金流!B:B,2029,月度现金流!L:L,"年度旅游") | F40: =SUMIFS(月度现金流!K:K,月度现金流!B:B,2030,月度现金流!L:L,"年度旅游") | H40: =SUMIFS('月度现金流（买房）'!K:K,'月度现金流（买房）'!B:B,2026,'月度现金流（买房）'!L:L,"年度旅游") | I40: =SUMIFS('月度现金流（买房）'!K:K,'月度现金流（买房）'!B:B,2027,'月度现金流（买房）'!L:L,"年度旅游") | J40: =SUMIFS('月度现金流（买房）'!K:K,'月度现金流（买房）'!B:B,2028,'月度现金流（买房）'!L:L,"年度旅游") | K40: =SUMIFS('月度现金流（买房）'!K:K,'月度现金流（买房）'!B:B,2029,'月度现金流（买房）'!L:L,"年度旅游") | L40: =SUMIFS('月度现金流（买房）'!K:K,'月度现金流（买房）'!B:B,2030,'月度现金流（买房）'!L:L,"年度旅游")
A41: 首付支出 | H41: =SUMIF('月度现金流（买房）'!B:B,2026,'月度现金流（买房）'!M:M) | I41: =SUMIF('月度现金流（买房）'!B:B,2027,'月度现金流（买房）'!M:M) | J41: =SUMIF('月度现金流（买房）'!B:B,2028,'月度现金流（买房）'!M:M) | K41: =SUMIF('月度现金流（买房）'!B:B,2029,'月度现金流（买房）'!M:M) | L41: =SUMIF('月度现金流（买房）'!B:B,2030,'月度现金流（买房）'!M:M)
A42: 房贷月供 | H42: =SUMIF('月度现金流（买房）'!B:B,2026,'月度现金流（买房）'!N:N) | I42: =SUMIF('月度现金流（买房）'!B:B,2027,'月度现金流（买房）'!N:N) | J42: =SUMIF('月度现金流（买房）'!B:B,2028,'月度现金流（买房）'!N:N) | K42: =SUMIF('月度现金流（买房）'!B:B,2029,'月度现金流（买房）'!N:N) | L42: =SUMIF('月度现金流（买房）'!B:B,2030,'月度现金流（买房）'!N:N)
A43: 【特殊支出】
A44: 结婚 | B44: =SUMIFS(月度现金流!K:K,月度现金流!B:B,2026,月度现金流!L:L,"结婚支出") | C44: =SUMIFS(月度现金流!K:K,月度现金流!B:B,2027,月度现金流!L:L,"结婚支出") | D44: =SUMIFS(月度现金流!K:K,月度现金流!B:B,2028,月度现金流!L:L,"结婚支出") | E44: =SUMIFS(月度现金流!K:K,月度现金流!B:B,2029,月度现金流!L:L,"结婚支出") | F44: =SUMIFS(月度现金流!K:K,月度现金流!B:B,2030,月度现金流!L:L,"结婚支出") | H44: =SUMIFS('月度现金流（买房）'!K:K,'月度现金流（买房）'!B:B,2026,'月度现金流（买房）'!L:L,"结婚支出") | I44: =SUMIFS('月度现金流（买房）'!K:K,'月度现金流（买房）'!B:B,2027,'月度现金流（买房）'!L:L,"结婚支出") | J44: =SUMIFS('月度现金流（买房）'!K:K,'月度现金流（买房）'!B:B,2028,'月度现金流（买房）'!L:L,"结婚支出") | K44: =SUMIFS('月度现金流（买房）'!K:K,'月度现金流（买房）'!B:B,2029,'月度现金流（买房）'!L:L,"结婚支出") | L44: =SUMIFS('月度现金流（买房）'!K:K,'月度现金流（买房）'!B:B,2030,'月度现金流（买房）'!L:L,"结婚支出")
A45: 产检及分娩 | B45: =SUMIFS(月度现金流!K:K,月度现金流!B:B,2026,月度现金流!L:L,"孕产费用") | C45: =SUMIFS(月度现金流!K:K,月度现金流!B:B,2027,月度现金流!L:L,"孕产费用") | D45: =SUMIFS(月度现金流!K:K,月度现金流!B:B,2028,月度现金流!L:L,"孕产费用") | E45: =SUMIFS(月度现金流!K:K,月度现金流!B:B,2029,月度现金流!L:L,"孕产费用") | F45: =SUMIFS(月度现金流!K:K,月度现金流!B:B,2030,月度现金流!L:L,"孕产费用") | H45: =SUMIFS('月度现金流（买房）'!K:K,'月度现金流（买房）'!B:B,2026,'月度现金流（买房）'!L:L,"孕产费用") | I45: =SUMIFS('月度现金流（买房）'!K:K,'月度现金流（买房）'!B:B,2027,'月度现金流（买房）'!L:L,"孕产费用") | J45: =SUMIFS('月度现金流（买房）'!K:K,'月度现金流（买房）'!B:B,2028,'月度现金流（买房）'!L:L,"孕产费用") | K45: =SUMIFS('月度现金流（买房）'!K:K,'月度现金流（买房）'!B:B,2029,'月度现金流（买房）'!L:L,"孕产费用") | L45: =SUMIFS('月度现金流（买房）'!K:K,'月度现金流（买房）'!B:B,2030,'月度现金流（买房）'!L:L,"孕产费用")
A46: * 特殊支出数据来源：月度现金流汇总；结婚（2026年5月）及孕产费用（2027年9月）均为一次性支出
A47: 支出小计 | B47: =SUM(B37:B40)+SUM(B44:B45) | C47: =SUM(C37:C40)+SUM(C44:C45) | D47: =SUM(D37:D40)+SUM(D44:D45) | E47: =SUM(E37:E40)+SUM(E44:E45) | F47: =SUM(F37:F40)+SUM(F44:F45) | H47: =SUM(H37:H40)+H41+H42+SUM(H44:H45) | I47: =SUM(I37:I40)+I41+I42+SUM(I44:I45) | J47: =SUM(J37:J40)+J41+J42+SUM(J44:J45) | K47: =SUM(K37:K40)+K41+K42+SUM(K44:K45) | L47: =SUM(L37:L40)+L41+L42+SUM(L44:L45)
A49: 年度结余（收入−支出） | B49: =B35-B47 | C49: =C35-C47 | D49: =D35-D47 | E49: =E35-E47 | F49: =F35-F47 | H49: =H35-H47 | I49: =I35-I47 | J49: =J35-J47 | K49: =K35-K47 | L49: =L35-L47
A50: 年末累计余额 | B50: =B30+B49 | C50: =C30+C49 | D50: =D30+D49 | E50: =E30+E49 | F50: =F30+F49 | H50: =H30+H49 | I50: =I30+I49 | J50: =J30+J49 | K50: =K30+K49 | L50: =L30+L49

Sheet 月度现金流
A1: 序号 | B1: 年份 | C1: 月份 | D1: 月收入(元) | E1: 年终奖(元) | F1: 理财收益(元) | G1: 总收入(元) | H1: 房租(元) | I1: 日常开销(元) | J1: 孩子开销(元) | K1: 特殊支出(元) | L1: 特殊说明 | M1: 总支出(元) | N1: 当月净储蓄(元) | O1: 累计储蓄(元)
A2: 1 | B2: 2026 | C2: 2月 | D2: =IF(AND(总览!$L$6<>"",B2*100+VALUE(LEFT(C2,LEN(C2)-1))>=总览!$L$6),总览!$M$6,IF(AND(总览!$J$6<>"",B2*100+VALUE(LEFT(C2,LEN(C2)-1))>=总览!$J$6),总览!$K$6,IF(AND(总览!$H$6<>"",B2*100+VALUE(LEFT(C2,LEN(C2)-1))>=总览!$H$6),总览!$I$6,IF(AND(总览!$F$6<>"",B2*100+VALUE(LEFT(C2,LEN(C2)-1))>=总览!$F$6),总览!$G$6,IF(AND(总览!$D$6<>"",B2*100+VALUE(LEFT(C2,LEN(C2)-1))>=总览!$D$6),总览!$E$6,总览!$B$6))))) | E2: =IF(C2="12月",IF(AND(总览!$L$7<>"",B2*100+VALUE(LEFT(C2,LEN(C2)-1))>=总览!$L$7),总览!$M$7,IF(AND(总览!$J$7<>"",B2*100+VALUE(LEFT(C2,LEN(C2)-1))>=总览!$J$7),总览!$K$7,IF(AND(总览!$H$7<>"",B2*100+VALUE(LEFT(C2,LEN(C2)-1))>=总览!$H$7),总览!$I$7,IF(AND(总览!$F$7<>"",B2*100+VALUE(LEFT(C2,LEN(C2)-1))>=总览!$F$7),总览!$G$7,IF(AND(总览!$D$7<>"",B2*100+VALUE(LEFT(C2,LEN(C2)-1))>=总览!$D$7),总览!$E$7,总览!$B$7))))),0) | F2: =ROUND(总览!$B$8*总览!$B$14/12,0) | G2: =D2+E2+F2 | H2: =IF(OR(B2>2027,AND(B2=2027,VALUE(LEFT(C2,LEN(C2)-1))>=9)),IF(AND(总览!$L$10<>"",B2*100+VALUE(LEFT(C2,LEN(C2)-1))>=总览!$L$10),总览!$M$10,IF(AND(总览!$J$10<>"",B2*100+VALUE(LEFT(C2,LEN(C2)-1))>=总览!$J$10),总览!$K$10,IF(AND(总览!$H$10<>"",B2*100+VALUE(LEFT(C2,LEN(C2)-1))>=总览!$H$10),总览!$I$10,IF(AND(总览!$F$10<>"",B2*100+VALUE(LEFT(C2,LEN(C2)-1))>=总览!$F$10),总览!$G$10,IF(AND(总览!$D$10<>"",B2*100+VALUE(LEFT(C2,LEN(C2)-1))>=总览!$D$10),总览!$E$10,总览!$B$10))))),IF(AND(总览!$L$9<>"",B2*100+VALUE(LEFT(C2,LEN(C2)-1))>=总览!$L$9),总览!$M$9,IF(AND(总览!$J$9<>"",B2*100+VALUE(LEFT(C2,LEN(C2)-1))>=总览!$J$9),总览!$K$9,IF(AND(总览!$H$9<>"",B2*100+VALUE(LEFT(C2,LEN(C2)-1))>=总览!$H$9),总览!$I$9,IF(AND(总览!$F$9<>"",B2*100+VALUE(LEFT(C2,LEN(C2)-1))>=总览!$F$9),总览!$G$9,IF(AND(总览!$D$9<>"",B2*100+VALUE(LEFT(C2,LEN(C2)-1))>=总览!$D$9),总览!$E$9,总览!$B$9)))))) | I2: =IF(AND(总览!$L$11<>"",B2*100+VALUE(LEFT(C2,LEN(C2)-1))>=总览!$L$11),总览!$M$11,IF(AND(总览!$J$11<>"",B2*100+VALUE(LEFT(C2,LEN(C2)-1))>=总览!$J$11),总览!$K$11,IF(AND(总览!$H$11<>"",B2*100+VALUE(LEFT(C2,LEN(C2)-1))>=总览!$H$11),总览!$I$11,IF(AND(总览!$F$11<>"",B2*100+VALUE(LEFT(C2,LEN(C2)-1))>=总览!$F$11),总览!$G$11,IF(AND(总览!$D$11<>"",B2*100+VALUE(LEFT(C2,LEN(C2)-1))>=总览!$D$11),总览!$E$11,总览!$B$11))))) | J2: =IF(OR(B2>2027,AND(B2=2027,VALUE(LEFT(C2,LEN(C2)-1))>=9)),IF(AND(总览!$L$12<>"",B2*100+VALUE(LEFT(C2,LEN(C2)-1))>=总览!$L$12),总览!$M$12,IF(AND(总览!$J$12<>"",B2*100+VALUE(LEFT(C2,LEN(C2)-1))>=总览!$J$12),总览!$K$12,IF(AND(总览!$H$12<>"",B2*100+VALUE(LEFT(C2,LEN(C2)-1))>=总览!$H$12),总览!$I$12,IF(AND(总览!$F$12<>"",B2*100+VALUE(LEFT(C2,LEN(C2)-1))>=总览!$F$12),总览!$G$12,IF(AND(总览!$D$12<>"",B2*100+VALUE(LEFT(C2,LEN(C2)-1))>=总览!$D$12),总览!$E$12,总览!$B$12))))),0) | K2: =IF(AND(B2=2026,C2="5月"),120000,IF(AND(B2=2027,C2="9月"),30000,IF(C2="10月",IF(AND(总览!$L$13<>"",B2*100+VALUE(LEFT(C2,LEN(C2)-1))>=总览!$L$13),总览!$M$13,IF(AND(总览!$J$13<>"",B2*100+VALUE(LEFT(C2,LEN(C2)-1))>=总览!$J$13),总览!$K$13,IF(AND(总览!$H$13<>"",B2*100+VALUE(LEFT(C2,LEN(C2)-1))>=总览!$H$13),总览!$I$13,IF(AND(总览!$F$13<>"",B2*100+VALUE(LEFT(C2,LEN(C2)-1))>=总览!$F$13),总览!$G$13,IF(AND(总览!$D$13<>"",B2*100+VALUE(LEFT(C2,LEN(C2)-1))>=总览!$D$13),总览!$E$13,总览!$B$13))))),0))) | M2: =SUM(H2:K2) | N2: =G2-M2 | O2: =总览!$B$8+N2
A3: 2 | B3: 2026 | C3: 3月 | D3: =IF(AND(总览!$L$6<>"",B3*100+VALUE(LEFT(C3,LEN(C3)-1))>=总览!$L$6),总览!$M$6,IF(AND(总览!$J$6<>"",B3*100+VALUE(LEFT(C3,LEN(C3)-1))>=总览!$J$6),总览!$K$6,IF(AND(总览!$H$6<>"",B3*100+VALUE(LEFT(C3,LEN(C3)-1))>=总览!$H$6),总览!$I$6,IF(AND(总览!$F$6<>"",B3*100+VALUE(LEFT(C3,LEN(C3)-1))>=总览!$F$6),总览!$G$6,IF(AND(总览!$D$6<>"",B3*100+VALUE(LEFT(C3,LEN(C3)-1))>=总览!$D$6),总览!$E$6,总览!$B$6))))) | E3: =IF(C3="12月",IF(AND(总览!$L$7<>"",B3*100+VALUE(LEFT(C3,LEN(C3)-1))>=总览!$L$7),总览!$M$7,IF(AND(总览!$J$7<>"",B3*100+VALUE(LEFT(C3,LEN(C3)-1))>=总览!$J$7),总览!$K$7,IF(AND(总览!$H$7<>"",B3*100+VALUE(LEFT(C3,LEN(C3)-1))>=总览!$H$7),总览!$I$7,IF(AND(总览!$F$7<>"",B3*100+VALUE(LEFT(C3,LEN(C3)-1))>=总览!$F$7),总览!$G$7,IF(AND(总览!$D$7<>"",B3*100+VALUE(LEFT(C3,LEN(C3)-1))>=总览!$D$7),总览!$E$7,总览!$B$7))))),0) | F3: =ROUND(O2*总览!$B$14/12,0) | G3: =D3+E3+F3 | H3: =IF(OR(B3>2027,AND(B3=2027,VALUE(LEFT(C3,LEN(C3)-1))>=9)),IF(AND(总览!$L$10<>"",B3*100+VALUE(LEFT(C3,LEN(C3)-1))>=总览!$L$10),总览!$M$10,IF(AND(总览!$J$10<>"",B3*100+VALUE(LEFT(C3,LEN(C3)-1))>=总览!$J$10),总览!$K$10,IF(AND(总览!$H$10<>"",B3*100+VALUE(LEFT(C3,LEN(C3)-1))>=总览!$H$10),总览!$I$10,IF(AND(总览!$F$10<>"",B3*100+VALUE(LEFT(C3,LEN(C3)-1))>=总览!$F$10),总览!$G$10,IF(AND(总览!$D$10<>"",B3*100+VALUE(LEFT(C3,LEN(C3)-1))>=总览!$D$10),总览!$E$10,总览!$B$10))))),IF(AND(总览!$L$9<>"",B3*100+VALUE(LEFT(C3,LEN(C3)-1))>=总览!$L$9),总览!$M$9,IF(AND(总览!$J$9<>"",B3*100+VALUE(LEFT(C3,LEN(C3)-1))>=总览!$J$9),总览!$K$9,IF(AND(总览!$H$9<>"",B3*100+VALUE(LEFT(C3,LEN(C3)-1))>=总览!$H$9),总览!$I$9,IF(AND(总览!$F$9<>"",B3*100+VALUE(LEFT(C3,LEN(C3)-1))>=总览!$F$9),总览!$G$9,IF(AND(总览!$D$9<>"",B3*100+VALUE(LEFT(C3,LEN(C3)-1))>=总览!$D$9),总览!$E$9,总览!$B$9)))))) | I3: =IF(AND(总览!$L$11<>"",B3*100+VALUE(LEFT(C3,LEN(C3)-1))>=总览!$L$11),总览!$M$11,IF(AND(总览!$J$11<>"",B3*100+VALUE(LEFT(C3,LEN(C3)-1))>=总览!$J$11),总览!$K$11,IF(AND(总览!$H$11<>"",B3*100+VALUE(LEFT(C3,LEN(C3)-1))>=总览!$H$11),总览!$I$11,IF(AND(总览!$F$11<>"",B3*100+VALUE(LEFT(C3,LEN(C3)-1))>=总览!$F$11),总览!$G$11,IF(AND(总览!$D$11<>"",B3*100+VALUE(LEFT(C3,LEN(C3)-1))>=总览!$D$11),总览!$E$11,总览!$B$11))))) | J3: =IF(OR(B3>2027,AND(B3=2027,VALUE(LEFT(C3,LEN(C3)-1))>=9)),IF(AND(总览!$L$12<>"",B3*100+VALUE(LEFT(C3,LEN(C3)-1))>=总览!$L$12),总览!$M$12,IF(AND(总览!$J$12<>"",B3*100+VALUE(LEFT(C3,LEN(C3)-1))>=总览!$J$12),总览!$K$12,IF(AND(总览!$H$12<>"",B3*100+VALUE(LEFT(C3,LEN(C3)-1))>=总览!$H$12),总览!$I$12,IF(AND(总览!$F$12<>"",B3*100+VALUE(LEFT(C3,LEN(C3)-1))>=总览!$F$12),总览!$G$12,IF(AND(总览!$D$12<>"",B3*100+VALUE(LEFT(C3,LEN(C3)-1))>=总览!$D$12),总览!$E$12,总览!$B$12))))),0) | K3: =IF(AND(B3=2026,C3="5月"),120000,IF(AND(B3=2027,C3="9月"),30000,IF(C3="10月",IF(AND(总览!$L$13<>"",B3*100+VALUE(LEFT(C3,LEN(C3)-1))>=总览!$L$13),总览!$M$13,IF(AND(总览!$J$13<>"",B3*100+VALUE(LEFT(C3,LEN(C3)-1))>=总览!$J$13),总览!$K$13,IF(AND(总览!$H$13<>"",B3*100+VALUE(LEFT(C3,LEN(C3)-1))>=总览!$H$13),总览!$I$13,IF(AND(总览!$F$13<>"",B3*100+VALUE(LEFT(C3,LEN(C3)-1))>=总览!$F$13),总览!$G$13,IF(AND(总览!$D$13<>"",B3*100+VALUE(LEFT(C3,LEN(C3)-1))>=总览!$D$13),总览!$E$13,总览!$B$13))))),0))) | M3: =SUM(H3:K3) | N3: =G3-M3 | O3: =O2+N3
A4: 3 | B4: 2026 | C4: 4月 | D4: =IF(AND(总览!$L$6<>"",B4*100+VALUE(LEFT(C4,LEN(C4)-1))>=总览!$L$6),总览!$M$6,IF(AND(总览!$J$6<>"",B4*100+VALUE(LEFT(C4,LEN(C4)-1))>=总览!$J$6),总览!$K$6,IF(AND(总览!$H$6<>"",B4*100+VALUE(LEFT(C4,LEN(C4)-1))>=总览!$H$6),总览!$I$6,IF(AND(总览!$F$6<>"",B4*100+VALUE(LEFT(C4,LEN(C4)-1))>=总览!$F$6),总览!$G$6,IF(AND(总览!$D$6<>"",B4*100+VALUE(LEFT(C4,LEN(C4)-1))>=总览!$D$6),总览!$E$6,总览!$B$6))))) | E4: =IF(C4="12月",IF(AND(总览!$L$7<>"",B4*100+VALUE(LEFT(C4,LEN(C4)-1))>=总览!$L$7),总览!$M$7,IF(AND(总览!$J$7<>"",B4*100+VALUE(LEFT(C4,LEN(C4)-1))>=总览!$J$7),总览!$K$7,IF(AND(总览!$H$7<>"",B4*100+VALUE(LEFT(C4,LEN(C4)-1))>=总览!$H$7),总览!$I$7,IF(AND(总览!$F$7<>"",B4*100+VALUE(LEFT(C4,LEN(C4)-1))>=总览!$F$7),总览!$G$7,IF(AND(总览!$D$7<>"",B4*100+VALUE(LEFT(C4,LEN(C4)-1))>=总览!$D$7),总览!$E$7,总览!$B$7))))),0) | F4: =ROUND(O3*总览!$B$14/12,0) | G4: =D4+E4+F4 | H4: =IF(OR(B4>2027,AND(B4=2027,VALUE(LEFT(C4,LEN(C4)-1))>=9)),IF(AND(总览!$L$10<>"",B4*100+VALUE(LEFT(C4,LEN(C4)-1))>=总览!$L$10),总览!$M$10,IF(AND(总览!$J$10<>"",B4*100+VALUE(LEFT(C4,LEN(C4)-1))>=总览!$J$10),总览!$K$10,IF(AND(总览!$H$10<>"",B4*100+VALUE(LEFT(C4,LEN(C4)-1))>=总览!$H$10),总览!$I$10,IF(AND(总览!$F$10<>"",B4*100+VALUE(LEFT(C4,LEN(C4)-1))>=总览!$F$10),总览!$G$10,IF(AND(总览!$D$10<>"",B4*100+VALUE(LEFT(C4,LEN(C4)-1))>=总览!$D$10),总览!$E$10,总览!$B$10))))),IF(AND(总览!$L$9<>"",B4*100+VALUE(LEFT(C4,LEN(C4)-1))>=总览!$L$9),总览!$M$9,IF(AND(总览!$J$9<>"",B4*100+VALUE(LEFT(C4,LEN(C4)-1))>=总览!$J$9),总览!$K$9,IF(AND(总览!$H$9<>"",B4*100+VALUE(LEFT(C4,LEN(C4)-1))>=总览!$H$9),总览!$I$9,IF(AND(总览!$F$9<>"",B4*100+VALUE(LEFT(C4,LEN(C4)-1))>=总览!$F$9),总览!$G$9,IF(AND(总览!$D$9<>"",B4*100+VALUE(LEFT(C4,LEN(C4)-1))>=总览!$D$9),总览!$E$9,总览!$B$9)))))) | I4: =IF(AND(总览!$L$11<>"",B4*100+VALUE(LEFT(C4,LEN(C4)-1))>=总览!$L$11),总览!$M$11,IF(AND(总览!$J$11<>"",B4*100+VALUE(LEFT(C4,LEN(C4)-1))>=总览!$J$11),总览!$K$11,IF(AND(总览!$H$11<>"",B4*100+VALUE(LEFT(C4,LEN(C4)-1))>=总览!$H$11),总览!$I$11,IF(AND(总览!$F$11<>"",B4*100+VALUE(LEFT(C4,LEN(C4)-1))>=总览!$F$11),总览!$G$11,IF(AND(总览!$D$11<>"",B4*100+VALUE(LEFT(C4,LEN(C4)-1))>=总览!$D$11),总览!$E$11,总览!$B$11))))) | J4: =IF(OR(B4>2027,AND(B4=2027,VALUE(LEFT(C4,LEN(C4)-1))>=9)),IF(AND(总览!$L$12<>"",B4*100+VALUE(LEFT(C4,LEN(C4)-1))>=总览!$L$12),总览!$M$12,IF(AND(总览!$J$12<>"",B4*100+VALUE(LEFT(C4,LEN(C4)-1))>=总览!$J$12),总览!$K$12,IF(AND(总览!$H$12<>"",B4*100+VALUE(LEFT(C4,LEN(C4)-1))>=总览!$H$12),总览!$I$12,IF(AND(总览!$F$12<>"",B4*100+VALUE(LEFT(C4,LEN(C4)-1))>=总览!$F$12),总览!$G$12,IF(AND(总览!$D$12<>"",B4*100+VALUE(LEFT(C4,LEN(C4)-1))>=总览!$D$12),总览!$E$12,总览!$B$12))))),0) | K4: =IF(AND(B4=2026,C4="5月"),120000,IF(AND(B4=2027,C4="9月"),30000,IF(C4="10月",IF(AND(总览!$L$13<>"",B4*100+VALUE(LEFT(C4,LEN(C4)-1))>=总览!$L$13),总览!$M$13,IF(AND(总览!$J$13<>"",B4*100+VALUE(LEFT(C4,LEN(C4)-1))>=总览!$J$13),总览!$K$13,IF(AND(总览!$H$13<>"",B4*100+VALUE(LEFT(C4,LEN(C4)-1))>=总览!$H$13),总览!$I$13,IF(AND(总览!$F$13<>"",B4*100+VALUE(LEFT(C4,LEN(C4)-1))>=总览!$F$13),总览!$G$13,IF(AND(总览!$D$13<>"",B4*100+VALUE(LEFT(C4,LEN(C4)-1))>=总览!$D$13),总览!$E$13,总览!$B$13))))),0))) | M4: =SUM(H4:K4) | N4: =G4-M4 | O4: =O3+N4
A5: 4 | B5: 2026 | C5: 5月 | D5: =IF(AND(总览!$L$6<>"",B5*100+VALUE(LEFT(C5,LEN(C5)-1))>=总览!$L$6),总览!$M$6,IF(AND(总览!$J$6<>"",B5*100+VALUE(LEFT(C5,LEN(C5)-1))>=总览!$J$6),总览!$K$6,IF(AND(总览!$H$6<>"",B5*100+VALUE(LEFT(C5,LEN(C5)-1))>=总览!$H$6),总览!$I$6,IF(AND(总览!$F$6<>"",B5*100+VALUE(LEFT(C5,LEN(C5)-1))>=总览!$F$6),总览!$G$6,IF(AND(总览!$D$6<>"",B5*100+VALUE(LEFT(C5,LEN(C5)-1))>=总览!$D$6),总览!$E$6,总览!$B$6))))) | E5: =IF(C5="12月",IF(AND(总览!$L$7<>"",B5*100+VALUE(LEFT(C5,LEN(C5)-1))>=总览!$L$7),总览!$M$7,IF(AND(总览!$J$7<>"",B5*100+VALUE(LEFT(C5,LEN(C5)-1))>=总览!$J$7),总览!$K$7,IF(AND(总览!$H$7<>"",B5*100+VALUE(LEFT(C5,LEN(C5)-1))>=总览!$H$7),总览!$I$7,IF(AND(总览!$F$7<>"",B5*100+VALUE(LEFT(C5,LEN(C5)-1))>=总览!$F$7),总览!$G$7,IF(AND(总览!$D$7<>"",B5*100+VALUE(LEFT(C5,LEN(C5)-1))>=总览!$D$7),总览!$E$7,总览!$B$7))))),0) | F5: =ROUND(O4*总览!$B$14/12,0) | G5: =D5+E5+F5 | H5: =IF(OR(B5>2027,AND(B5=2027,VALUE(LEFT(C5,LEN(C5)-1))>=9)),IF(AND(总览!$L$10<>"",B5*100+VALUE(LEFT(C5,LEN(C5)-1))>=总览!$L$10),总览!$M$10,IF(AND(总览!$J$10<>"",B5*100+VALUE(LEFT(C5,LEN(C5)-1))>=总览!$J$10),总览!$K$10,IF(AND(总览!$H$10<>"",B5*100+VALUE(LEFT(C5,LEN(C5)-1))>=总览!$H$10),总览!$I$10,IF(AND(总览!$F$10<>"",B5*100+VALUE(LEFT(C5,LEN(C5)-1))>=总览!$F$10),总览!$G$10,IF(AND(总览!$D$10<>"",B5*100+VALUE(LEFT(C5,LEN(C5)-1))>=总览!$D$10),总览!$E$10,总览!$B$10))))),IF(AND(总览!$L$9<>"",B5*100+VALUE(LEFT(C5,LEN(C5)-1))>=总览!$L$9),总览!$M$9,IF(AND(总览!$J$9<>"",B5*100+VALUE(LEFT(C5,LEN(C5)-1))>=总览!$J$9),总览!$K$9,IF(AND(总览!$H$9<>"",B5*100+VALUE(LEFT(C5,LEN(C5)-1))>=总览!$H$9),总览!$I$9,IF(AND(总览!$F$9<>"",B5*100+VALUE(LEFT(C5,LEN(C5)-1))>=总览!$F$9),总览!$G$9,IF(AND(总览!$D$9<>"",B5*100+VALUE(LEFT(C5,LEN(C5)-1))>=总览!$D$9),总览!$E$9,总览!$B$9)))))) | I5: =IF(AND(总览!$L$11<>"",B5*100+VALUE(LEFT(C5,LEN(C5)-1))>=总览!$L$11),总览!$M$11,IF(AND(总览!$J$11<>"",B5*100+VALUE(LEFT(C5,LEN(C5)-1))>=总览!$J$11),总览!$K$11,IF(AND(总览!$H$11<>"",B5*100+VALUE(LEFT(C5,LEN(C5)-1))>=总览!$H$11),总览!$I$11,IF(AND(总览!$F$11<>"",B5*100+VALUE(LEFT(C5,LEN(C5)-1))>=总览!$F$11),总览!$G$11,IF(AND(总览!$D$11<>"",B5*100+VALUE(LEFT(C5,LEN(C5)-1))>=总览!$D$11),总览!$E$11,总览!$B$11))))) | J5: =IF(OR(B5>2027,AND(B5=2027,VALUE(LEFT(C5,LEN(C5)-1))>=9)),IF(AND(总览!$L$12<>"",B5*100+VALUE(LEFT(C5,LEN(C5)-1))>=总览!$L$12),总览!$M$12,IF(AND(总览!$J$12<>"",B5*100+VALUE(LEFT(C5,LEN(C5)-1))>=总览!$J$12),总览!$K$12,IF(AND(总览!$H$12<>"",B5*100+VALUE(LEFT(C5,LEN(C5)-1))>=总览!$H$12),总览!$I$12,IF(AND(总览!$F$12<>"",B5*100+VALUE(LEFT(C5,LEN(C5)-1))>=总览!$F$12),总览!$G$12,IF(AND(总览!$D$12<>"",B5*100+VALUE(LEFT(C5,LEN(C5)-1))>=总览!$D$12),总览!$E$12,总览!$B$12))))),0) | K5: =IF(AND(B5=2026,C5="5月"),120000,IF(AND(B5=2027,C5="9月"),30000,IF(C5="10月",IF(AND(总览!$L$13<>"",B5*100+VALUE(LEFT(C5,LEN(C5)-1))>=总览!$L$13),总览!$M$13,IF(AND(总览!$J$13<>"",B5*100+VALUE(LEFT(C5,LEN(C5)-1))>=总览!$J$13),总览!$K$13,IF(AND(总览!$H$13<>"",B5*100+VALUE(LEFT(C5,LEN(C5)-1))>=总览!$H$13),总览!$I$13,IF(AND(总览!$F$13<>"",B5*100+VALUE(LEFT(C5,LEN(C5)-1))>=总览!$F$13),总览!$G$13,IF(AND(总览!$D$13<>"",B5*100+VALUE(LEFT(C5,LEN(C5)-1))>=总览!$D$13),总览!$E$13,总览!$B$13))))),0))) | L5: 结婚支出 | M5: =SUM(H5:K5) | N5: =G5-M5 | O5: =O4+N5
A6: 5 | B6: 2026 | C6: 6月 | D6: =IF(AND(总览!$L$6<>"",B6*100+VALUE(LEFT(C6,LEN(C6)-1))>=总览!$L$6),总览!$M$6,IF(AND(总览!$J$6<>"",B6*100+VALUE(LEFT(C6,LEN(C6)-1))>=总览!$J$6),总览!$K$6,IF(AND(总览!$H$6<>"",B6*100+VALUE(LEFT(C6,LEN(C6)-1))>=总览!$H$6),总览!$I$6,IF(AND(总览!$F$6<>"",B6*100+VALUE(LEFT(C6,LEN(C6)-1))>=总览!$F$6),总览!$G$6,IF(AND(总览!$D$6<>"",B6*100+VALUE(LEFT(C6,LEN(C6)-1))>=总览!$D$6),总览!$E$6,总览!$B$6))))) | E6: =IF(C6="12月",IF(AND(总览!$L$7<>"",B6*100+VALUE(LEFT(C6,LEN(C6)-1))>=总览!$L$7),总览!$M$7,IF(AND(总览!$J$7<>"",B6*100+VALUE(LEFT(C6,LEN(C6)-1))>=总览!$J$7),总览!$K$7,IF(AND(总览!$H$7<>"",B6*100+VALUE(LEFT(C6,LEN(C6)-1))>=总览!$H$7),总览!$I$7,IF(AND(总览!$F$7<>"",B6*100+VALUE(LEFT(C6,LEN(C6)-1))>=总览!$F$7),总览!$G$7,IF(AND(总览!$D$7<>"",B6*100+VALUE(LEFT(C6,LEN(C6)-1))>=总览!$D$7),总览!$E$7,总览!$B$7))))),0) | F6: =ROUND(O5*总览!$B$14/12,0) | G6: =D6+E6+F6 | H6: =IF(OR(B6>2027,AND(B6=2027,VALUE(LEFT(C6,LEN(C6)-1))>=9)),IF(AND(总览!$L$10<>"",B6*100+VALUE(LEFT(C6,LEN(C6)-1))>=总览!$L$10),总览!$M$10,IF(AND(总览!$J$10<>"",B6*100+VALUE(LEFT(C6,LEN(C6)-1))>=总览!$J$10),总览!$K$10,IF(AND(总览!$H$10<>"",B6*100+VALUE(LEFT(C6,LEN(C6)-1))>=总览!$H$10),总览!$I$10,IF(AND(总览!$F$10<>"",B6*100+VALUE(LEFT(C6,LEN(C6)-1))>=总览!$F$10),总览!$G$10,IF(AND(总览!$D$10<>"",B6*100+VALUE(LEFT(C6,LEN(C6)-1))>=总览!$D$10),总览!$E$10,总览!$B$10))))),IF(AND(总览!$L$9<>"",B6*100+VALUE(LEFT(C6,LEN(C6)-1))>=总览!$L$9),总览!$M$9,IF(AND(总览!$J$9<>"",B6*100+VALUE(LEFT(C6,LEN(C6)-1))>=总览!$J$9),总览!$K$9,IF(AND(总览!$H$9<>"",B6*100+VALUE(LEFT(C6,LEN(C6)-1))>=总览!$H$9),总览!$I$9,IF(AND(总览!$F$9<>"",B6*100+VALUE(LEFT(C6,LEN(C6)-1))>=总览!$F$9),总览!$G$9,IF(AND(总览!$D$9<>"",B6*100+VALUE(LEFT(C6,LEN(C6)-1))>=总览!$D$9),总览!$E$9,总览!$B$9)))))) | I6: =IF(AND(总览!$L$11<>"",B6*100+VALUE(LEFT(C6,LEN(C6)-1))>=总览!$L$11),总览!$M$11,IF(AND(总览!$J$11<>"",B6*100+VALUE(LEFT(C6,LEN(C6)-1))>=总览!$J$11),总览!$K$11,IF(AND(总览!$H$11<>"",B6*100+VALUE(LEFT(C6,LEN(C6)-1))>=总览!$H$11),总览!$I$11,IF(AND(总览!$F$11<>"",B6*100+VALUE(LEFT(C6,LEN(C6)-1))>=总览!$F$11),总览!$G$11,IF(AND(总览!$D$11<>"",B6*100+VALUE(LEFT(C6,LEN(C6)-1))>=总览!$D$11),总览!$E$11,总览!$B$11))))) | J6: =IF(OR(B6>2027,AND(B6=2027,VALUE(LEFT(C6,LEN(C6)-1))>=9)),IF(AND(总览!$L$12<>"",B6*100+VALUE(LEFT(C6,LEN(C6)-1))>=总览!$L$12),总览!$M$12,IF(AND(总览!$J$12<>"",B6*100+VALUE(LEFT(C6,LEN(C6)-1))>=总览!$J$12),总览!$K$12,IF(AND(总览!$H$12<>"",B6*100+VALUE(LEFT(C6,LEN(C6)-1))>=总览!$H$12),总览!$I$12,IF(AND(总览!$F$12<>"",B6*100+VALUE(LEFT(C6,LEN(C6)-1))>=总览!$F$12),总览!$G$12,IF(AND(总览!$D$12<>"",B6*100+VALUE(LEFT(C6,LEN(C6)-1))>=总览!$D$12),总览!$E$12,总览!$B$12))))),0) | K6: =IF(AND(B6=2026,C6="5月"),120000,IF(AND(B6=2027,C6="9月"),30000,IF(C6="10月",IF(AND(总览!$L$13<>"",B6*100+VALUE(LEFT(C6,LEN(C6)-1))>=总览!$L$13),总览!$M$13,IF(AND(总览!$J$13<>"",B6*100+VALUE(LEFT(C6,LEN(C6)-1))>=总览!$J$13),总览!$K$13,IF(AND(总览!$H$13<>"",B6*100+VALUE(LEFT(C6,LEN(C6)-1))>=总览!$H$13),总览!$I$13,IF(AND(总览!$F$13<>"",B6*100+VALUE(LEFT(C6,LEN(C6)-1))>=总览!$F$13),总览!$G$13,IF(AND(总览!$D$13<>"",B6*100+VALUE(LEFT(C6,LEN(C6)-1))>=总览!$D$13),总览!$E$13,总览!$B$13))))),0))) | M6: =SUM(H6:K6) | N6: =G6-M6 | O6: =O5+N6
A7: 6 | B7: 2026 | C7: 7月 | D7: =IF(AND(总览!$L$6<>"",B7*100+VALUE(LEFT(C7,LEN(C7)-1))>=总览!$L$6),总览!$M$6,IF(AND(总览!$J$6<>"",B7*100+VALUE(LEFT(C7,LEN(C7)-1))>=总览!$J$6),总览!$K$6,IF(AND(总览!$H$6<>"",B7*100+VALUE(LEFT(C7,LEN(C7)-1))>=总览!$H$6),总览!$I$6,IF(AND(总览!$F$6<>"",B7*100+VALUE(LEFT(C7,LEN(C7)-1))>=总览!$F$6),总览!$G$6,IF(AND(总览!$D$6<>"",B7*100+VALUE(LEFT(C7,LEN(C7)-1))>=总览!$D$6),总览!$E$6,总览!$B$6))))) | E7: =IF(C7="12月",IF(AND(总览!$L$7<>"",B7*100+VALUE(LEFT(C7,LEN(C7)-1))>=总览!$L$7),总览!$M$7,IF(AND(总览!$J$7<>"",B7*100+VALUE(LEFT(C7,LEN(C7)-1))>=总览!$J$7),总览!$K$7,IF(AND(总览!$H$7<>"",B7*100+VALUE(LEFT(C7,LEN(C7)-1))>=总览!$H$7),总览!$I$7,IF(AND(总览!$F$7<>"",B7*100+VALUE(LEFT(C7,LEN(C7)-1))>=总览!$F$7),总览!$G$7,IF(AND(总览!$D$7<>"",B7*100+VALUE(LEFT(C7,LEN(C7)-1))>=总览!$D$7),总览!$E$7,总览!$B$7))))),0) | F7: =ROUND(O6*总览!$B$14/12,0) | G7: =D7+E7+F7 | H7: =IF(OR(B7>2027,AND(B7=2027,VALUE(LEFT(C7,LEN(C7)-1))>=9)),IF(AND(总览!$L$10<>"",B7*100+VALUE(LEFT(C7,LEN(C7)-1))>=总览!$L$10),总览!$M$10,IF(AND(总览!$J$10<>"",B7*100+VALUE(LEFT(C7,LEN(C7)-1))>=总览!$J$10),总览!$K$10,IF(AND(总览!$H$10<>"",B7*100+VALUE(LEFT(C7,LEN(C7)-1))>=总览!$H$10),总览!$I$10,IF(AND(总览!$F$10<>"",B7*100+VALUE(LEFT(C7,LEN(C7)-1))>=总览!$F$10),总览!$G$10,IF(AND(总览!$D$10<>"",B7*100+VALUE(LEFT(C7,LEN(C7)-1))>=总览!$D$10),总览!$E$10,总览!$B$10))))),IF(AND(总览!$L$9<>"",B7*100+VALUE(LEFT(C7,LEN(C7)-1))>=总览!$L$9),总览!$M$9,IF(AND(总览!$J$9<>"",B7*100+VALUE(LEFT(C7,LEN(C7)-1))>=总览!$J$9),总览!$K$9,IF(AND(总览!$H$9<>"",B7*100+VALUE(LEFT(C7,LEN(C7)-1))>=总览!$H$9),总览!$I$9,IF(AND(总览!$F$9<>"",B7*100+VALUE(LEFT(C7,LEN(C7)-1))>=总览!$F$9),总览!$G$9,IF(AND(总览!$D$9<>"",B7*100+VALUE(LEFT(C7,LEN(C7)-1))>=总览!$D$9),总览!$E$9,总览!$B$9)))))) | I7: =IF(AND(总览!$L$11<>"",B7*100+VALUE(LEFT(C7,LEN(C7)-1))>=总览!$L$11),总览!$M$11,IF(AND(总览!$J$11<>"",B7*100+VALUE(LEFT(C7,LEN(C7)-1))>=总览!$J$11),总览!$K$11,IF(AND(总览!$H$11<>"",B7*100+VALUE(LEFT(C7,LEN(C7)-1))>=总览!$H$11),总览!$I$11,IF(AND(总览!$F$11<>"",B7*100+VALUE(LEFT(C7,LEN(C7)-1))>=总览!$F$11),总览!$G$11,IF(AND(总览!$D$11<>"",B7*100+VALUE(LEFT(C7,LEN(C7)-1))>=总览!$D$11),总览!$E$11,总览!$B$11))))) | J7: =IF(OR(B7>2027,AND(B7=2027,VALUE(LEFT(C7,LEN(C7)-1))>=9)),IF(AND(总览!$L$12<>"",B7*100+VALUE(LEFT(C7,LEN(C7)-1))>=总览!$L$12),总览!$M$12,IF(AND(总览!$J$12<>"",B7*100+VALUE(LEFT(C7,LEN(C7)-1))>=总览!$J$12),总览!$K$12,IF(AND(总览!$H$12<>"",B7*100+VALUE(LEFT(C7,LEN(C7)-1))>=总览!$H$12),总览!$I$12,IF(AND(总览!$F$12<>"",B7*100+VALUE(LEFT(C7,LEN(C7)-1))>=总览!$F$12),总览!$G$12,IF(AND(总览!$D$12<>"",B7*100+VALUE(LEFT(C7,LEN(C7)-1))>=总览!$D$12),总览!$E$12,总览!$B$12))))),0) | K7: =IF(AND(B7=2026,C7="5月"),120000,IF(AND(B7=2027,C7="9月"),30000,IF(C7="10月",IF(AND(总览!$L$13<>"",B7*100+VALUE(LEFT(C7,LEN(C7)-1))>=总览!$L$13),总览!$M$13,IF(AND(总览!$J$13<>"",B7*100+VALUE(LEFT(C7,LEN(C7)-1))>=总览!$J$13),总览!$K$13,IF(AND(总览!$H$13<>"",B7*100+VALUE(LEFT(C7,LEN(C7)-1))>=总览!$H$13),总览!$I$13,IF(AND(总览!$F$13<>"",B7*100+VALUE(LEFT(C7,LEN(C7)-1))>=总览!$F$13),总览!$G$13,IF(AND(总览!$D$13<>"",B7*100+VALUE(LEFT(C7,LEN(C7)-1))>=总览!$D$13),总览!$E$13,总览!$B$13))))),0))) | M7: =SUM(H7:K7) | N7: =G7-M7 | O7: =O6+N7
A8: 7 | B8: 2026 | C8: 8月 | D8: =IF(AND(总览!$L$6<>"",B8*100+VALUE(LEFT(C8,LEN(C8)-1))>=总览!$L$6),总览!$M$6,IF(AND(总览!$J$6<>"",B8*100+VALUE(LEFT(C8,LEN(C8)-1))>=总览!$J$6),总览!$K$6,IF(AND(总览!$H$6<>"",B8*100+VALUE(LEFT(C8,LEN(C8)-1))>=总览!$H$6),总览!$I$6,IF(AND(总览!$F$6<>"",B8*100+VALUE(LEFT(C8,LEN(C8)-1))>=总览!$F$6),总览!$G$6,IF(AND(总览!$D$6<>"",B8*100+VALUE(LEFT(C8,LEN(C8)-1))>=总览!$D$6),总览!$E$6,总览!$B$6))))) | E8: =IF(C8="12月",IF(AND(总览!$L$7<>"",B8*100+VALUE(LEFT(C8,LEN(C8)-1))>=总览!$L$7),总览!$M$7,IF(AND(总览!$J$7<>"",B8*100+VALUE(LEFT(C8,LEN(C8)-1))>=总览!$J$7),总览!$K$7,IF(AND(总览!$H$7<>"",B8*100+VALUE(LEFT(C8,LEN(C8)-1))>=总览!$H$7),总览!$I$7,IF(AND(总览!$F$7<>"",B8*100+VALUE(LEFT(C8,LEN(C8)-1))>=总览!$F$7),总览!$G$7,IF(AND(总览!$D$7<>"",B8*100+VALUE(LEFT(C8,LEN(C8)-1))>=总览!$D$7),总览!$E$7,总览!$B$7))))),0) | F8: =ROUND(O7*总览!$B$14/12,0) | G8: =D8+E8+F8 | H8: =IF(OR(B8>2027,AND(B8=2027,VALUE(LEFT(C8,LEN(C8)-1))>=9)),IF(AND(总览!$L$10<>"",B8*100+VALUE(LEFT(C8,LEN(C8)-1))>=总览!$L$10),总览!$M$10,IF(AND(总览!$J$10<>"",B8*100+VALUE(LEFT(C8,LEN(C8)-1))>=总览!$J$10),总览!$K$10,IF(AND(总览!$H$10<>"",B8*100+VALUE(LEFT(C8,LEN(C8)-1))>=总览!$H$10),总览!$I$10,IF(AND(总览!$F$10<>"",B8*100+VALUE(LEFT(C8,LEN(C8)-1))>=总览!$F$10),总览!$G$10,IF(AND(总览!$D$10<>"",B8*100+VALUE(LEFT(C8,LEN(C8)-1))>=总览!$D$10),总览!$E$10,总览!$B$10))))),IF(AND(总览!$L$9<>"",B8*100+VALUE(LEFT(C8,LEN(C8)-1))>=总览!$L$9),总览!$M$9,IF(AND(总览!$J$9<>"",B8*100+VALUE(LEFT(C8,LEN(C8)-1))>=总览!$J$9),总览!$K$9,IF(AND(总览!$H$9<>"",B8*100+VALUE(LEFT(C8,LEN(C8)-1))>=总览!$H$9),总览!$I$9,IF(AND(总览!$F$9<>"",B8*100+VALUE(LEFT(C8,LEN(C8)-1))>=总览!$F$9),总览!$G$9,IF(AND(总览!$D$9<>"",B8*100+VALUE(LEFT(C8,LEN(C8)-1))>=总览!$D$9),总览!$E$9,总览!$B$9)))))) | I8: =IF(AND(总览!$L$11<>"",B8*100+VALUE(LEFT(C8,LEN(C8)-1))>=总览!$L$11),总览!$M$11,IF(AND(总览!$J$11<>"",B8*100+VALUE(LEFT(C8,LEN(C8)-1))>=总览!$J$11),总览!$K$11,IF(AND(总览!$H$11<>"",B8*100+VALUE(LEFT(C8,LEN(C8)-1))>=总览!$H$11),总览!$I$11,IF(AND(总览!$F$11<>"",B8*100+VALUE(LEFT(C8,LEN(C8)-1))>=总览!$F$11),总览!$G$11,IF(AND(总览!$D$11<>"",B8*100+VALUE(LEFT(C8,LEN(C8)-1))>=总览!$D$11),总览!$E$11,总览!$B$11))))) | J8: =IF(OR(B8>2027,AND(B8=2027,VALUE(LEFT(C8,LEN(C8)-1))>=9)),IF(AND(总览!$L$12<>"",B8*100+VALUE(LEFT(C8,LEN(C8)-1))>=总览!$L$12),总览!$M$12,IF(AND(总览!$J$12<>"",B8*100+VALUE(LEFT(C8,LEN(C8)-1))>=总览!$J$12),总览!$K$12,IF(AND(总览!$H$12<>"",B8*100+VALUE(LEFT(C8,LEN(C8)-1))>=总览!$H$12),总览!$I$12,IF(AND(总览!$F$12<>"",B8*100+VALUE(LEFT(C8,LEN(C8)-1))>=总览!$F$12),总览!$G$12,IF(AND(总览!$D$12<>"",B8*100+VALUE(LEFT(C8,LEN(C8)-1))>=总览!$D$12),总览!$E$12,总览!$B$12))))),0) | K8: =IF(AND(B8=2026,C8="5月"),120000,IF(AND(B8=2027,C8="9月"),30000,IF(C8="10月",IF(AND(总览!$L$13<>"",B8*100+VALUE(LEFT(C8,LEN(C8)-1))>=总览!$L$13),总览!$M$13,IF(AND(总览!$J$13<>"",B8*100+VALUE(LEFT(C8,LEN(C8)-1))>=总览!$J$13),总览!$K$13,IF(AND(总览!$H$13<>"",B8*100+VALUE(LEFT(C8,LEN(C8)-1))>=总览!$H$13),总览!$I$13,IF(AND(总览!$F$13<>"",B8*100+VALUE(LEFT(C8,LEN(C8)-1))>=总览!$F$13),总览!$G$13,IF(AND(总览!$D$13<>"",B8*100+VALUE(LEFT(C8,LEN(C8)-1))>=总览!$D$13),总览!$E$13,总览!$B$13))))),0))) | M8: =SUM(H8:K8) | N8: =G8-M8 | O8: =O7+N8
A9: 8 | B9: 2026 | C9: 9月 | D9: =IF(AND(总览!$L$6<>"",B9*100+VALUE(LEFT(C9,LEN(C9)-1))>=总览!$L$6),总览!$M$6,IF(AND(总览!$J$6<>"",B9*100+VALUE(LEFT(C9,LEN(C9)-1))>=总览!$J$6),总览!$K$6,IF(AND(总览!$H$6<>"",B9*100+VALUE(LEFT(C9,LEN(C9)-1))>=总览!$H$6),总览!$I$6,IF(AND(总览!$F$6<>"",B9*100+VALUE(LEFT(C9,LEN(C9)-1))>=总览!$F$6),总览!$G$6,IF(AND(总览!$D$6<>"",B9*100+VALUE(LEFT(C9,LEN(C9)-1))>=总览!$D$6),总览!$E$6,总览!$B$6))))) | E9: =IF(C9="12月",IF(AND(总览!$L$7<>"",B9*100+VALUE(LEFT(C9,LEN(C9)-1))>=总览!$L$7),总览!$M$7,IF(AND(总览!$J$7<>"",B9*100+VALUE(LEFT(C9,LEN(C9)-1))>=总览!$J$7),总览!$K$7,IF(AND(总览!$H$7<>"",B9*100+VALUE(LEFT(C9,LEN(C9)-1))>=总览!$H$7),总览!$I$7,IF(AND(总览!$F$7<>"",B9*100+VALUE(LEFT(C9,LEN(C9)-1))>=总览!$F$7),总览!$G$7,IF(AND(总览!$D$7<>"",B9*100+VALUE(LEFT(C9,LEN(C9)-1))>=总览!$D$7),总览!$E$7,总览!$B$7))))),0) | F9: =ROUND(O8*总览!$B$14/12,0) | G9: =D9+E9+F9 | H9: =IF(OR(B9>2027,AND(B9=2027,VALUE(LEFT(C9,LEN(C9)-1))>=9)),IF(AND(总览!$L$10<>"",B9*100+VALUE(LEFT(C9,LEN(C9)-1))>=总览!$L$10),总览!$M$10,IF(AND(总览!$J$10<>"",B9*100+VALUE(LEFT(C9,LEN(C9)-1))>=总览!$J$10),总览!$K$10,IF(AND(总览!$H$10<>"",B9*100+VALUE(LEFT(C9,LEN(C9)-1))>=总览!$H$10),总览!$I$10,IF(AND(总览!$F$10<>"",B9*100+VALUE(LEFT(C9,LEN(C9)-1))>=总览!$F$10),总览!$G$10,IF(AND(总览!$D$10<>"",B9*100+VALUE(LEFT(C9,LEN(C9)-1))>=总览!$D$10),总览!$E$10,总览!$B$10))))),IF(AND(总览!$L$9<>"",B9*100+VALUE(LEFT(C9,LEN(C9)-1))>=总览!$L$9),总览!$M$9,IF(AND(总览!$J$9<>"",B9*100+VALUE(LEFT(C9,LEN(C9)-1))>=总览!$J$9),总览!$K$9,IF(AND(总览!$H$9<>"",B9*100+VALUE(LEFT(C9,LEN(C9)-1))>=总览!$H$9),总览!$I$9,IF(AND(总览!$F$9<>"",B9*100+VALUE(LEFT(C9,LEN(C9)-1))>=总览!$F$9),总览!$G$9,IF(AND(总览!$D$9<>"",B9*100+VALUE(LEFT(C9,LEN(C9)-1))>=总览!$D$9),总览!$E$9,总览!$B$9)))))) | I9: =IF(AND(总览!$L$11<>"",B9*100+VALUE(LEFT(C9,LEN(C9)-1))>=总览!$L$11),总览!$M$11,IF(AND(总览!$J$11<>"",B9*100+VALUE(LEFT(C9,LEN(C9)-1))>=总览!$J$11),总览!$K$11,IF(AND(总览!$H$11<>"",B9*100+VALUE(LEFT(C9,LEN(C9)-1))>=总览!$H$11),总览!$I$11,IF(AND(总览!$F$11<>"",B9*100+VALUE(LEFT(C9,LEN(C9)-1))>=总览!$F$11),总览!$G$11,IF(AND(总览!$D$11<>"",B9*100+VALUE(LEFT(C9,LEN(C9)-1))>=总览!$D$11),总览!$E$11,总览!$B$11))))) | J9: =IF(OR(B9>2027,AND(B9=2027,VALUE(LEFT(C9,LEN(C9)-1))>=9)),IF(AND(总览!$L$12<>"",B9*100+VALUE(LEFT(C9,LEN(C9)-1))>=总览!$L$12),总览!$M$12,IF(AND(总览!$J$12<>"",B9*100+VALUE(LEFT(C9,LEN(C9)-1))>=总览!$J$12),总览!$K$12,IF(AND(总览!$H$12<>"",B9*100+VALUE(LEFT(C9,LEN(C9)-1))>=总览!$H$12),总览!$I$12,IF(AND(总览!$F$12<>"",B9*100+VALUE(LEFT(C9,LEN(C9)-1))>=总览!$F$12),总览!$G$12,IF(AND(总览!$D$12<>"",B9*100+VALUE(LEFT(C9,LEN(C9)-1))>=总览!$D$12),总览!$E$12,总览!$B$12))))),0) | K9: =IF(AND(B9=2026,C9="5月"),120000,IF(AND(B9=2027,C9="9月"),30000,IF(C9="10月",IF(AND(总览!$L$13<>"",B9*100+VALUE(LEFT(C9,LEN(C9)-1))>=总览!$L$13),总览!$M$13,IF(AND(总览!$J$13<>"",B9*100+VALUE(LEFT(C9,LEN(C9)-1))>=总览!$J$13),总览!$K$13,IF(AND(总览!$H$13<>"",B9*100+VALUE(LEFT(C9,LEN(C9)-1))>=总览!$H$13),总览!$I$13,IF(AND(总览!$F$13<>"",B9*100+VALUE(LEFT(C9,LEN(C9)-1))>=总览!$F$13),总览!$G$13,IF(AND(总览!$D$13<>"",B9*100+VALUE(LEFT(C9,LEN(C9)-1))>=总览!$D$13),总览!$E$13,总览!$B$13))))),0))) | M9: =SUM(H9:K9) | N9: =G9-M9 | O9: =O8+N9
A10: 9 | B10: 2026 | C10: 10月 | D10: =IF(AND(总览!$L$6<>"",B10*100+VALUE(LEFT(C10,LEN(C10)-1))>=总览!$L$6),总览!$M$6,IF(AND(总览!$J$6<>"",B10*100+VALUE(LEFT(C10,LEN(C10)-1))>=总览!$J$6),总览!$K$6,IF(AND(总览!$H$6<>"",B10*100+VALUE(LEFT(C10,LEN(C10)-1))>=总览!$H$6),总览!$I$6,IF(AND(总览!$F$6<>"",B10*100+VALUE(LEFT(C10,LEN(C10)-1))>=总览!$F$6),总览!$G$6,IF(AND(总览!$D$6<>"",B10*100+VALUE(LEFT(C10,LEN(C10)-1))>=总览!$D$6),总览!$E$6,总览!$B$6))))) | E10: =IF(C10="12月",IF(AND(总览!$L$7<>"",B10*100+VALUE(LEFT(C10,LEN(C10)-1))>=总览!$L$7),总览!$M$7,IF(AND(总览!$J$7<>"",B10*100+VALUE(LEFT(C10,LEN(C10)-1))>=总览!$J$7),总览!$K$7,IF(AND(总览!$H$7<>"",B10*100+VALUE(LEFT(C10,LEN(C10)-1))>=总览!$H$7),总览!$I$7,IF(AND(总览!$F$7<>"",B10*100+VALUE(LEFT(C10,LEN(C10)-1))>=总览!$F$7),总览!$G$7,IF(AND(总览!$D$7<>"",B10*100+VALUE(LEFT(C10,LEN(C10)-1))>=总览!$D$7),总览!$E$7,总览!$B$7))))),0) | F10: =ROUND(O9*总览!$B$14/12,0) | G10: =D10+E10+F10 | H10: =IF(OR(B10>2027,AND(B10=2027,VALUE(LEFT(C10,LEN(C10)-1))>=9)),IF(AND(总览!$L$10<>"",B10*100+VALUE(LEFT(C10,LEN(C10)-1))>=总览!$L$10),总览!$M$10,IF(AND(总览!$J$10<>"",B10*100+VALUE(LEFT(C10,LEN(C10)-1))>=总览!$J$10),总览!$K$10,IF(AND(总览!$H$10<>"",B10*100+VALUE(LEFT(C10,LEN(C10)-1))>=总览!$H$10),总览!$I$10,IF(AND(总览!$F$10<>"",B10*100+VALUE(LEFT(C10,LEN(C10)-1))>=总览!$F$10),总览!$G$10,IF(AND(总览!$D$10<>"",B10*100+VALUE(LEFT(C10,LEN(C10)-1))>=总览!$D$10),总览!$E$10,总览!$B$10))))),IF(AND(总览!$L$9<>"",B10*100+VALUE(LEFT(C10,LEN(C10)-1))>=总览!$L$9),总览!$M$9,IF(AND(总览!$J$9<>"",B10*100+VALUE(LEFT(C10,LEN(C10)-1))>=总览!$J$9),总览!$K$9,IF(AND(总览!$H$9<>"",B10*100+VALUE(LEFT(C10,LEN(C10)-1))>=总览!$H$9),总览!$I$9,IF(AND(总览!$F$9<>"",B10*100+VALUE(LEFT(C10,LEN(C10)-1))>=总览!$F$9),总览!$G$9,IF(AND(总览!$D$9<>"",B10*100+VALUE(LEFT(C10,LEN(C10)-1))>=总览!$D$9),总览!$E$9,总览!$B$9)))))) | I10: =IF(AND(总览!$L$11<>"",B10*100+VALUE(LEFT(C10,LEN(C10)-1))>=总览!$L$11),总览!$M$11,IF(AND(总览!$J$11<>"",B10*100+VALUE(LEFT(C10,LEN(C10)-1))>=总览!$J$11),总览!$K$11,IF(AND(总览!$H$11<>"",B10*100+VALUE(LEFT(C10,LEN(C10)-1))>=总览!$H$11),总览!$I$11,IF(AND(总览!$F$11<>"",B10*100+VALUE(LEFT(C10,LEN(C10)-1))>=总览!$F$11),总览!$G$11,IF(AND(总览!$D$11<>"",B10*100+VALUE(LEFT(C10,LEN(C10)-1))>=总览!$D$11),总览!$E$11,总览!$B$11))))) | J10: =IF(OR(B10>2027,AND(B10=2027,VALUE(LEFT(C10,LEN(C10)-1))>=9)),IF(AND(总览!$L$12<>"",B10*100+VALUE(LEFT(C10,LEN(C10)-1))>=总览!$L$12),总览!$M$12,IF(AND(总览!$J$12<>"",B10*100+VALUE(LEFT(C10,LEN(C10)-1))>=总览!$J$12),总览!$K$12,IF(AND(总览!$H$12<>"",B10*100+VALUE(LEFT(C10,LEN(C10)-1))>=总览!$H$12),总览!$I$12,IF(AND(总览!$F$12<>"",B10*100+VALUE(LEFT(C10,LEN(C10)-1))>=总览!$F$12),总览!$G$12,IF(AND(总览!$D$12<>"",B10*100+VALUE(LEFT(C10,LEN(C10)-1))>=总览!$D$12),总览!$E$12,总览!$B$12))))),0) | K10: =IF(AND(B10=2026,C10="5月"),120000,IF(AND(B10=2027,C10="9月"),30000,IF(C10="10月",IF(AND(总览!$L$13<>"",B10*100+VALUE(LEFT(C10,LEN(C10)-1))>=总览!$L$13),总览!$M$13,IF(AND(总览!$J$13<>"",B10*100+VALUE(LEFT(C10,LEN(C10)-1))>=总览!$J$13),总览!$K$13,IF(AND(总览!$H$13<>"",B10*100+VALUE(LEFT(C10,LEN(C10)-1))>=总览!$H$13),总览!$I$13,IF(AND(总览!$F$13<>"",B10*100+VALUE(LEFT(C10,LEN(C10)-1))>=总览!$F$13),总览!$G$13,IF(AND(总览!$D$13<>"",B10*100+VALUE(LEFT(C10,LEN(C10)-1))>=总览!$D$13),总览!$E$13,总览!$B$13))))),0))) | L10: 年度旅游 | M10: =SUM(H10:K10) | N10: =G10-M10 | O10: =O9+N10
A11: 10 | B11: 2026 | C11: 11月 | D11: =IF(AND(总览!$L$6<>"",B11*100+VALUE(LEFT(C11,LEN(C11)-1))>=总览!$L$6),总览!$M$6,IF(AND(总览!$J$6<>"",B11*100+VALUE(LEFT(C11,LEN(C11)-1))>=总览!$J$6),总览!$K$6,IF(AND(总览!$H$6<>"",B11*100+VALUE(LEFT(C11,LEN(C11)-1))>=总览!$H$6),总览!$I$6,IF(AND(总览!$F$6<>"",B11*100+VALUE(LEFT(C11,LEN(C11)-1))>=总览!$F$6),总览!$G$6,IF(AND(总览!$D$6<>"",B11*100+VALUE(LEFT(C11,LEN(C11)-1))>=总览!$D$6),总览!$E$6,总览!$B$6))))) | E11: =IF(C11="12月",IF(AND(总览!$L$7<>"",B11*100+VALUE(LEFT(C11,LEN(C11)-1))>=总览!$L$7),总览!$M$7,IF(AND(总览!$J$7<>"",B11*100+VALUE(LEFT(C11,LEN(C11)-1))>=总览!$J$7),总览!$K$7,IF(AND(总览!$H$7<>"",B11*100+VALUE(LEFT(C11,LEN(C11)-1))>=总览!$H$7),总览!$I$7,IF(AND(总览!$F$7<>"",B11*100+VALUE(LEFT(C11,LEN(C11)-1))>=总览!$F$7),总览!$G$7,IF(AND(总览!$D$7<>"",B11*100+VALUE(LEFT(C11,LEN(C11)-1))>=总览!$D$7),总览!$E$7,总览!$B$7))))),0) | F11: =ROUND(O10*总览!$B$14/12,0) | G11: =D11+E11+F11 | H11: =IF(OR(B11>2027,AND(B11=2027,VALUE(LEFT(C11,LEN(C11)-1))>=9)),IF(AND(总览!$L$10<>"",B11*100+VALUE(LEFT(C11,LEN(C11)-1))>=总览!$L$10),总览!$M$10,IF(AND(总览!$J$10<>"",B11*100+VALUE(LEFT(C11,LEN(C11)-1))>=总览!$J$10),总览!$K$10,IF(AND(总览!$H$10<>"",B11*100+VALUE(LEFT(C11,LEN(C11)-1))>=总览!$H$10),总览!$I$10,IF(AND(总览!$F$10<>"",B11*100+VALUE(LEFT(C11,LEN(C11)-1))>=总览!$F$10),总览!$G$10,IF(AND(总览!$D$10<>"",B11*100+VALUE(LEFT(C11,LEN(C11)-1))>=总览!$D$10),总览!$E$10,总览!$B$10))))),IF(AND(总览!$L$9<>"",B11*100+VALUE(LEFT(C11,LEN(C11)-1))>=总览!$L$9),总览!$M$9,IF(AND(总览!$J$9<>"",B11*100+VALUE(LEFT(C11,LEN(C11)-1))>=总览!$J$9),总览!$K$9,IF(AND(总览!$H$9<>"",B11*100+VALUE(LEFT(C11,LEN(C11)-1))>=总览!$H$9),总览!$I$9,IF(AND(总览!$F$9<>"",B11*100+VALUE(LEFT(C11,LEN(C11)-1))>=总览!$F$9),总览!$G$9,IF(AND(总览!$D$9<>"",B11*100+VALUE(LEFT(C11,LEN(C11)-1))>=总览!$D$9),总览!$E$9,总览!$B$9)))))) | I11: =IF(AND(总览!$L$11<>"",B11*100+VALUE(LEFT(C11,LEN(C11)-1))>=总览!$L$11),总览!$M$11,IF(AND(总览!$J$11<>"",B11*100+VALUE(LEFT(C11,LEN(C11)-1))>=总览!$J$11),总览!$K$11,IF(AND(总览!$H$11<>"",B11*100+VALUE(LEFT(C11,LEN(C11)-1))>=总览!$H$11),总览!$I$11,IF(AND(总览!$F$11<>"",B11*100+VALUE(LEFT(C11,LEN(C11)-1))>=总览!$F$11),总览!$G$11,IF(AND(总览!$D$11<>"",B11*100+VALUE(LEFT(C11,LEN(C11)-1))>=总览!$D$11),总览!$E$11,总览!$B$11))))) | J11: =IF(OR(B11>2027,AND(B11=2027,VALUE(LEFT(C11,LEN(C11)-1))>=9)),IF(AND(总览!$L$12<>"",B11*100+VALUE(LEFT(C11,LEN(C11)-1))>=总览!$L$12),总览!$M$12,IF(AND(总览!$J$12<>"",B11*100+VALUE(LEFT(C11,LEN(C11)-1))>=总览!$J$12),总览!$K$12,IF(AND(总览!$H$12<>"",B11*100+VALUE(LEFT(C11,LEN(C11)-1))>=总览!$H$12),总览!$I$12,IF(AND(总览!$F$12<>"",B11*100+VALUE(LEFT(C11,LEN(C11)-1))>=总览!$F$12),总览!$G$12,IF(AND(总览!$D$12<>"",B11*100+VALUE(LEFT(C11,LEN(C11)-1))>=总览!$D$12),总览!$E$12,总览!$B$12))))),0) | K11: =IF(AND(B11=2026,C11="5月"),120000,IF(AND(B11=2027,C11="9月"),30000,IF(C11="10月",IF(AND(总览!$L$13<>"",B11*100+VALUE(LEFT(C11,LEN(C11)-1))>=总览!$L$13),总览!$M$13,IF(AND(总览!$J$13<>"",B11*100+VALUE(LEFT(C11,LEN(C11)-1))>=总览!$J$13),总览!$K$13,IF(AND(总览!$H$13<>"",B11*100+VALUE(LEFT(C11,LEN(C11)-1))>=总览!$H$13),总览!$I$13,IF(AND(总览!$F$13<>"",B11*100+VALUE(LEFT(C11,LEN(C11)-1))>=总览!$F$13),总览!$G$13,IF(AND(总览!$D$13<>"",B11*100+VALUE(LEFT(C11,LEN(C11)-1))>=总览!$D$13),总览!$E$13,总览!$B$13))))),0))) | M11: =SUM(H11:K11) | N11: =G11-M11 | O11: =O10+N11
A12: 11 | B12: 2026 | C12: 12月 | D12: =IF(AND(总览!$L$6<>"",B12*100+VALUE(LEFT(C12,LEN(C12)-1))>=总览!$L$6),总览!$M$6,IF(AND(总览!$J$6<>"",B12*100+VALUE(LEFT(C12,LEN(C12)-1))>=总览!$J$6),总览!$K$6,IF(AND(总览!$H$6<>"",B12*100+VALUE(LEFT(C12,LEN(C12)-1))>=总览!$H$6),总览!$I$6,IF(AND(总览!$F$6<>"",B12*100+VALUE(LEFT(C12,LEN(C12)-1))>=总览!$F$6),总览!$G$6,IF(AND(总览!$D$6<>"",B12*100+VALUE(LEFT(C12,LEN(C12)-1))>=总览!$D$6),总览!$E$6,总览!$B$6))))) | E12: =IF(C12="12月",IF(AND(总览!$L$7<>"",B12*100+VALUE(LEFT(C12,LEN(C12)-1))>=总览!$L$7),总览!$M$7,IF(AND(总览!$J$7<>"",B12*100+VALUE(LEFT(C12,LEN(C12)-1))>=总览!$J$7),总览!$K$7,IF(AND(总览!$H$7<>"",B12*100+VALUE(LEFT(C12,LEN(C12)-1))>=总览!$H$7),总览!$I$7,IF(AND(总览!$F$7<>"",B12*100+VALUE(LEFT(C12,LEN(C12)-1))>=总览!$F$7),总览!$G$7,IF(AND(总览!$D$7<>"",B12*100+VALUE(LEFT(C12,LEN(C12)-1))>=总览!$D$7),总览!$E$7,总览!$B$7))))),0) | F12: =ROUND(O11*总览!$B$14/12,0) | G12: =D12+E12+F12 | H12: =IF(OR(B12>2027,AND(B12=2027,VALUE(LEFT(C12,LEN(C12)-1))>=9)),IF(AND(总览!$L$10<>"",B12*100+VALUE(LEFT(C12,LEN(C12)-1))>=总览!$L$10),总览!$M$10,IF(AND(总览!$J$10<>"",B12*100+VALUE(LEFT(C12,LEN(C12)-1))>=总览!$J$10),总览!$K$10,IF(AND(总览!$H$10<>"",B12*100+VALUE(LEFT(C12,LEN(C12)-1))>=总览!$H$10),总览!$I$10,IF(AND(总览!$F$10<>"",B12*100+VALUE(LEFT(C12,LEN(C12)-1))>=总览!$F$10),总览!$G$10,IF(AND(总览!$D$10<>"",B12*100+VALUE(LEFT(C12,LEN(C12)-1))>=总览!$D$10),总览!$E$10,总览!$B$10))))),IF(AND(总览!$L$9<>"",B12*100+VALUE(LEFT(C12,LEN(C12)-1))>=总览!$L$9),总览!$M$9,IF(AND(总览!$J$9<>"",B12*100+VALUE(LEFT(C12,LEN(C12)-1))>=总览!$J$9),总览!$K$9,IF(AND(总览!$H$9<>"",B12*100+VALUE(LEFT(C12,LEN(C12)-1))>=总览!$H$9),总览!$I$9,IF(AND(总览!$F$9<>"",B12*100+VALUE(LEFT(C12,LEN(C12)-1))>=总览!$F$9),总览!$G$9,IF(AND(总览!$D$9<>"",B12*100+VALUE(LEFT(C12,LEN(C12)-1))>=总览!$D$9),总览!$E$9,总览!$B$9)))))) | I12: =IF(AND(总览!$L$11<>"",B12*100+VALUE(LEFT(C12,LEN(C12)-1))>=总览!$L$11),总览!$M$11,IF(AND(总览!$J$11<>"",B12*100+VALUE(LEFT(C12,LEN(C12)-1))>=总览!$J$11),总览!$K$11,IF(AND(总览!$H$11<>"",B12*100+VALUE(LEFT(C12,LEN(C12)-1))>=总览!$H$11),总览!$I$11,IF(AND(总览!$F$11<>"",B12*100+VALUE(LEFT(C12,LEN(C12)-1))>=总览!$F$11),总览!$G$11,IF(AND(总览!$D$11<>"",B12*100+VALUE(LEFT(C12,LEN(C12)-1))>=总览!$D$11),总览!$E$11,总览!$B$11))))) | J12: =IF(OR(B12>2027,AND(B12=2027,VALUE(LEFT(C12,LEN(C12)-1))>=9)),IF(AND(总览!$L$12<>"",B12*100+VALUE(LEFT(C12,LEN(C12)-1))>=总览!$L$12),总览!$M$12,IF(AND(总览!$J$12<>"",B12*100+VALUE(LEFT(C12,LEN(C12)-1))>=总览!$J$12),总览!$K$12,IF(AND(总览!$H$12<>"",B12*100+VALUE(LEFT(C12,LEN(C12)-1))>=总览!$H$12),总览!$I$12,IF(AND(总览!$F$12<>"",B12*100+VALUE(LEFT(C12,LEN(C12)-1))>=总览!$F$12),总览!$G$12,IF(AND(总览!$D$12<>"",B12*100+VALUE(LEFT(C12,LEN(C12)-1))>=总览!$D$12),总览!$E$12,总览!$B$12))))),0) | K12: =IF(AND(B12=2026,C12="5月"),120000,IF(AND(B12=2027,C12="9月"),30000,IF(C12="10月",IF(AND(总览!$L$13<>"",B12*100+VALUE(LEFT(C12,LEN(C12)-1))>=总览!$L$13),总览!$M$13,IF(AND(总览!$J$13<>"",B12*100+VALUE(LEFT(C12,LEN(C12)-1))>=总览!$J$13),总览!$K$13,IF(AND(总览!$H$13<>"",B12*100+VALUE(LEFT(C12,LEN(C12)-1))>=总览!$H$13),总览!$I$13,IF(AND(总览!$F$13<>"",B12*100+VALUE(LEFT(C12,LEN(C12)-1))>=总览!$F$13),总览!$G$13,IF(AND(总览!$D$13<>"",B12*100+VALUE(LEFT(C12,LEN(C12)-1))>=总览!$D$13),总览!$E$13,总览!$B$13))))),0))) | M12: =SUM(H12:K12) | N12: =G12-M12 | O12: =O11+N12
A13: 12 | B13: 2027 | C13: 1月 | D13: =IF(AND(总览!$L$6<>"",B13*100+VALUE(LEFT(C13,LEN(C13)-1))>=总览!$L$6),总览!$M$6,IF(AND(总览!$J$6<>"",B13*100+VALUE(LEFT(C13,LEN(C13)-1))>=总览!$J$6),总览!$K$6,IF(AND(总览!$H$6<>"",B13*100+VALUE(LEFT(C13,LEN(C13)-1))>=总览!$H$6),总览!$I$6,IF(AND(总览!$F$6<>"",B13*100+VALUE(LEFT(C13,LEN(C13)-1))>=总览!$F$6),总览!$G$6,IF(AND(总览!$D$6<>"",B13*100+VALUE(LEFT(C13,LEN(C13)-1))>=总览!$D$6),总览!$E$6,总览!$B$6))))) | E13: =IF(C13="12月",IF(AND(总览!$L$7<>"",B13*100+VALUE(LEFT(C13,LEN(C13)-1))>=总览!$L$7),总览!$M$7,IF(AND(总览!$J$7<>"",B13*100+VALUE(LEFT(C13,LEN(C13)-1))>=总览!$J$7),总览!$K$7,IF(AND(总览!$H$7<>"",B13*100+VALUE(LEFT(C13,LEN(C13)-1))>=总览!$H$7),总览!$I$7,IF(AND(总览!$F$7<>"",B13*100+VALUE(LEFT(C13,LEN(C13)-1))>=总览!$F$7),总览!$G$7,IF(AND(总览!$D$7<>"",B13*100+VALUE(LEFT(C13,LEN(C13)-1))>=总览!$D$7),总览!$E$7,总览!$B$7))))),0) | F13: =ROUND(O12*总览!$B$14/12,0) | G13: =D13+E13+F13 | H13: =IF(OR(B13>2027,AND(B13=2027,VALUE(LEFT(C13,LEN(C13)-1))>=9)),IF(AND(总览!$L$10<>"",B13*100+VALUE(LEFT(C13,LEN(C13)-1))>=总览!$L$10),总览!$M$10,IF(AND(总览!$J$10<>"",B13*100+VALUE(LEFT(C13,LEN(C13)-1))>=总览!$J$10),总览!$K$10,IF(AND(总览!$H$10<>"",B13*100+VALUE(LEFT(C13,LEN(C13)-1))>=总览!$H$10),总览!$I$10,IF(AND(总览!$F$10<>"",B13*100+VALUE(LEFT(C13,LEN(C13)-1))>=总览!$F$10),总览!$G$10,IF(AND(总览!$D$10<>"",B13*100+VALUE(LEFT(C13,LEN(C13)-1))>=总览!$D$10),总览!$E$10,总览!$B$10))))),IF(AND(总览!$L$9<>"",B13*100+VALUE(LEFT(C13,LEN(C13)-1))>=总览!$L$9),总览!$M$9,IF(AND(总览!$J$9<>"",B13*100+VALUE(LEFT(C13,LEN(C13)-1))>=总览!$J$9),总览!$K$9,IF(AND(总览!$H$9<>"",B13*100+VALUE(LEFT(C13,LEN(C13)-1))>=总览!$H$9),总览!$I$9,IF(AND(总览!$F$9<>"",B13*100+VALUE(LEFT(C13,LEN(C13)-1))>=总览!$F$9),总览!$G$9,IF(AND(总览!$D$9<>"",B13*100+VALUE(LEFT(C13,LEN(C13)-1))>=总览!$D$9),总览!$E$9,总览!$B$9)))))) | I13: =IF(AND(总览!$L$11<>"",B13*100+VALUE(LEFT(C13,LEN(C13)-1))>=总览!$L$11),总览!$M$11,IF(AND(总览!$J$11<>"",B13*100+VALUE(LEFT(C13,LEN(C13)-1))>=总览!$J$11),总览!$K$11,IF(AND(总览!$H$11<>"",B13*100+VALUE(LEFT(C13,LEN(C13)-1))>=总览!$H$11),总览!$I$11,IF(AND(总览!$F$11<>"",B13*100+VALUE(LEFT(C13,LEN(C13)-1))>=总览!$F$11),总览!$G$11,IF(AND(总览!$D$11<>"",B13*100+VALUE(LEFT(C13,LEN(C13)-1))>=总览!$D$11),总览!$E$11,总览!$B$11))))) | J13: =IF(OR(B13>2027,AND(B13=2027,VALUE(LEFT(C13,LEN(C13)-1))>=9)),IF(AND(总览!$L$12<>"",B13*100+VALUE(LEFT(C13,LEN(C13)-1))>=总览!$L$12),总览!$M$12,IF(AND(总览!$J$12<>"",B13*100+VALUE(LEFT(C13,LEN(C13)-1))>=总览!$J$12),总览!$K$12,IF(AND(总览!$H$12<>"",B13*100+VALUE(LEFT(C13,LEN(C13)-1))>=总览!$H$12),总览!$I$12,IF(AND(总览!$F$12<>"",B13*100+VALUE(LEFT(C13,LEN(C13)-1))>=总览!$F$12),总览!$G$12,IF(AND(总览!$D$12<>"",B13*100+VALUE(LEFT(C13,LEN(C13)-1))>=总览!$D$12),总览!$E$12,总览!$B$12))))),0) | K13: =IF(AND(B13=2026,C13="5月"),120000,IF(AND(B13=2027,C13="9月"),30000,IF(C13="10月",IF(AND(总览!$L$13<>"",B13*100+VALUE(LEFT(C13,LEN(C13)-1))>=总览!$L$13),总览!$M$13,IF(AND(总览!$J$13<>"",B13*100+VALUE(LEFT(C13,LEN(C13)-1))>=总览!$J$13),总览!$K$13,IF(AND(总览!$H$13<>"",B13*100+VALUE(LEFT(C13,LEN(C13)-1))>=总览!$H$13),总览!$I$13,IF(AND(总览!$F$13<>"",B13*100+VALUE(LEFT(C13,LEN(C13)-1))>=总览!$F$13),总览!$G$13,IF(AND(总览!$D$13<>"",B13*100+VALUE(LEFT(C13,LEN(C13)-1))>=总览!$D$13),总览!$E$13,总览!$B$13))))),0))) | M13: =SUM(H13:K13) | N13: =G13-M13 | O13: =O12+N13
A14: 13 | B14: 2027 | C14: 2月 | D14: =IF(AND(总览!$L$6<>"",B14*100+VALUE(LEFT(C14,LEN(C14)-1))>=总览!$L$6),总览!$M$6,IF(AND(总览!$J$6<>"",B14*100+VALUE(LEFT(C14,LEN(C14)-1))>=总览!$J$6),总览!$K$6,IF(AND(总览!$H$6<>"",B14*100+VALUE(LEFT(C14,LEN(C14)-1))>=总览!$H$6),总览!$I$6,IF(AND(总览!$F$6<>"",B14*100+VALUE(LEFT(C14,LEN(C14)-1))>=总览!$F$6),总览!$G$6,IF(AND(总览!$D$6<>"",B14*100+VALUE(LEFT(C14,LEN(C14)-1))>=总览!$D$6),总览!$E$6,总览!$B$6))))) | E14: =IF(C14="12月",IF(AND(总览!$L$7<>"",B14*100+VALUE(LEFT(C14,LEN(C14)-1))>=总览!$L$7),总览!$M$7,IF(AND(总览!$J$7<>"",B14*100+VALUE(LEFT(C14,LEN(C14)-1))>=总览!$J$7),总览!$K$7,IF(AND(总览!$H$7<>"",B14*100+VALUE(LEFT(C14,LEN(C14)-1))>=总览!$H$7),总览!$I$7,IF(AND(总览!$F$7<>"",B14*100+VALUE(LEFT(C14,LEN(C14)-1))>=总览!$F$7),总览!$G$7,IF(AND(总览!$D$7<>"",B14*100+VALUE(LEFT(C14,LEN(C14)-1))>=总览!$D$7),总览!$E$7,总览!$B$7))))),0) | F14: =ROUND(O13*总览!$B$14/12,0) | G14: =D14+E14+F14 | H14: =IF(OR(B14>2027,AND(B14=2027,VALUE(LEFT(C14,LEN(C14)-1))>=9)),IF(AND(总览!$L$10<>"",B14*100+VALUE(LEFT(C14,LEN(C14)-1))>=总览!$L$10),总览!$M$10,IF(AND(总览!$J$10<>"",B14*100+VALUE(LEFT(C14,LEN(C14)-1))>=总览!$J$10),总览!$K$10,IF(AND(总览!$H$10<>"",B14*100+VALUE(LEFT(C14,LEN(C14)-1))>=总览!$H$10),总览!$I$10,IF(AND(总览!$F$10<>"",B14*100+VALUE(LEFT(C14,LEN(C14)-1))>=总览!$F$10),总览!$G$10,IF(AND(总览!$D$10<>"",B14*100+VALUE(LEFT(C14,LEN(C14)-1))>=总览!$D$10),总览!$E$10,总览!$B$10))))),IF(AND(总览!$L$9<>"",B14*100+VALUE(LEFT(C14,LEN(C14)-1))>=总览!$L$9),总览!$M$9,IF(AND(总览!$J$9<>"",B14*100+VALUE(LEFT(C14,LEN(C14)-1))>=总览!$J$9),总览!$K$9,IF(AND(总览!$H$9<>"",B14*100+VALUE(LEFT(C14,LEN(C14)-1))>=总览!$H$9),总览!$I$9,IF(AND(总览!$F$9<>"",B14*100+VALUE(LEFT(C14,LEN(C14)-1))>=总览!$F$9),总览!$G$9,IF(AND(总览!$D$9<>"",B14*100+VALUE(LEFT(C14,LEN(C14)-1))>=总览!$D$9),总览!$E$9,总览!$B$9)))))) | I14: =IF(AND(总览!$L$11<>"",B14*100+VALUE(LEFT(C14,LEN(C14)-1))>=总览!$L$11),总览!$M$11,IF(AND(总览!$J$11<>"",B14*100+VALUE(LEFT(C14,LEN(C14)-1))>=总览!$J$11),总览!$K$11,IF(AND(总览!$H$11<>"",B14*100+VALUE(LEFT(C14,LEN(C14)-1))>=总览!$H$11),总览!$I$11,IF(AND(总览!$F$11<>"",B14*100+VALUE(LEFT(C14,LEN(C14)-1))>=总览!$F$11),总览!$G$11,IF(AND(总览!$D$11<>"",B14*100+VALUE(LEFT(C14,LEN(C14)-1))>=总览!$D$11),总览!$E$11,总览!$B$11))))) | J14: =IF(OR(B14>2027,AND(B14=2027,VALUE(LEFT(C14,LEN(C14)-1))>=9)),IF(AND(总览!$L$12<>"",B14*100+VALUE(LEFT(C14,LEN(C14)-1))>=总览!$L$12),总览!$M$12,IF(AND(总览!$J$12<>"",B14*100+VALUE(LEFT(C14,LEN(C14)-1))>=总览!$J$12),总览!$K$12,IF(AND(总览!$H$12<>"",B14*100+VALUE(LEFT(C14,LEN(C14)-1))>=总览!$H$12),总览!$I$12,IF(AND(总览!$F$12<>"",B14*100+VALUE(LEFT(C14,LEN(C14)-1))>=总览!$F$12),总览!$G$12,IF(AND(总览!$D$12<>"",B14*100+VALUE(LEFT(C14,LEN(C14)-1))>=总览!$D$12),总览!$E$12,总览!$B$12))))),0) | K14: =IF(AND(B14=2026,C14="5月"),120000,IF(AND(B14=2027,C14="9月"),30000,IF(C14="10月",IF(AND(总览!$L$13<>"",B14*100+VALUE(LEFT(C14,LEN(C14)-1))>=总览!$L$13),总览!$M$13,IF(AND(总览!$J$13<>"",B14*100+VALUE(LEFT(C14,LEN(C14)-1))>=总览!$J$13),总览!$K$13,IF(AND(总览!$H$13<>"",B14*100+VALUE(LEFT(C14,LEN(C14)-1))>=总览!$H$13),总览!$I$13,IF(AND(总览!$F$13<>"",B14*100+VALUE(LEFT(C14,LEN(C14)-1))>=总览!$F$13),总览!$G$13,IF(AND(总览!$D$13<>"",B14*100+VALUE(LEFT(C14,LEN(C14)-1))>=总览!$D$13),总览!$E$13,总览!$B$13))))),0))) | M14: =SUM(H14:K14) | N14: =G14-M14 | O14: =O13+N14
A15: 14 | B15: 2027 | C15: 3月 | D15: =IF(AND(总览!$L$6<>"",B15*100+VALUE(LEFT(C15,LEN(C15)-1))>=总览!$L$6),总览!$M$6,IF(AND(总览!$J$6<>"",B15*100+VALUE(LEFT(C15,LEN(C15)-1))>=总览!$J$6),总览!$K$6,IF(AND(总览!$H$6<>"",B15*100+VALUE(LEFT(C15,LEN(C15)-1))>=总览!$H$6),总览!$I$6,IF(AND(总览!$F$6<>"",B15*100+VALUE(LEFT(C15,LEN(C15)-1))>=总览!$F$6),总览!$G$6,IF(AND(总览!$D$6<>"",B15*100+VALUE(LEFT(C15,LEN(C15)-1))>=总览!$D$6),总览!$E$6,总览!$B$6))))) | E15: =IF(C15="12月",IF(AND(总览!$L$7<>"",B15*100+VALUE(LEFT(C15,LEN(C15)-1))>=总览!$L$7),总览!$M$7,IF(AND(总览!$J$7<>"",B15*100+VALUE(LEFT(C15,LEN(C15)-1))>=总览!$J$7),总览!$K$7,IF(AND(总览!$H$7<>"",B15*100+VALUE(LEFT(C15,LEN(C15)-1))>=总览!$H$7),总览!$I$7,IF(AND(总览!$F$7<>"",B15*100+VALUE(LEFT(C15,LEN(C15)-1))>=总览!$F$7),总览!$G$7,IF(AND(总览!$D$7<>"",B15*100+VALUE(LEFT(C15,LEN(C15)-1))>=总览!$D$7),总览!$E$7,总览!$B$7))))),0) | F15: =ROUND(O14*总览!$B$14/12,0) | G15: =D15+E15+F15 | H15: =IF(OR(B15>2027,AND(B15=2027,VALUE(LEFT(C15,LEN(C15)-1))>=9)),IF(AND(总览!$L$10<>"",B15*100+VALUE(LEFT(C15,LEN(C15)-1))>=总览!$L$10),总览!$M$10,IF(AND(总览!$J$10<>"",B15*100+VALUE(LEFT(C15,LEN(C15)-1))>=总览!$J$10),总览!$K$10,IF(AND(总览!$H$10<>"",B15*100+VALUE(LEFT(C15,LEN(C15)-1))>=总览!$H$10),总览!$I$10,IF(AND(总览!$F$10<>"",B15*100+VALUE(LEFT(C15,LEN(C15)-1))>=总览!$F$10),总览!$G$10,IF(AND(总览!$D$10<>"",B15*100+VALUE(LEFT(C15,LEN(C15)-1))>=总览!$D$10),总览!$E$10,总览!$B$10))))),IF(AND(总览!$L$9<>"",B15*100+VALUE(LEFT(C15,LEN(C15)-1))>=总览!$L$9),总览!$M$9,IF(AND(总览!$J$9<>"",B15*100+VALUE(LEFT(C15,LEN(C15)-1))>=总览!$J$9),总览!$K$9,IF(AND(总览!$H$9<>"",B15*100+VALUE(LEFT(C15,LEN(C15)-1))>=总览!$H$9),总览!$I$9,IF(AND(总览!$F$9<>"",B15*100+VALUE(LEFT(C15,LEN(C15)-1))>=总览!$F$9),总览!$G$9,IF(AND(总览!$D$9<>"",B15*100+VALUE(LEFT(C15,LEN(C15)-1))>=总览!$D$9),总览!$E$9,总览!$B$9)))))) | I15: =IF(AND(总览!$L$11<>"",B15*100+VALUE(LEFT(C15,LEN(C15)-1))>=总览!$L$11),总览!$M$11,IF(AND(总览!$J$11<>"",B15*100+VALUE(LEFT(C15,LEN(C15)-1))>=总览!$J$11),总览!$K$11,IF(AND(总览!$H$11<>"",B15*100+VALUE(LEFT(C15,LEN(C15)-1))>=总览!$H$11),总览!$I$11,IF(AND(总览!$F$11<>"",B15*100+VALUE(LEFT(C15,LEN(C15)-1))>=总览!$F$11),总览!$G$11,IF(AND(总览!$D$11<>"",B15*100+VALUE(LEFT(C15,LEN(C15)-1))>=总览!$D$11),总览!$E$11,总览!$B$11))))) | J15: =IF(OR(B15>2027,AND(B15=2027,VALUE(LEFT(C15,LEN(C15)-1))>=9)),IF(AND(总览!$L$12<>"",B15*100+VALUE(LEFT(C15,LEN(C15)-1))>=总览!$L$12),总览!$M$12,IF(AND(总览!$J$12<>"",B15*100+VALUE(LEFT(C15,LEN(C15)-1))>=总览!$J$12),总览!$K$12,IF(AND(总览!$H$12<>"",B15*100+VALUE(LEFT(C15,LEN(C15)-1))>=总览!$H$12),总览!$I$12,IF(AND(总览!$F$12<>"",B15*100+VALUE(LEFT(C15,LEN(C15)-1))>=总览!$F$12),总览!$G$12,IF(AND(总览!$D$12<>"",B15*100+VALUE(LEFT(C15,LEN(C15)-1))>=总览!$D$12),总览!$E$12,总览!$B$12))))),0) | K15: =IF(AND(B15=2026,C15="5月"),120000,IF(AND(B15=2027,C15="9月"),30000,IF(C15="10月",IF(AND(总览!$L$13<>"",B15*100+VALUE(LEFT(C15,LEN(C15)-1))>=总览!$L$13),总览!$M$13,IF(AND(总览!$J$13<>"",B15*100+VALUE(LEFT(C15,LEN(C15)-1))>=总览!$J$13),总览!$K$13,IF(AND(总览!$H$13<>"",B15*100+VALUE(LEFT(C15,LEN(C15)-1))>=总览!$H$13),总览!$I$13,IF(AND(总览!$F$13<>"",B15*100+VALUE(LEFT(C15,LEN(C15)-1))>=总览!$F$13),总览!$G$13,IF(AND(总览!$D$13<>"",B15*100+VALUE(LEFT(C15,LEN(C15)-1))>=总览!$D$13),总览!$E$13,总览!$B$13))))),0))) | M15: =SUM(H15:K15) | N15: =G15-M15 | O15: =O14+N15
A16: 15 | B16: 2027 | C16: 4月 | D16: =IF(AND(总览!$L$6<>"",B16*100+VALUE(LEFT(C16,LEN(C16)-1))>=总览!$L$6),总览!$M$6,IF(AND(总览!$J$6<>"",B16*100+VALUE(LEFT(C16,LEN(C16)-1))>=总览!$J$6),总览!$K$6,IF(AND(总览!$H$6<>"",B16*100+VALUE(LEFT(C16,LEN(C16)-1))>=总览!$H$6),总览!$I$6,IF(AND(总览!$F$6<>"",B16*100+VALUE(LEFT(C16,LEN(C16)-1))>=总览!$F$6),总览!$G$6,IF(AND(总览!$D$6<>"",B16*100+VALUE(LEFT(C16,LEN(C16)-1))>=总览!$D$6),总览!$E$6,总览!$B$6))))) | E16: =IF(C16="12月",IF(AND(总览!$L$7<>"",B16*100+VALUE(LEFT(C16,LEN(C16)-1))>=总览!$L$7),总览!$M$7,IF(AND(总览!$J$7<>"",B16*100+VALUE(LEFT(C16,LEN(C16)-1))>=总览!$J$7),总览!$K$7,IF(AND(总览!$H$7<>"",B16*100+VALUE(LEFT(C16,LEN(C16)-1))>=总览!$H$7),总览!$I$7,IF(AND(总览!$F$7<>"",B16*100+VALUE(LEFT(C16,LEN(C16)-1))>=总览!$F$7),总览!$G$7,IF(AND(总览!$D$7<>"",B16*100+VALUE(LEFT(C16,LEN(C16)-1))>=总览!$D$7),总览!$E$7,总览!$B$7))))),0) | F16: =ROUND(O15*总览!$B$14/12,0) | G16: =D16+E16+F16 | H16: =IF(OR(B16>2027,AND(B16=2027,VALUE(LEFT(C16,LEN(C16)-1))>=9)),IF(AND(总览!$L$10<>"",B16*100+VALUE(LEFT(C16,LEN(C16)-1))>=总览!$L$10),总览!$M$10,IF(AND(总览!$J$10<>"",B16*100+VALUE(LEFT(C16,LEN(C16)-1))>=总览!$J$10),总览!$K$10,IF(AND(总览!$H$10<>"",B16*100+VALUE(LEFT(C16,LEN(C16)-1))>=总览!$H$10),总览!$I$10,IF(AND(总览!$F$10<>"",B16*100+VALUE(LEFT(C16,LEN(C16)-1))>=总览!$F$10),总览!$G$10,IF(AND(总览!$D$10<>"",B16*100+VALUE(LEFT(C16,LEN(C16)-1))>=总览!$D$10),总览!$E$10,总览!$B$10))))),IF(AND(总览!$L$9<>"",B16*100+VALUE(LEFT(C16,LEN(C16)-1))>=总览!$L$9),总览!$M$9,IF(AND(总览!$J$9<>"",B16*100+VALUE(LEFT(C16,LEN(C16)-1))>=总览!$J$9),总览!$K$9,IF(AND(总览!$H$9<>"",B16*100+VALUE(LEFT(C16,LEN(C16)-1))>=总览!$H$9),总览!$I$9,IF(AND(总览!$F$9<>"",B16*100+VALUE(LEFT(C16,LEN(C16)-1))>=总览!$F$9),总览!$G$9,IF(AND(总览!$D$9<>"",B16*100+VALUE(LEFT(C16,LEN(C16)-1))>=总览!$D$9),总览!$E$9,总览!$B$9)))))) | I16: =IF(AND(总览!$L$11<>"",B16*100+VALUE(LEFT(C16,LEN(C16)-1))>=总览!$L$11),总览!$M$11,IF(AND(总览!$J$11<>"",B16*100+VALUE(LEFT(C16,LEN(C16)-1))>=总览!$J$11),总览!$K$11,IF(AND(总览!$H$11<>"",B16*100+VALUE(LEFT(C16,LEN(C16)-1))>=总览!$H$11),总览!$I$11,IF(AND(总览!$F$11<>"",B16*100+VALUE(LEFT(C16,LEN(C16)-1))>=总览!$F$11),总览!$G$11,IF(AND(总览!$D$11<>"",B16*100+VALUE(LEFT(C16,LEN(C16)-1))>=总览!$D$11),总览!$E$11,总览!$B$11))))) | J16: =IF(OR(B16>2027,AND(B16=2027,VALUE(LEFT(C16,LEN(C16)-1))>=9)),IF(AND(总览!$L$12<>"",B16*100+VALUE(LEFT(C16,LEN(C16)-1))>=总览!$L$12),总览!$M$12,IF(AND(总览!$J$12<>"",B16*100+VALUE(LEFT(C16,LEN(C16)-1))>=总览!$J$12),总览!$K$12,IF(AND(总览!$H$12<>"",B16*100+VALUE(LEFT(C16,LEN(C16)-1))>=总览!$H$12),总览!$I$12,IF(AND(总览!$F$12<>"",B16*100+VALUE(LEFT(C16,LEN(C16)-1))>=总览!$F$12),总览!$G$12,IF(AND(总览!$D$12<>"",B16*100+VALUE(LEFT(C16,LEN(C16)-1))>=总览!$D$12),总览!$E$12,总览!$B$12))))),0) | K16: =IF(AND(B16=2026,C16="5月"),120000,IF(AND(B16=2027,C16="9月"),30000,IF(C16="10月",IF(AND(总览!$L$13<>"",B16*100+VALUE(LEFT(C16,LEN(C16)-1))>=总览!$L$13),总览!$M$13,IF(AND(总览!$J$13<>"",B16*100+VALUE(LEFT(C16,LEN(C16)-1))>=总览!$J$13),总览!$K$13,IF(AND(总览!$H$13<>"",B16*100+VALUE(LEFT(C16,LEN(C16)-1))>=总览!$H$13),总览!$I$13,IF(AND(总览!$F$13<>"",B16*100+VALUE(LEFT(C16,LEN(C16)-1))>=总览!$F$13),总览!$G$13,IF(AND(总览!$D$13<>"",B16*100+VALUE(LEFT(C16,LEN(C16)-1))>=总览!$D$13),总览!$E$13,总览!$B$13))))),0))) | M16: =SUM(H16:K16) | N16: =G16-M16 | O16: =O15+N16
A17: 16 | B17: 2027 | C17: 5月 | D17: =IF(AND(总览!$L$6<>"",B17*100+VALUE(LEFT(C17,LEN(C17)-1))>=总览!$L$6),总览!$M$6,IF(AND(总览!$J$6<>"",B17*100+VALUE(LEFT(C17,LEN(C17)-1))>=总览!$J$6),总览!$K$6,IF(AND(总览!$H$6<>"",B17*100+VALUE(LEFT(C17,LEN(C17)-1))>=总览!$H$6),总览!$I$6,IF(AND(总览!$F$6<>"",B17*100+VALUE(LEFT(C17,LEN(C17)-1))>=总览!$F$6),总览!$G$6,IF(AND(总览!$D$6<>"",B17*100+VALUE(LEFT(C17,LEN(C17)-1))>=总览!$D$6),总览!$E$6,总览!$B$6))))) | E17: =IF(C17="12月",IF(AND(总览!$L$7<>"",B17*100+VALUE(LEFT(C17,LEN(C17)-1))>=总览!$L$7),总览!$M$7,IF(AND(总览!$J$7<>"",B17*100+VALUE(LEFT(C17,LEN(C17)-1))>=总览!$J$7),总览!$K$7,IF(AND(总览!$H$7<>"",B17*100+VALUE(LEFT(C17,LEN(C17)-1))>=总览!$H$7),总览!$I$7,IF(AND(总览!$F$7<>"",B17*100+VALUE(LEFT(C17,LEN(C17)-1))>=总览!$F$7),总览!$G$7,IF(AND(总览!$D$7<>"",B17*100+VALUE(LEFT(C17,LEN(C17)-1))>=总览!$D$7),总览!$E$7,总览!$B$7))))),0) | F17: =ROUND(O16*总览!$B$14/12,0) | G17: =D17+E17+F17 | H17: =IF(OR(B17>2027,AND(B17=2027,VALUE(LEFT(C17,LEN(C17)-1))>=9)),IF(AND(总览!$L$10<>"",B17*100+VALUE(LEFT(C17,LEN(C17)-1))>=总览!$L$10),总览!$M$10,IF(AND(总览!$J$10<>"",B17*100+VALUE(LEFT(C17,LEN(C17)-1))>=总览!$J$10),总览!$K$10,IF(AND(总览!$H$10<>"",B17*100+VALUE(LEFT(C17,LEN(C17)-1))>=总览!$H$10),总览!$I$10,IF(AND(总览!$F$10<>"",B17*100+VALUE(LEFT(C17,LEN(C17)-1))>=总览!$F$10),总览!$G$10,IF(AND(总览!$D$10<>"",B17*100+VALUE(LEFT(C17,LEN(C17)-1))>=总览!$D$10),总览!$E$10,总览!$B$10))))),IF(AND(总览!$L$9<>"",B17*100+VALUE(LEFT(C17,LEN(C17)-1))>=总览!$L$9),总览!$M$9,IF(AND(总览!$J$9<>"",B17*100+VALUE(LEFT(C17,LEN(C17)-1))>=总览!$J$9),总览!$K$9,IF(AND(总览!$H$9<>"",B17*100+VALUE(LEFT(C17,LEN(C17)-1))>=总览!$H$9),总览!$I$9,IF(AND(总览!$F$9<>"",B17*100+VALUE(LEFT(C17,LEN(C17)-1))>=总览!$F$9),总览!$G$9,IF(AND(总览!$D$9<>"",B17*100+VALUE(LEFT(C17,LEN(C17)-1))>=总览!$D$9),总览!$E$9,总览!$B$9)))))) | I17: =IF(AND(总览!$L$11<>"",B17*100+VALUE(LEFT(C17,LEN(C17)-1))>=总览!$L$11),总览!$M$11,IF(AND(总览!$J$11<>"",B17*100+VALUE(LEFT(C17,LEN(C17)-1))>=总览!$J$11),总览!$K$11,IF(AND(总览!$H$11<>"",B17*100+VALUE(LEFT(C17,LEN(C17)-1))>=总览!$H$11),总览!$I$11,IF(AND(总览!$F$11<>"",B17*100+VALUE(LEFT(C17,LEN(C17)-1))>=总览!$F$11),总览!$G$11,IF(AND(总览!$D$11<>"",B17*100+VALUE(LEFT(C17,LEN(C17)-1))>=总览!$D$11),总览!$E$11,总览!$B$11))))) | J17: =IF(OR(B17>2027,AND(B17=2027,VALUE(LEFT(C17,LEN(C17)-1))>=9)),IF(AND(总览!$L$12<>"",B17*100+VALUE(LEFT(C17,LEN(C17)-1))>=总览!$L$12),总览!$M$12,IF(AND(总览!$J$12<>"",B17*100+VALUE(LEFT(C17,LEN(C17)-1))>=总览!$J$12),总览!$K$12,IF(AND(总览!$H$12<>"",B17*100+VALUE(LEFT(C17,LEN(C17)-1))>=总览!$H$12),总览!$I$12,IF(AND(总览!$F$12<>"",B17*100+VALUE(LEFT(C17,LEN(C17)-1))>=总览!$F$12),总览!$G$12,IF(AND(总览!$D$12<>"",B17*100+VALUE(LEFT(C17,LEN(C17)-1))>=总览!$D$12),总览!$E$12,总览!$B$12))))),0) | K17: =IF(AND(B17=2026,C17="5月"),120000,IF(AND(B17=2027,C17="9月"),30000,IF(C17="10月",IF(AND(总览!$L$13<>"",B17*100+VALUE(LEFT(C17,LEN(C17)-1))>=总览!$L$13),总览!$M$13,IF(AND(总览!$J$13<>"",B17*100+VALUE(LEFT(C17,LEN(C17)-1))>=总览!$J$13),总览!$K$13,IF(AND(总览!$H$13<>"",B17*100+VALUE(LEFT(C17,LEN(C17)-1))>=总览!$H$13),总览!$I$13,IF(AND(总览!$F$13<>"",B17*100+VALUE(LEFT(C17,LEN(C17)-1))>=总览!$F$13),总览!$G$13,IF(AND(总览!$D$13<>"",B17*100+VALUE(LEFT(C17,LEN(C17)-1))>=总览!$D$13),总览!$E$13,总览!$B$13))))),0))) | M17: =SUM(H17:K17) | N17: =G17-M17 | O17: =O16+N17
A18: 17 | B18: 2027 | C18: 6月 | D18: =IF(AND(总览!$L$6<>"",B18*100+VALUE(LEFT(C18,LEN(C18)-1))>=总览!$L$6),总览!$M$6,IF(AND(总览!$J$6<>"",B18*100+VALUE(LEFT(C18,LEN(C18)-1))>=总览!$J$6),总览!$K$6,IF(AND(总览!$H$6<>"",B18*100+VALUE(LEFT(C18,LEN(C18)-1))>=总览!$H$6),总览!$I$6,IF(AND(总览!$F$6<>"",B18*100+VALUE(LEFT(C18,LEN(C18)-1))>=总览!$F$6),总览!$G$6,IF(AND(总览!$D$6<>"",B18*100+VALUE(LEFT(C18,LEN(C18)-1))>=总览!$D$6),总览!$E$6,总览!$B$6))))) | E18: =IF(C18="12月",IF(AND(总览!$L$7<>"",B18*100+VALUE(LEFT(C18,LEN(C18)-1))>=总览!$L$7),总览!$M$7,IF(AND(总览!$J$7<>"",B18*100+VALUE(LEFT(C18,LEN(C18)-1))>=总览!$J$7),总览!$K$7,IF(AND(总览!$H$7<>"",B18*100+VALUE(LEFT(C18,LEN(C18)-1))>=总览!$H$7),总览!$I$7,IF(AND(总览!$F$7<>"",B18*100+VALUE(LEFT(C18,LEN(C18)-1))>=总览!$F$7),总览!$G$7,IF(AND(总览!$D$7<>"",B18*100+VALUE(LEFT(C18,LEN(C18)-1))>=总览!$D$7),总览!$E$7,总览!$B$7))))),0) | F18: =ROUND(O17*总览!$B$14/12,0) | G18: =D18+E18+F18 | H18: =IF(OR(B18>2027,AND(B18=2027,VALUE(LEFT(C18,LEN(C18)-1))>=9)),IF(AND(总览!$L$10<>"",B18*100+VALUE(LEFT(C18,LEN(C18)-1))>=总览!$L$10),总览!$M$10,IF(AND(总览!$J$10<>"",B18*100+VALUE(LEFT(C18,LEN(C18)-1))>=总览!$J$10),总览!$K$10,IF(AND(总览!$H$10<>"",B18*100+VALUE(LEFT(C18,LEN(C18)-1))>=总览!$H$10),总览!$I$10,IF(AND(总览!$F$10<>"",B18*100+VALUE(LEFT(C18,LEN(C18)-1))>=总览!$F$10),总览!$G$10,IF(AND(总览!$D$10<>"",B18*100+VALUE(LEFT(C18,LEN(C18)-1))>=总览!$D$10),总览!$E$10,总览!$B$10))))),IF(AND(总览!$L$9<>"",B18*100+VALUE(LEFT(C18,LEN(C18)-1))>=总览!$L$9),总览!$M$9,IF(AND(总览!$J$9<>"",B18*100+VALUE(LEFT(C18,LEN(C18)-1))>=总览!$J$9),总览!$K$9,IF(AND(总览!$H$9<>"",B18*100+VALUE(LEFT(C18,LEN(C18)-1))>=总览!$H$9),总览!$I$9,IF(AND(总览!$F$9<>"",B18*100+VALUE(LEFT(C18,LEN(C18)-1))>=总览!$F$9),总览!$G$9,IF(AND(总览!$D$9<>"",B18*100+VALUE(LEFT(C18,LEN(C18)-1))>=总览!$D$9),总览!$E$9,总览!$B$9)))))) | I18: =IF(AND(总览!$L$11<>"",B18*100+VALUE(LEFT(C18,LEN(C18)-1))>=总览!$L$11),总览!$M$11,IF(AND(总览!$J$11<>"",B18*100+VALUE(LEFT(C18,LEN(C18)-1))>=总览!$J$11),总览!$K$11,IF(AND(总览!$H$11<>"",B18*100+VALUE(LEFT(C18,LEN(C18)-1))>=总览!$H$11),总览!$I$11,IF(AND(总览!$F$11<>"",B18*100+VALUE(LEFT(C18,LEN(C18)-1))>=总览!$F$11),总览!$G$11,IF(AND(总览!$D$11<>"",B18*100+VALUE(LEFT(C18,LEN(C18)-1))>=总览!$D$11),总览!$E$11,总览!$B$11))))) | J18: =IF(OR(B18>2027,AND(B18=2027,VALUE(LEFT(C18,LEN(C18)-1))>=9)),IF(AND(总览!$L$12<>"",B18*100+VALUE(LEFT(C18,LEN(C18)-1))>=总览!$L$12),总览!$M$12,IF(AND(总览!$J$12<>"",B18*100+VALUE(LEFT(C18,LEN(C18)-1))>=总览!$J$12),总览!$K$12,IF(AND(总览!$H$12<>"",B18*100+VALUE(LEFT(C18,LEN(C18)-1))>=总览!$H$12),总览!$I$12,IF(AND(总览!$F$12<>"",B18*100+VALUE(LEFT(C18,LEN(C18)-1))>=总览!$F$12),总览!$G$12,IF(AND(总览!$D$12<>"",B18*100+VALUE(LEFT(C18,LEN(C18)-1))>=总览!$D$12),总览!$E$12,总览!$B$12))))),0) | K18: =IF(AND(B18=2026,C18="5月"),120000,IF(AND(B18=2027,C18="9月"),30000,IF(C18="10月",IF(AND(总览!$L$13<>"",B18*100+VALUE(LEFT(C18,LEN(C18)-1))>=总览!$L$13),总览!$M$13,IF(AND(总览!$J$13<>"",B18*100+VALUE(LEFT(C18,LEN(C18)-1))>=总览!$J$13),总览!$K$13,IF(AND(总览!$H$13<>"",B18*100+VALUE(LEFT(C18,LEN(C18)-1))>=总览!$H$13),总览!$I$13,IF(AND(总览!$F$13<>"",B18*100+VALUE(LEFT(C18,LEN(C18)-1))>=总览!$F$13),总览!$G$13,IF(AND(总览!$D$13<>"",B18*100+VALUE(LEFT(C18,LEN(C18)-1))>=总览!$D$13),总览!$E$13,总览!$B$13))))),0))) | M18: =SUM(H18:K18) | N18: =G18-M18 | O18: =O17+N18
A19: 18 | B19: 2027 | C19: 7月 | D19: =IF(AND(总览!$L$6<>"",B19*100+VALUE(LEFT(C19,LEN(C19)-1))>=总览!$L$6),总览!$M$6,IF(AND(总览!$J$6<>"",B19*100+VALUE(LEFT(C19,LEN(C19)-1))>=总览!$J$6),总览!$K$6,IF(AND(总览!$H$6<>"",B19*100+VALUE(LEFT(C19,LEN(C19)-1))>=总览!$H$6),总览!$I$6,IF(AND(总览!$F$6<>"",B19*100+VALUE(LEFT(C19,LEN(C19)-1))>=总览!$F$6),总览!$G$6,IF(AND(总览!$D$6<>"",B19*100+VALUE(LEFT(C19,LEN(C19)-1))>=总览!$D$6),总览!$E$6,总览!$B$6))))) | E19: =IF(C19="12月",IF(AND(总览!$L$7<>"",B19*100+VALUE(LEFT(C19,LEN(C19)-1))>=总览!$L$7),总览!$M$7,IF(AND(总览!$J$7<>"",B19*100+VALUE(LEFT(C19,LEN(C19)-1))>=总览!$J$7),总览!$K$7,IF(AND(总览!$H$7<>"",B19*100+VALUE(LEFT(C19,LEN(C19)-1))>=总览!$H$7),总览!$I$7,IF(AND(总览!$F$7<>"",B19*100+VALUE(LEFT(C19,LEN(C19)-1))>=总览!$F$7),总览!$G$7,IF(AND(总览!$D$7<>"",B19*100+VALUE(LEFT(C19,LEN(C19)-1))>=总览!$D$7),总览!$E$7,总览!$B$7))))),0) | F19: =ROUND(O18*总览!$B$14/12,0) | G19: =D19+E19+F19 | H19: =IF(OR(B19>2027,AND(B19=2027,VALUE(LEFT(C19,LEN(C19)-1))>=9)),IF(AND(总览!$L$10<>"",B19*100+VALUE(LEFT(C19,LEN(C19)-1))>=总览!$L$10),总览!$M$10,IF(AND(总览!$J$10<>"",B19*100+VALUE(LEFT(C19,LEN(C19)-1))>=总览!$J$10),总览!$K$10,IF(AND(总览!$H$10<>"",B19*100+VALUE(LEFT(C19,LEN(C19)-1))>=总览!$H$10),总览!$I$10,IF(AND(总览!$F$10<>"",B19*100+VALUE(LEFT(C19,LEN(C19)-1))>=总览!$F$10),总览!$G$10,IF(AND(总览!$D$10<>"",B19*100+VALUE(LEFT(C19,LEN(C19)-1))>=总览!$D$10),总览!$E$10,总览!$B$10))))),IF(AND(总览!$L$9<>"",B19*100+VALUE(LEFT(C19,LEN(C19)-1))>=总览!$L$9),总览!$M$9,IF(AND(总览!$J$9<>"",B19*100+VALUE(LEFT(C19,LEN(C19)-1))>=总览!$J$9),总览!$K$9,IF(AND(总览!$H$9<>"",B19*100+VALUE(LEFT(C19,LEN(C19)-1))>=总览!$H$9),总览!$I$9,IF(AND(总览!$F$9<>"",B19*100+VALUE(LEFT(C19,LEN(C19)-1))>=总览!$F$9),总览!$G$9,IF(AND(总览!$D$9<>"",B19*100+VALUE(LEFT(C19,LEN(C19)-1))>=总览!$D$9),总览!$E$9,总览!$B$9)))))) | I19: =IF(AND(总览!$L$11<>"",B19*100+VALUE(LEFT(C19,LEN(C19)-1))>=总览!$L$11),总览!$M$11,IF(AND(总览!$J$11<>"",B19*100+VALUE(LEFT(C19,LEN(C19)-1))>=总览!$J$11),总览!$K$11,IF(AND(总览!$H$11<>"",B19*100+VALUE(LEFT(C19,LEN(C19)-1))>=总览!$H$11),总览!$I$11,IF(AND(总览!$F$11<>"",B19*100+VALUE(LEFT(C19,LEN(C19)-1))>=总览!$F$11),总览!$G$11,IF(AND(总览!$D$11<>"",B19*100+VALUE(LEFT(C19,LEN(C19)-1))>=总览!$D$11),总览!$E$11,总览!$B$11))))) | J19: =IF(OR(B19>2027,AND(B19=2027,VALUE(LEFT(C19,LEN(C19)-1))>=9)),IF(AND(总览!$L$12<>"",B19*100+VALUE(LEFT(C19,LEN(C19)-1))>=总览!$L$12),总览!$M$12,IF(AND(总览!$J$12<>"",B19*100+VALUE(LEFT(C19,LEN(C19)-1))>=总览!$J$12),总览!$K$12,IF(AND(总览!$H$12<>"",B19*100+VALUE(LEFT(C19,LEN(C19)-1))>=总览!$H$12),总览!$I$12,IF(AND(总览!$F$12<>"",B19*100+VALUE(LEFT(C19,LEN(C19)-1))>=总览!$F$12),总览!$G$12,IF(AND(总览!$D$12<>"",B19*100+VALUE(LEFT(C19,LEN(C19)-1))>=总览!$D$12),总览!$E$12,总览!$B$12))))),0) | K19: =IF(AND(B19=2026,C19="5月"),120000,IF(AND(B19=2027,C19="9月"),30000,IF(C19="10月",IF(AND(总览!$L$13<>"",B19*100+VALUE(LEFT(C19,LEN(C19)-1))>=总览!$L$13),总览!$M$13,IF(AND(总览!$J$13<>"",B19*100+VALUE(LEFT(C19,LEN(C19)-1))>=总览!$J$13),总览!$K$13,IF(AND(总览!$H$13<>"",B19*100+VALUE(LEFT(C19,LEN(C19)-1))>=总览!$H$13),总览!$I$13,IF(AND(总览!$F$13<>"",B19*100+VALUE(LEFT(C19,LEN(C19)-1))>=总览!$F$13),总览!$G$13,IF(AND(总览!$D$13<>"",B19*100+VALUE(LEFT(C19,LEN(C19)-1))>=总览!$D$13),总览!$E$13,总览!$B$13))))),0))) | M19: =SUM(H19:K19) | N19: =G19-M19 | O19: =O18+N19
A20: 19 | B20: 2027 | C20: 8月 | D20: =IF(AND(总览!$L$6<>"",B20*100+VALUE(LEFT(C20,LEN(C20)-1))>=总览!$L$6),总览!$M$6,IF(AND(总览!$J$6<>"",B20*100+VALUE(LEFT(C20,LEN(C20)-1))>=总览!$J$6),总览!$K$6,IF(AND(总览!$H$6<>"",B20*100+VALUE(LEFT(C20,LEN(C20)-1))>=总览!$H$6),总览!$I$6,IF(AND(总览!$F$6<>"",B20*100+VALUE(LEFT(C20,LEN(C20)-1))>=总览!$F$6),总览!$G$6,IF(AND(总览!$D$6<>"",B20*100+VALUE(LEFT(C20,LEN(C20)-1))>=总览!$D$6),总览!$E$6,总览!$B$6))))) | E20: =IF(C20="12月",IF(AND(总览!$L$7<>"",B20*100+VALUE(LEFT(C20,LEN(C20)-1))>=总览!$L$7),总览!$M$7,IF(AND(总览!$J$7<>"",B20*100+VALUE(LEFT(C20,LEN(C20)-1))>=总览!$J$7),总览!$K$7,IF(AND(总览!$H$7<>"",B20*100+VALUE(LEFT(C20,LEN(C20)-1))>=总览!$H$7),总览!$I$7,IF(AND(总览!$F$7<>"",B20*100+VALUE(LEFT(C20,LEN(C20)-1))>=总览!$F$7),总览!$G$7,IF(AND(总览!$D$7<>"",B20*100+VALUE(LEFT(C20,LEN(C20)-1))>=总览!$D$7),总览!$E$7,总览!$B$7))))),0) | F20: =ROUND(O19*总览!$B$14/12,0) | G20: =D20+E20+F20 | H20: =IF(OR(B20>2027,AND(B20=2027,VALUE(LEFT(C20,LEN(C20)-1))>=9)),IF(AND(总览!$L$10<>"",B20*100+VALUE(LEFT(C20,LEN(C20)-1))>=总览!$L$10),总览!$M$10,IF(AND(总览!$J$10<>"",B20*100+VALUE(LEFT(C20,LEN(C20)-1))>=总览!$J$10),总览!$K$10,IF(AND(总览!$H$10<>"",B20*100+VALUE(LEFT(C20,LEN(C20)-1))>=总览!$H$10),总览!$I$10,IF(AND(总览!$F$10<>"",B20*100+VALUE(LEFT(C20,LEN(C20)-1))>=总览!$F$10),总览!$G$10,IF(AND(总览!$D$10<>"",B20*100+VALUE(LEFT(C20,LEN(C20)-1))>=总览!$D$10),总览!$E$10,总览!$B$10))))),IF(AND(总览!$L$9<>"",B20*100+VALUE(LEFT(C20,LEN(C20)-1))>=总览!$L$9),总览!$M$9,IF(AND(总览!$J$9<>"",B20*100+VALUE(LEFT(C20,LEN(C20)-1))>=总览!$J$9),总览!$K$9,IF(AND(总览!$H$9<>"",B20*100+VALUE(LEFT(C20,LEN(C20)-1))>=总览!$H$9),总览!$I$9,IF(AND(总览!$F$9<>"",B20*100+VALUE(LEFT(C20,LEN(C20)-1))>=总览!$F$9),总览!$G$9,IF(AND(总览!$D$9<>"",B20*100+VALUE(LEFT(C20,LEN(C20)-1))>=总览!$D$9),总览!$E$9,总览!$B$9)))))) | I20: =IF(AND(总览!$L$11<>"",B20*100+VALUE(LEFT(C20,LEN(C20)-1))>=总览!$L$11),总览!$M$11,IF(AND(总览!$J$11<>"",B20*100+VALUE(LEFT(C20,LEN(C20)-1))>=总览!$J$11),总览!$K$11,IF(AND(总览!$H$11<>"",B20*100+VALUE(LEFT(C20,LEN(C20)-1))>=总览!$H$11),总览!$I$11,IF(AND(总览!$F$11<>"",B20*100+VALUE(LEFT(C20,LEN(C20)-1))>=总览!$F$11),总览!$G$11,IF(AND(总览!$D$11<>"",B20*100+VALUE(LEFT(C20,LEN(C20)-1))>=总览!$D$11),总览!$E$11,总览!$B$11))))) | J20: =IF(OR(B20>2027,AND(B20=2027,VALUE(LEFT(C20,LEN(C20)-1))>=9)),IF(AND(总览!$L$12<>"",B20*100+VALUE(LEFT(C20,LEN(C20)-1))>=总览!$L$12),总览!$M$12,IF(AND(总览!$J$12<>"",B20*100+VALUE(LEFT(C20,LEN(C20)-1))>=总览!$J$12),总览!$K$12,IF(AND(总览!$H$12<>"",B20*100+VALUE(LEFT(C20,LEN(C20)-1))>=总览!$H$12),总览!$I$12,IF(AND(总览!$F$12<>"",B20*100+VALUE(LEFT(C20,LEN(C20)-1))>=总览!$F$12),总览!$G$12,IF(AND(总览!$D$12<>"",B20*100+VALUE(LEFT(C20,LEN(C20)-1))>=总览!$D$12),总览!$E$12,总览!$B$12))))),0) | K20: =IF(AND(B20=2026,C20="5月"),120000,IF(AND(B20=2027,C20="9月"),30000,IF(C20="10月",IF(AND(总览!$L$13<>"",B20*100+VALUE(LEFT(C20,LEN(C20)-1))>=总览!$L$13),总览!$M$13,IF(AND(总览!$J$13<>"",B20*100+VALUE(LEFT(C20,LEN(C20)-1))>=总览!$J$13),总览!$K$13,IF(AND(总览!$H$13<>"",B20*100+VALUE(LEFT(C20,LEN(C20)-1))>=总览!$H$13),总览!$I$13,IF(AND(总览!$F$13<>"",B20*100+VALUE(LEFT(C20,LEN(C20)-1))>=总览!$F$13),总览!$G$13,IF(AND(总览!$D$13<>"",B20*100+VALUE(LEFT(C20,LEN(C20)-1))>=总览!$D$13),总览!$E$13,总览!$B$13))))),0))) | M20: =SUM(H20:K20) | N20: =G20-M20 | O20: =O19+N20
A21: 20 | B21: 2027 | C21: 9月 | D21: =IF(AND(总览!$L$6<>"",B21*100+VALUE(LEFT(C21,LEN(C21)-1))>=总览!$L$6),总览!$M$6,IF(AND(总览!$J$6<>"",B21*100+VALUE(LEFT(C21,LEN(C21)-1))>=总览!$J$6),总览!$K$6,IF(AND(总览!$H$6<>"",B21*100+VALUE(LEFT(C21,LEN(C21)-1))>=总览!$H$6),总览!$I$6,IF(AND(总览!$F$6<>"",B21*100+VALUE(LEFT(C21,LEN(C21)-1))>=总览!$F$6),总览!$G$6,IF(AND(总览!$D$6<>"",B21*100+VALUE(LEFT(C21,LEN(C21)-1))>=总览!$D$6),总览!$E$6,总览!$B$6))))) | E21: =IF(C21="12月",IF(AND(总览!$L$7<>"",B21*100+VALUE(LEFT(C21,LEN(C21)-1))>=总览!$L$7),总览!$M$7,IF(AND(总览!$J$7<>"",B21*100+VALUE(LEFT(C21,LEN(C21)-1))>=总览!$J$7),总览!$K$7,IF(AND(总览!$H$7<>"",B21*100+VALUE(LEFT(C21,LEN(C21)-1))>=总览!$H$7),总览!$I$7,IF(AND(总览!$F$7<>"",B21*100+VALUE(LEFT(C21,LEN(C21)-1))>=总览!$F$7),总览!$G$7,IF(AND(总览!$D$7<>"",B21*100+VALUE(LEFT(C21,LEN(C21)-1))>=总览!$D$7),总览!$E$7,总览!$B$7))))),0) | F21: =ROUND(O20*总览!$B$14/12,0) | G21: =D21+E21+F21 | H21: =IF(OR(B21>2027,AND(B21=2027,VALUE(LEFT(C21,LEN(C21)-1))>=9)),IF(AND(总览!$L$10<>"",B21*100+VALUE(LEFT(C21,LEN(C21)-1))>=总览!$L$10),总览!$M$10,IF(AND(总览!$J$10<>"",B21*100+VALUE(LEFT(C21,LEN(C21)-1))>=总览!$J$10),总览!$K$10,IF(AND(总览!$H$10<>"",B21*100+VALUE(LEFT(C21,LEN(C21)-1))>=总览!$H$10),总览!$I$10,IF(AND(总览!$F$10<>"",B21*100+VALUE(LEFT(C21,LEN(C21)-1))>=总览!$F$10),总览!$G$10,IF(AND(总览!$D$10<>"",B21*100+VALUE(LEFT(C21,LEN(C21)-1))>=总览!$D$10),总览!$E$10,总览!$B$10))))),IF(AND(总览!$L$9<>"",B21*100+VALUE(LEFT(C21,LEN(C21)-1))>=总览!$L$9),总览!$M$9,IF(AND(总览!$J$9<>"",B21*100+VALUE(LEFT(C21,LEN(C21)-1))>=总览!$J$9),总览!$K$9,IF(AND(总览!$H$9<>"",B21*100+VALUE(LEFT(C21,LEN(C21)-1))>=总览!$H$9),总览!$I$9,IF(AND(总览!$F$9<>"",B21*100+VALUE(LEFT(C21,LEN(C21)-1))>=总览!$F$9),总览!$G$9,IF(AND(总览!$D$9<>"",B21*100+VALUE(LEFT(C21,LEN(C21)-1))>=总览!$D$9),总览!$E$9,总览!$B$9)))))) | I21: =IF(AND(总览!$L$11<>"",B21*100+VALUE(LEFT(C21,LEN(C21)-1))>=总览!$L$11),总览!$M$11,IF(AND(总览!$J$11<>"",B21*100+VALUE(LEFT(C21,LEN(C21)-1))>=总览!$J$11),总览!$K$11,IF(AND(总览!$H$11<>"",B21*100+VALUE(LEFT(C21,LEN(C21)-1))>=总览!$H$11),总览!$I$11,IF(AND(总览!$F$11<>"",B21*100+VALUE(LEFT(C21,LEN(C21)-1))>=总览!$F$11),总览!$G$11,IF(AND(总览!$D$11<>"",B21*100+VALUE(LEFT(C21,LEN(C21)-1))>=总览!$D$11),总览!$E$11,总览!$B$11))))) | J21: =IF(OR(B21>2027,AND(B21=2027,VALUE(LEFT(C21,LEN(C21)-1))>=9)),IF(AND(总览!$L$12<>"",B21*100+VALUE(LEFT(C21,LEN(C21)-1))>=总览!$L$12),总览!$M$12,IF(AND(总览!$J$12<>"",B21*100+VALUE(LEFT(C21,LEN(C21)-1))>=总览!$J$12),总览!$K$12,IF(AND(总览!$H$12<>"",B21*100+VALUE(LEFT(C21,LEN(C21)-1))>=总览!$H$12),总览!$I$12,IF(AND(总览!$F$12<>"",B21*100+VALUE(LEFT(C21,LEN(C21)-1))>=总览!$F$12),总览!$G$12,IF(AND(总览!$D$12<>"",B21*100+VALUE(LEFT(C21,LEN(C21)-1))>=总览!$D$12),总览!$E$12,总览!$B$12))))),0) | K21: =IF(AND(B21=2026,C21="5月"),120000,IF(AND(B21=2027,C21="9月"),30000,IF(C21="10月",IF(AND(总览!$L$13<>"",B21*100+VALUE(LEFT(C21,LEN(C21)-1))>=总览!$L$13),总览!$M$13,IF(AND(总览!$J$13<>"",B21*100+VALUE(LEFT(C21,LEN(C21)-1))>=总览!$J$13),总览!$K$13,IF(AND(总览!$H$13<>"",B21*100+VALUE(LEFT(C21,LEN(C21)-1))>=总览!$H$13),总览!$I$13,IF(AND(总览!$F$13<>"",B21*100+VALUE(LEFT(C21,LEN(C21)-1))>=总览!$F$13),总览!$G$13,IF(AND(总览!$D$13<>"",B21*100+VALUE(LEFT(C21,LEN(C21)-1))>=总览!$D$13),总览!$E$13,总览!$B$13))))),0))) | L21: 孕产费用 | M21: =SUM(H21:K21) | N21: =G21-M21 | O21: =O20+N21
A22: 21 | B22: 2027 | C22: 10月 | D22: =IF(AND(总览!$L$6<>"",B22*100+VALUE(LEFT(C22,LEN(C22)-1))>=总览!$L$6),总览!$M$6,IF(AND(总览!$J$6<>"",B22*100+VALUE(LEFT(C22,LEN(C22)-1))>=总览!$J$6),总览!$K$6,IF(AND(总览!$H$6<>"",B22*100+VALUE(LEFT(C22,LEN(C22)-1))>=总览!$H$6),总览!$I$6,IF(AND(总览!$F$6<>"",B22*100+VALUE(LEFT(C22,LEN(C22)-1))>=总览!$F$6),总览!$G$6,IF(AND(总览!$D$6<>"",B22*100+VALUE(LEFT(C22,LEN(C22)-1))>=总览!$D$6),总览!$E$6,总览!$B$6))))) | E22: =IF(C22="12月",IF(AND(总览!$L$7<>"",B22*100+VALUE(LEFT(C22,LEN(C22)-1))>=总览!$L$7),总览!$M$7,IF(AND(总览!$J$7<>"",B22*100+VALUE(LEFT(C22,LEN(C22)-1))>=总览!$J$7),总览!$K$7,IF(AND(总览!$H$7<>"",B22*100+VALUE(LEFT(C22,LEN(C22)-1))>=总览!$H$7),总览!$I$7,IF(AND(总览!$F$7<>"",B22*100+VALUE(LEFT(C22,LEN(C22)-1))>=总览!$F$7),总览!$G$7,IF(AND(总览!$D$7<>"",B22*100+VALUE(LEFT(C22,LEN(C22)-1))>=总览!$D$7),总览!$E$7,总览!$B$7))))),0) | F22: =ROUND(O21*总览!$B$14/12,0) | G22: =D22+E22+F22 | H22: =IF(OR(B22>2027,AND(B22=2027,VALUE(LEFT(C22,LEN(C22)-1))>=9)),IF(AND(总览!$L$10<>"",B22*100+VALUE(LEFT(C22,LEN(C22)-1))>=总览!$L$10),总览!$M$10,IF(AND(总览!$J$10<>"",B22*100+VALUE(LEFT(C22,LEN(C22)-1))>=总览!$J$10),总览!$K$10,IF(AND(总览!$H$10<>"",B22*100+VALUE(LEFT(C22,LEN(C22)-1))>=总览!$H$10),总览!$I$10,IF(AND(总览!$F$10<>"",B22*100+VALUE(LEFT(C22,LEN(C22)-1))>=总览!$F$10),总览!$G$10,IF(AND(总览!$D$10<>"",B22*100+VALUE(LEFT(C22,LEN(C22)-1))>=总览!$D$10),总览!$E$10,总览!$B$10))))),IF(AND(总览!$L$9<>"",B22*100+VALUE(LEFT(C22,LEN(C22)-1))>=总览!$L$9),总览!$M$9,IF(AND(总览!$J$9<>"",B22*100+VALUE(LEFT(C22,LEN(C22)-1))>=总览!$J$9),总览!$K$9,IF(AND(总览!$H$9<>"",B22*100+VALUE(LEFT(C22,LEN(C22)-1))>=总览!$H$9),总览!$I$9,IF(AND(总览!$F$9<>"",B22*100+VALUE(LEFT(C22,LEN(C22)-1))>=总览!$F$9),总览!$G$9,IF(AND(总览!$D$9<>"",B22*100+VALUE(LEFT(C22,LEN(C22)-1))>=总览!$D$9),总览!$E$9,总览!$B$9)))))) | I22: =IF(AND(总览!$L$11<>"",B22*100+VALUE(LEFT(C22,LEN(C22)-1))>=总览!$L$11),总览!$M$11,IF(AND(总览!$J$11<>"",B22*100+VALUE(LEFT(C22,LEN(C22)-1))>=总览!$J$11),总览!$K$11,IF(AND(总览!$H$11<>"",B22*100+VALUE(LEFT(C22,LEN(C22)-1))>=总览!$H$11),总览!$I$11,IF(AND(总览!$F$11<>"",B22*100+VALUE(LEFT(C22,LEN(C22)-1))>=总览!$F$11),总览!$G$11,IF(AND(总览!$D$11<>"",B22*100+VALUE(LEFT(C22,LEN(C22)-1))>=总览!$D$11),总览!$E$11,总览!$B$11))))) | J22: =IF(OR(B22>2027,AND(B22=2027,VALUE(LEFT(C22,LEN(C22)-1))>=9)),IF(AND(总览!$L$12<>"",B22*100+VALUE(LEFT(C22,LEN(C22)-1))>=总览!$L$12),总览!$M$12,IF(AND(总览!$J$12<>"",B22*100+VALUE(LEFT(C22,LEN(C22)-1))>=总览!$J$12),总览!$K$12,IF(AND(总览!$H$12<>"",B22*100+VALUE(LEFT(C22,LEN(C22)-1))>=总览!$H$12),总览!$I$12,IF(AND(总览!$F$12<>"",B22*100+VALUE(LEFT(C22,LEN(C22)-1))>=总览!$F$12),总览!$G$12,IF(AND(总览!$D$12<>"",B22*100+VALUE(LEFT(C22,LEN(C22)-1))>=总览!$D$12),总览!$E$12,总览!$B$12))))),0) | K22: =IF(AND(B22=2026,C22="5月"),120000,IF(AND(B22=2027,C22="9月"),30000,IF(C22="10月",IF(AND(总览!$L$13<>"",B22*100+VALUE(LEFT(C22,LEN(C22)-1))>=总览!$L$13),总览!$M$13,IF(AND(总览!$J$13<>"",B22*100+VALUE(LEFT(C22,LEN(C22)-1))>=总览!$J$13),总览!$K$13,IF(AND(总览!$H$13<>"",B22*100+VALUE(LEFT(C22,LEN(C22)-1))>=总览!$H$13),总览!$I$13,IF(AND(总览!$F$13<>"",B22*100+VALUE(LEFT(C22,LEN(C22)-1))>=总览!$F$13),总览!$G$13,IF(AND(总览!$D$13<>"",B22*100+VALUE(LEFT(C22,LEN(C22)-1))>=总览!$D$13),总览!$E$13,总览!$B$13))))),0))) | L22: 年度旅游 | M22: =SUM(H22:K22) | N22: =G22-M22 | O22: =O21+N22
A23: 22 | B23: 2027 | C23: 11月 | D23: =IF(AND(总览!$L$6<>"",B23*100+VALUE(LEFT(C23,LEN(C23)-1))>=总览!$L$6),总览!$M$6,IF(AND(总览!$J$6<>"",B23*100+VALUE(LEFT(C23,LEN(C23)-1))>=总览!$J$6),总览!$K$6,IF(AND(总览!$H$6<>"",B23*100+VALUE(LEFT(C23,LEN(C23)-1))>=总览!$H$6),总览!$I$6,IF(AND(总览!$F$6<>"",B23*100+VALUE(LEFT(C23,LEN(C23)-1))>=总览!$F$6),总览!$G$6,IF(AND(总览!$D$6<>"",B23*100+VALUE(LEFT(C23,LEN(C23)-1))>=总览!$D$6),总览!$E$6,总览!$B$6))))) | E23: =IF(C23="12月",IF(AND(总览!$L$7<>"",B23*100+VALUE(LEFT(C23,LEN(C23)-1))>=总览!$L$7),总览!$M$7,IF(AND(总览!$J$7<>"",B23*100+VALUE(LEFT(C23,LEN(C23)-1))>=总览!$J$7),总览!$K$7,IF(AND(总览!$H$7<>"",B23*100+VALUE(LEFT(C23,LEN(C23)-1))>=总览!$H$7),总览!$I$7,IF(AND(总览!$F$7<>"",B23*100+VALUE(LEFT(C23,LEN(C23)-1))>=总览!$F$7),总览!$G$7,IF(AND(总览!$D$7<>"",B23*100+VALUE(LEFT(C23,LEN(C23)-1))>=总览!$D$7),总览!$E$7,总览!$B$7))))),0) | F23: =ROUND(O22*总览!$B$14/12,0) | G23: =D23+E23+F23 | H23: =IF(OR(B23>2027,AND(B23=2027,VALUE(LEFT(C23,LEN(C23)-1))>=9)),IF(AND(总览!$L$10<>"",B23*100+VALUE(LEFT(C23,LEN(C23)-1))>=总览!$L$10),总览!$M$10,IF(AND(总览!$J$10<>"",B23*100+VALUE(LEFT(C23,LEN(C23)-1))>=总览!$J$10),总览!$K$10,IF(AND(总览!$H$10<>"",B23*100+VALUE(LEFT(C23,LEN(C23)-1))>=总览!$H$10),总览!$I$10,IF(AND(总览!$F$10<>"",B23*100+VALUE(LEFT(C23,LEN(C23)-1))>=总览!$F$10),总览!$G$10,IF(AND(总览!$D$10<>"",B23*100+VALUE(LEFT(C23,LEN(C23)-1))>=总览!$D$10),总览!$E$10,总览!$B$10))))),IF(AND(总览!$L$9<>"",B23*100+VALUE(LEFT(C23,LEN(C23)-1))>=总览!$L$9),总览!$M$9,IF(AND(总览!$J$9<>"",B23*100+VALUE(LEFT(C23,LEN(C23)-1))>=总览!$J$9),总览!$K$9,IF(AND(总览!$H$9<>"",B23*100+VALUE(LEFT(C23,LEN(C23)-1))>=总览!$H$9),总览!$I$9,IF(AND(总览!$F$9<>"",B23*100+VALUE(LEFT(C23,LEN(C23)-1))>=总览!$F$9),总览!$G$9,IF(AND(总览!$D$9<>"",B23*100+VALUE(LEFT(C23,LEN(C23)-1))>=总览!$D$9),总览!$E$9,总览!$B$9)))))) | I23: =IF(AND(总览!$L$11<>"",B23*100+VALUE(LEFT(C23,LEN(C23)-1))>=总览!$L$11),总览!$M$11,IF(AND(总览!$J$11<>"",B23*100+VALUE(LEFT(C23,LEN(C23)-1))>=总览!$J$11),总览!$K$11,IF(AND(总览!$H$11<>"",B23*100+VALUE(LEFT(C23,LEN(C23)-1))>=总览!$H$11),总览!$I$11,IF(AND(总览!$F$11<>"",B23*100+VALUE(LEFT(C23,LEN(C23)-1))>=总览!$F$11),总览!$G$11,IF(AND(总览!$D$11<>"",B23*100+VALUE(LEFT(C23,LEN(C23)-1))>=总览!$D$11),总览!$E$11,总览!$B$11))))) | J23: =IF(OR(B23>2027,AND(B23=2027,VALUE(LEFT(C23,LEN(C23)-1))>=9)),IF(AND(总览!$L$12<>"",B23*100+VALUE(LEFT(C23,LEN(C23)-1))>=总览!$L$12),总览!$M$12,IF(AND(总览!$J$12<>"",B23*100+VALUE(LEFT(C23,LEN(C23)-1))>=总览!$J$12),总览!$K$12,IF(AND(总览!$H$12<>"",B23*100+VALUE(LEFT(C23,LEN(C23)-1))>=总览!$H$12),总览!$I$12,IF(AND(总览!$F$12<>"",B23*100+VALUE(LEFT(C23,LEN(C23)-1))>=总览!$F$12),总览!$G$12,IF(AND(总览!$D$12<>"",B23*100+VALUE(LEFT(C23,LEN(C23)-1))>=总览!$D$12),总览!$E$12,总览!$B$12))))),0) | K23: =IF(AND(B23=2026,C23="5月"),120000,IF(AND(B23=2027,C23="9月"),30000,IF(C23="10月",IF(AND(总览!$L$13<>"",B23*100+VALUE(LEFT(C23,LEN(C23)-1))>=总览!$L$13),总览!$M$13,IF(AND(总览!$J$13<>"",B23*100+VALUE(LEFT(C23,LEN(C23)-1))>=总览!$J$13),总览!$K$13,IF(AND(总览!$H$13<>"",B23*100+VALUE(LEFT(C23,LEN(C23)-1))>=总览!$H$13),总览!$I$13,IF(AND(总览!$F$13<>"",B23*100+VALUE(LEFT(C23,LEN(C23)-1))>=总览!$F$13),总览!$G$13,IF(AND(总览!$D$13<>"",B23*100+VALUE(LEFT(C23,LEN(C23)-1))>=总览!$D$13),总览!$E$13,总览!$B$13))))),0))) | M23: =SUM(H23:K23) | N23: =G23-M23 | O23: =O22+N23
A24: 23 | B24: 2027 | C24: 12月 | D24: =IF(AND(总览!$L$6<>"",B24*100+VALUE(LEFT(C24,LEN(C24)-1))>=总览!$L$6),总览!$M$6,IF(AND(总览!$J$6<>"",B24*100+VALUE(LEFT(C24,LEN(C24)-1))>=总览!$J$6),总览!$K$6,IF(AND(总览!$H$6<>"",B24*100+VALUE(LEFT(C24,LEN(C24)-1))>=总览!$H$6),总览!$I$6,IF(AND(总览!$F$6<>"",B24*100+VALUE(LEFT(C24,LEN(C24)-1))>=总览!$F$6),总览!$G$6,IF(AND(总览!$D$6<>"",B24*100+VALUE(LEFT(C24,LEN(C24)-1))>=总览!$D$6),总览!$E$6,总览!$B$6))))) | E24: =IF(C24="12月",IF(AND(总览!$L$7<>"",B24*100+VALUE(LEFT(C24,LEN(C24)-1))>=总览!$L$7),总览!$M$7,IF(AND(总览!$J$7<>"",B24*100+VALUE(LEFT(C24,LEN(C24)-1))>=总览!$J$7),总览!$K$7,IF(AND(总览!$H$7<>"",B24*100+VALUE(LEFT(C24,LEN(C24)-1))>=总览!$H$7),总览!$I$7,IF(AND(总览!$F$7<>"",B24*100+VALUE(LEFT(C24,LEN(C24)-1))>=总览!$F$7),总览!$G$7,IF(AND(总览!$D$7<>"",B24*100+VALUE(LEFT(C24,LEN(C24)-1))>=总览!$D$7),总览!$E$7,总览!$B$7))))),0) | F24: =ROUND(O23*总览!$B$14/12,0) | G24: =D24+E24+F24 | H24: =IF(OR(B24>2027,AND(B24=2027,VALUE(LEFT(C24,LEN(C24)-1))>=9)),IF(AND(总览!$L$10<>"",B24*100+VALUE(LEFT(C24,LEN(C24)-1))>=总览!$L$10),总览!$M$10,IF(AND(总览!$J$10<>"",B24*100+VALUE(LEFT(C24,LEN(C24)-1))>=总览!$J$10),总览!$K$10,IF(AND(总览!$H$10<>"",B24*100+VALUE(LEFT(C24,LEN(C24)-1))>=总览!$H$10),总览!$I$10,IF(AND(总览!$F$10<>"",B24*100+VALUE(LEFT(C24,LEN(C24)-1))>=总览!$F$10),总览!$G$10,IF(AND(总览!$D$10<>"",B24*100+VALUE(LEFT(C24,LEN(C24)-1))>=总览!$D$10),总览!$E$10,总览!$B$10))))),IF(AND(总览!$L$9<>"",B24*100+VALUE(LEFT(C24,LEN(C24)-1))>=总览!$L$9),总览!$M$9,IF(AND(总览!$J$9<>"",B24*100+VALUE(LEFT(C24,LEN(C24)-1))>=总览!$J$9),总览!$K$9,IF(AND(总览!$H$9<>"",B24*100+VALUE(LEFT(C24,LEN(C24)-1))>=总览!$H$9),总览!$I$9,IF(AND(总览!$F$9<>"",B24*100+VALUE(LEFT(C24,LEN(C24)-1))>=总览!$F$9),总览!$G$9,IF(AND(总览!$D$9<>"",B24*100+VALUE(LEFT(C24,LEN(C24)-1))>=总览!$D$9),总览!$E$9,总览!$B$9)))))) | I24: =IF(AND(总览!$L$11<>"",B24*100+VALUE(LEFT(C24,LEN(C24)-1))>=总览!$L$11),总览!$M$11,IF(AND(总览!$J$11<>"",B24*100+VALUE(LEFT(C24,LEN(C24)-1))>=总览!$J$11),总览!$K$11,IF(AND(总览!$H$11<>"",B24*100+VALUE(LEFT(C24,LEN(C24)-1))>=总览!$H$11),总览!$I$11,IF(AND(总览!$F$11<>"",B24*100+VALUE(LEFT(C24,LEN(C24)-1))>=总览!$F$11),总览!$G$11,IF(AND(总览!$D$11<>"",B24*100+VALUE(LEFT(C24,LEN(C24)-1))>=总览!$D$11),总览!$E$11,总览!$B$11))))) | J24: =IF(OR(B24>2027,AND(B24=2027,VALUE(LEFT(C24,LEN(C24)-1))>=9)),IF(AND(总览!$L$12<>"",B24*100+VALUE(LEFT(C24,LEN(C24)-1))>=总览!$L$12),总览!$M$12,IF(AND(总览!$J$12<>"",B24*100+VALUE(LEFT(C24,LEN(C24)-1))>=总览!$J$12),总览!$K$12,IF(AND(总览!$H$12<>"",B24*100+VALUE(LEFT(C24,LEN(C24)-1))>=总览!$H$12),总览!$I$12,IF(AND(总览!$F$12<>"",B24*100+VALUE(LEFT(C24,LEN(C24)-1))>=总览!$F$12),总览!$G$12,IF(AND(总览!$D$12<>"",B24*100+VALUE(LEFT(C24,LEN(C24)-1))>=总览!$D$12),总览!$E$12,总览!$B$12))))),0) | K24: =IF(AND(B24=2026,C24="5月"),120000,IF(AND(B24=2027,C24="9月"),30000,IF(C24="10月",IF(AND(总览!$L$13<>"",B24*100+VALUE(LEFT(C24,LEN(C24)-1))>=总览!$L$13),总览!$M$13,IF(AND(总览!$J$13<>"",B24*100+VALUE(LEFT(C24,LEN(C24)-1))>=总览!$J$13),总览!$K$13,IF(AND(总览!$H$13<>"",B24*100+VALUE(LEFT(C24,LEN(C24)-1))>=总览!$H$13),总览!$I$13,IF(AND(总览!$F$13<>"",B24*100+VALUE(LEFT(C24,LEN(C24)-1))>=总览!$F$13),总览!$G$13,IF(AND(总览!$D$13<>"",B24*100+VALUE(LEFT(C24,LEN(C24)-1))>=总览!$D$13),总览!$E$13,总览!$B$13))))),0))) | M24: =SUM(H24:K24) | N24: =G24-M24 | O24: =O23+N24
A25: 24 | B25: 2028 | C25: 1月 | D25: =IF(AND(总览!$L$6<>"",B25*100+VALUE(LEFT(C25,LEN(C25)-1))>=总览!$L$6),总览!$M$6,IF(AND(总览!$J$6<>"",B25*100+VALUE(LEFT(C25,LEN(C25)-1))>=总览!$J$6),总览!$K$6,IF(AND(总览!$H$6<>"",B25*100+VALUE(LEFT(C25,LEN(C25)-1))>=总览!$H$6),总览!$I$6,IF(AND(总览!$F$6<>"",B25*100+VALUE(LEFT(C25,LEN(C25)-1))>=总览!$F$6),总览!$G$6,IF(AND(总览!$D$6<>"",B25*100+VALUE(LEFT(C25,LEN(C25)-1))>=总览!$D$6),总览!$E$6,总览!$B$6))))) | E25: =IF(C25="12月",IF(AND(总览!$L$7<>"",B25*100+VALUE(LEFT(C25,LEN(C25)-1))>=总览!$L$7),总览!$M$7,IF(AND(总览!$J$7<>"",B25*100+VALUE(LEFT(C25,LEN(C25)-1))>=总览!$J$7),总览!$K$7,IF(AND(总览!$H$7<>"",B25*100+VALUE(LEFT(C25,LEN(C25)-1))>=总览!$H$7),总览!$I$7,IF(AND(总览!$F$7<>"",B25*100+VALUE(LEFT(C25,LEN(C25)-1))>=总览!$F$7),总览!$G$7,IF(AND(总览!$D$7<>"",B25*100+VALUE(LEFT(C25,LEN(C25)-1))>=总览!$D$7),总览!$E$7,总览!$B$7))))),0) | F25: =ROUND(O24*总览!$B$14/12,0) | G25: =D25+E25+F25 | H25: =IF(OR(B25>2027,AND(B25=2027,VALUE(LEFT(C25,LEN(C25)-1))>=9)),IF(AND(总览!$L$10<>"",B25*100+VALUE(LEFT(C25,LEN(C25)-1))>=总览!$L$10),总览!$M$10,IF(AND(总览!$J$10<>"",B25*100+VALUE(LEFT(C25,LEN(C25)-1))>=总览!$J$10),总览!$K$10,IF(AND(总览!$H$10<>"",B25*100+VALUE(LEFT(C25,LEN(C25)-1))>=总览!$H$10),总览!$I$10,IF(AND(总览!$F$10<>"",B25*100+VALUE(LEFT(C25,LEN(C25)-1))>=总览!$F$10),总览!$G$10,IF(AND(总览!$D$10<>"",B25*100+VALUE(LEFT(C25,LEN(C25)-1))>=总览!$D$10),总览!$E$10,总览!$B$10))))),IF(AND(总览!$L$9<>"",B25*100+VALUE(LEFT(C25,LEN(C25)-1))>=总览!$L$9),总览!$M$9,IF(AND(总览!$J$9<>"",B25*100+VALUE(LEFT(C25,LEN(C25)-1))>=总览!$J$9),总览!$K$9,IF(AND(总览!$H$9<>"",B25*100+VALUE(LEFT(C25,LEN(C25)-1))>=总览!$H$9),总览!$I$9,IF(AND(总览!$F$9<>"",B25*100+VALUE(LEFT(C25,LEN(C25)-1))>=总览!$F$9),总览!$G$9,IF(AND(总览!$D$9<>"",B25*100+VALUE(LEFT(C25,LEN(C25)-1))>=总览!$D$9),总览!$E$9,总览!$B$9)))))) | I25: =IF(AND(总览!$L$11<>"",B25*100+VALUE(LEFT(C25,LEN(C25)-1))>=总览!$L$11),总览!$M$11,IF(AND(总览!$J$11<>"",B25*100+VALUE(LEFT(C25,LEN(C25)-1))>=总览!$J$11),总览!$K$11,IF(AND(总览!$H$11<>"",B25*100+VALUE(LEFT(C25,LEN(C25)-1))>=总览!$H$11),总览!$I$11,IF(AND(总览!$F$11<>"",B25*100+VALUE(LEFT(C25,LEN(C25)-1))>=总览!$F$11),总览!$G$11,IF(AND(总览!$D$11<>"",B25*100+VALUE(LEFT(C25,LEN(C25)-1))>=总览!$D$11),总览!$E$11,总览!$B$11))))) | J25: =IF(OR(B25>2027,AND(B25=2027,VALUE(LEFT(C25,LEN(C25)-1))>=9)),IF(AND(总览!$L$12<>"",B25*100+VALUE(LEFT(C25,LEN(C25)-1))>=总览!$L$12),总览!$M$12,IF(AND(总览!$J$12<>"",B25*100+VALUE(LEFT(C25,LEN(C25)-1))>=总览!$J$12),总览!$K$12,IF(AND(总览!$H$12<>"",B25*100+VALUE(LEFT(C25,LEN(C25)-1))>=总览!$H$12),总览!$I$12,IF(AND(总览!$F$12<>"",B25*100+VALUE(LEFT(C25,LEN(C25)-1))>=总览!$F$12),总览!$G$12,IF(AND(总览!$D$12<>"",B25*100+VALUE(LEFT(C25,LEN(C25)-1))>=总览!$D$12),总览!$E$12,总览!$B$12))))),0) | K25: =IF(AND(B25=2026,C25="5月"),120000,IF(AND(B25=2027,C25="9月"),30000,IF(C25="10月",IF(AND(总览!$L$13<>"",B25*100+VALUE(LEFT(C25,LEN(C25)-1))>=总览!$L$13),总览!$M$13,IF(AND(总览!$J$13<>"",B25*100+VALUE(LEFT(C25,LEN(C25)-1))>=总览!$J$13),总览!$K$13,IF(AND(总览!$H$13<>"",B25*100+VALUE(LEFT(C25,LEN(C25)-1))>=总览!$H$13),总览!$I$13,IF(AND(总览!$F$13<>"",B25*100+VALUE(LEFT(C25,LEN(C25)-1))>=总览!$F$13),总览!$G$13,IF(AND(总览!$D$13<>"",B25*100+VALUE(LEFT(C25,LEN(C25)-1))>=总览!$D$13),总览!$E$13,总览!$B$13))))),0))) | M25: =SUM(H25:K25) | N25: =G25-M25 | O25: =O24+N25
A26: 25 | B26: 2028 | C26: 2月 | D26: =IF(AND(总览!$L$6<>"",B26*100+VALUE(LEFT(C26,LEN(C26)-1))>=总览!$L$6),总览!$M$6,IF(AND(总览!$J$6<>"",B26*100+VALUE(LEFT(C26,LEN(C26)-1))>=总览!$J$6),总览!$K$6,IF(AND(总览!$H$6<>"",B26*100+VALUE(LEFT(C26,LEN(C26)-1))>=总览!$H$6),总览!$I$6,IF(AND(总览!$F$6<>"",B26*100+VALUE(LEFT(C26,LEN(C26)-1))>=总览!$F$6),总览!$G$6,IF(AND(总览!$D$6<>"",B26*100+VALUE(LEFT(C26,LEN(C26)-1))>=总览!$D$6),总览!$E$6,总览!$B$6))))) | E26: =IF(C26="12月",IF(AND(总览!$L$7<>"",B26*100+VALUE(LEFT(C26,LEN(C26)-1))>=总览!$L$7),总览!$M$7,IF(AND(总览!$J$7<>"",B26*100+VALUE(LEFT(C26,LEN(C26)-1))>=总览!$J$7),总览!$K$7,IF(AND(总览!$H$7<>"",B26*100+VALUE(LEFT(C26,LEN(C26)-1))>=总览!$H$7),总览!$I$7,IF(AND(总览!$F$7<>"",B26*100+VALUE(LEFT(C26,LEN(C26)-1))>=总览!$F$7),总览!$G$7,IF(AND(总览!$D$7<>"",B26*100+VALUE(LEFT(C26,LEN(C26)-1))>=总览!$D$7),总览!$E$7,总览!$B$7))))),0) | F26: =ROUND(O25*总览!$B$14/12,0) | G26: =D26+E26+F26 | H26: =IF(OR(B26>2027,AND(B26=2027,VALUE(LEFT(C26,LEN(C26)-1))>=9)),IF(AND(总览!$L$10<>"",B26*100+VALUE(LEFT(C26,LEN(C26)-1))>=总览!$L$10),总览!$M$10,IF(AND(总览!$J$10<>"",B26*100+VALUE(LEFT(C26,LEN(C26)-1))>=总览!$J$10),总览!$K$10,IF(AND(总览!$H$10<>"",B26*100+VALUE(LEFT(C26,LEN(C26)-1))>=总览!$H$10),总览!$I$10,IF(AND(总览!$F$10<>"",B26*100+VALUE(LEFT(C26,LEN(C26)-1))>=总览!$F$10),总览!$G$10,IF(AND(总览!$D$10<>"",B26*100+VALUE(LEFT(C26,LEN(C26)-1))>=总览!$D$10),总览!$E$10,总览!$B$10))))),IF(AND(总览!$L$9<>"",B26*100+VALUE(LEFT(C26,LEN(C26)-1))>=总览!$L$9),总览!$M$9,IF(AND(总览!$J$9<>"",B26*100+VALUE(LEFT(C26,LEN(C26)-1))>=总览!$J$9),总览!$K$9,IF(AND(总览!$H$9<>"",B26*100+VALUE(LEFT(C26,LEN(C26)-1))>=总览!$H$9),总览!$I$9,IF(AND(总览!$F$9<>"",B26*100+VALUE(LEFT(C26,LEN(C26)-1))>=总览!$F$9),总览!$G$9,IF(AND(总览!$D$9<>"",B26*100+VALUE(LEFT(C26,LEN(C26)-1))>=总览!$D$9),总览!$E$9,总览!$B$9)))))) | I26: =IF(AND(总览!$L$11<>"",B26*100+VALUE(LEFT(C26,LEN(C26)-1))>=总览!$L$11),总览!$M$11,IF(AND(总览!$J$11<>"",B26*100+VALUE(LEFT(C26,LEN(C26)-1))>=总览!$J$11),总览!$K$11,IF(AND(总览!$H$11<>"",B26*100+VALUE(LEFT(C26,LEN(C26)-1))>=总览!$H$11),总览!$I$11,IF(AND(总览!$F$11<>"",B26*100+VALUE(LEFT(C26,LEN(C26)-1))>=总览!$F$11),总览!$G$11,IF(AND(总览!$D$11<>"",B26*100+VALUE(LEFT(C26,LEN(C26)-1))>=总览!$D$11),总览!$E$11,总览!$B$11))))) | J26: =IF(OR(B26>2027,AND(B26=2027,VALUE(LEFT(C26,LEN(C26)-1))>=9)),IF(AND(总览!$L$12<>"",B26*100+VALUE(LEFT(C26,LEN(C26)-1))>=总览!$L$12),总览!$M$12,IF(AND(总览!$J$12<>"",B26*100+VALUE(LEFT(C26,LEN(C26)-1))>=总览!$J$12),总览!$K$12,IF(AND(总览!$H$12<>"",B26*100+VALUE(LEFT(C26,LEN(C26)-1))>=总览!$H$12),总览!$I$12,IF(AND(总览!$F$12<>"",B26*100+VALUE(LEFT(C26,LEN(C26)-1))>=总览!$F$12),总览!$G$12,IF(AND(总览!$D$12<>"",B26*100+VALUE(LEFT(C26,LEN(C26)-1))>=总览!$D$12),总览!$E$12,总览!$B$12))))),0) | K26: =IF(AND(B26=2026,C26="5月"),120000,IF(AND(B26=2027,C26="9月"),30000,IF(C26="10月",IF(AND(总览!$L$13<>"",B26*100+VALUE(LEFT(C26,LEN(C26)-1))>=总览!$L$13),总览!$M$13,IF(AND(总览!$J$13<>"",B26*100+VALUE(LEFT(C26,LEN(C26)-1))>=总览!$J$13),总览!$K$13,IF(AND(总览!$H$13<>"",B26*100+VALUE(LEFT(C26,LEN(C26)-1))>=总览!$H$13),总览!$I$13,IF(AND(总览!$F$13<>"",B26*100+VALUE(LEFT(C26,LEN(C26)-1))>=总览!$F$13),总览!$G$13,IF(AND(总览!$D$13<>"",B26*100+VALUE(LEFT(C26,LEN(C26)-1))>=总览!$D$13),总览!$E$13,总览!$B$13))))),0))) | M26: =SUM(H26:K26) | N26: =G26-M26 | O26: =O25+N26
A27: 26 | B27: 2028 | C27: 3月 | D27: =IF(AND(总览!$L$6<>"",B27*100+VALUE(LEFT(C27,LEN(C27)-1))>=总览!$L$6),总览!$M$6,IF(AND(总览!$J$6<>"",B27*100+VALUE(LEFT(C27,LEN(C27)-1))>=总览!$J$6),总览!$K$6,IF(AND(总览!$H$6<>"",B27*100+VALUE(LEFT(C27,LEN(C27)-1))>=总览!$H$6),总览!$I$6,IF(AND(总览!$F$6<>"",B27*100+VALUE(LEFT(C27,LEN(C27)-1))>=总览!$F$6),总览!$G$6,IF(AND(总览!$D$6<>"",B27*100+VALUE(LEFT(C27,LEN(C27)-1))>=总览!$D$6),总览!$E$6,总览!$B$6))))) | E27: =IF(C27="12月",IF(AND(总览!$L$7<>"",B27*100+VALUE(LEFT(C27,LEN(C27)-1))>=总览!$L$7),总览!$M$7,IF(AND(总览!$J$7<>"",B27*100+VALUE(LEFT(C27,LEN(C27)-1))>=总览!$J$7),总览!$K$7,IF(AND(总览!$H$7<>"",B27*100+VALUE(LEFT(C27,LEN(C27)-1))>=总览!$H$7),总览!$I$7,IF(AND(总览!$F$7<>"",B27*100+VALUE(LEFT(C27,LEN(C27)-1))>=总览!$F$7),总览!$G$7,IF(AND(总览!$D$7<>"",B27*100+VALUE(LEFT(C27,LEN(C27)-1))>=总览!$D$7),总览!$E$7,总览!$B$7))))),0) | F27: =ROUND(O26*总览!$B$14/12,0) | G27: =D27+E27+F27 | H27: =IF(OR(B27>2027,AND(B27=2027,VALUE(LEFT(C27,LEN(C27)-1))>=9)),IF(AND(总览!$L$10<>"",B27*100+VALUE(LEFT(C27,LEN(C27)-1))>=总览!$L$10),总览!$M$10,IF(AND(总览!$J$10<>"",B27*100+VALUE(LEFT(C27,LEN(C27)-1))>=总览!$J$10),总览!$K$10,IF(AND(总览!$H$10<>"",B27*100+VALUE(LEFT(C27,LEN(C27)-1))>=总览!$H$10),总览!$I$10,IF(AND(总览!$F$10<>"",B27*100+VALUE(LEFT(C27,LEN(C27)-1))>=总览!$F$10),总览!$G$10,IF(AND(总览!$D$10<>"",B27*100+VALUE(LEFT(C27,LEN(C27)-1))>=总览!$D$10),总览!$E$10,总览!$B$10))))),IF(AND(总览!$L$9<>"",B27*100+VALUE(LEFT(C27,LEN(C27)-1))>=总览!$L$9),总览!$M$9,IF(AND(总览!$J$9<>"",B27*100+VALUE(LEFT(C27,LEN(C27)-1))>=总览!$J$9),总览!$K$9,IF(AND(总览!$H$9<>"",B27*100+VALUE(LEFT(C27,LEN(C27)-1))>=总览!$H$9),总览!$I$9,IF(AND(总览!$F$9<>"",B27*100+VALUE(LEFT(C27,LEN(C27)-1))>=总览!$F$9),总览!$G$9,IF(AND(总览!$D$9<>"",B27*100+VALUE(LEFT(C27,LEN(C27)-1))>=总览!$D$9),总览!$E$9,总览!$B$9)))))) | I27: =IF(AND(总览!$L$11<>"",B27*100+VALUE(LEFT(C27,LEN(C27)-1))>=总览!$L$11),总览!$M$11,IF(AND(总览!$J$11<>"",B27*100+VALUE(LEFT(C27,LEN(C27)-1))>=总览!$J$11),总览!$K$11,IF(AND(总览!$H$11<>"",B27*100+VALUE(LEFT(C27,LEN(C27)-1))>=总览!$H$11),总览!$I$11,IF(AND(总览!$F$11<>"",B27*100+VALUE(LEFT(C27,LEN(C27)-1))>=总览!$F$11),总览!$G$11,IF(AND(总览!$D$11<>"",B27*100+VALUE(LEFT(C27,LEN(C27)-1))>=总览!$D$11),总览!$E$11,总览!$B$11))))) | J27: =IF(OR(B27>2027,AND(B27=2027,VALUE(LEFT(C27,LEN(C27)-1))>=9)),IF(AND(总览!$L$12<>"",B27*100+VALUE(LEFT(C27,LEN(C27)-1))>=总览!$L$12),总览!$M$12,IF(AND(总览!$J$12<>"",B27*100+VALUE(LEFT(C27,LEN(C27)-1))>=总览!$J$12),总览!$K$12,IF(AND(总览!$H$12<>"",B27*100+VALUE(LEFT(C27,LEN(C27)-1))>=总览!$H$12),总览!$I$12,IF(AND(总览!$F$12<>"",B27*100+VALUE(LEFT(C27,LEN(C27)-1))>=总览!$F$12),总览!$G$12,IF(AND(总览!$D$12<>"",B27*100+VALUE(LEFT(C27,LEN(C27)-1))>=总览!$D$12),总览!$E$12,总览!$B$12))))),0) | K27: =IF(AND(B27=2026,C27="5月"),120000,IF(AND(B27=2027,C27="9月"),30000,IF(C27="10月",IF(AND(总览!$L$13<>"",B27*100+VALUE(LEFT(C27,LEN(C27)-1))>=总览!$L$13),总览!$M$13,IF(AND(总览!$J$13<>"",B27*100+VALUE(LEFT(C27,LEN(C27)-1))>=总览!$J$13),总览!$K$13,IF(AND(总览!$H$13<>"",B27*100+VALUE(LEFT(C27,LEN(C27)-1))>=总览!$H$13),总览!$I$13,IF(AND(总览!$F$13<>"",B27*100+VALUE(LEFT(C27,LEN(C27)-1))>=总览!$F$13),总览!$G$13,IF(AND(总览!$D$13<>"",B27*100+VALUE(LEFT(C27,LEN(C27)-1))>=总览!$D$13),总览!$E$13,总览!$B$13))))),0))) | M27: =SUM(H27:K27) | N27: =G27-M27 | O27: =O26+N27
A28: 27 | B28: 2028 | C28: 4月 | D28: =IF(AND(总览!$L$6<>"",B28*100+VALUE(LEFT(C28,LEN(C28)-1))>=总览!$L$6),总览!$M$6,IF(AND(总览!$J$6<>"",B28*100+VALUE(LEFT(C28,LEN(C28)-1))>=总览!$J$6),总览!$K$6,IF(AND(总览!$H$6<>"",B28*100+VALUE(LEFT(C28,LEN(C28)-1))>=总览!$H$6),总览!$I$6,IF(AND(总览!$F$6<>"",B28*100+VALUE(LEFT(C28,LEN(C28)-1))>=总览!$F$6),总览!$G$6,IF(AND(总览!$D$6<>"",B28*100+VALUE(LEFT(C28,LEN(C28)-1))>=总览!$D$6),总览!$E$6,总览!$B$6))))) | E28: =IF(C28="12月",IF(AND(总览!$L$7<>"",B28*100+VALUE(LEFT(C28,LEN(C28)-1))>=总览!$L$7),总览!$M$7,IF(AND(总览!$J$7<>"",B28*100+VALUE(LEFT(C28,LEN(C28)-1))>=总览!$J$7),总览!$K$7,IF(AND(总览!$H$7<>"",B28*100+VALUE(LEFT(C28,LEN(C28)-1))>=总览!$H$7),总览!$I$7,IF(AND(总览!$F$7<>"",B28*100+VALUE(LEFT(C28,LEN(C28)-1))>=总览!$F$7),总览!$G$7,IF(AND(总览!$D$7<>"",B28*100+VALUE(LEFT(C28,LEN(C28)-1))>=总览!$D$7),总览!$E$7,总览!$B$7))))),0) | F28: =ROUND(O27*总览!$B$14/12,0) | G28: =D28+E28+F28 | H28: =IF(OR(B28>2027,AND(B28=2027,VALUE(LEFT(C28,LEN(C28)-1))>=9)),IF(AND(总览!$L$10<>"",B28*100+VALUE(LEFT(C28,LEN(C28)-1))>=总览!$L$10),总览!$M$10,IF(AND(总览!$J$10<>"",B28*100+VALUE(LEFT(C28,LEN(C28)-1))>=总览!$J$10),总览!$K$10,IF(AND(总览!$H$10<>"",B28*100+VALUE(LEFT(C28,LEN(C28)-1))>=总览!$H$10),总览!$I$10,IF(AND(总览!$F$10<>"",B28*100+VALUE(LEFT(C28,LEN(C28)-1))>=总览!$F$10),总览!$G$10,IF(AND(总览!$D$10<>"",B28*100+VALUE(LEFT(C28,LEN(C28)-1))>=总览!$D$10),总览!$E$10,总览!$B$10))))),IF(AND(总览!$L$9<>"",B28*100+VALUE(LEFT(C28,LEN(C28)-1))>=总览!$L$9),总览!$M$9,IF(AND(总览!$J$9<>"",B28*100+VALUE(LEFT(C28,LEN(C28)-1))>=总览!$J$9),总览!$K$9,IF(AND(总览!$H$9<>"",B28*100+VALUE(LEFT(C28,LEN(C28)-1))>=总览!$H$9),总览!$I$9,IF(AND(总览!$F$9<>"",B28*100+VALUE(LEFT(C28,LEN(C28)-1))>=总览!$F$9),总览!$G$9,IF(AND(总览!$D$9<>"",B28*100+VALUE(LEFT(C28,LEN(C28)-1))>=总览!$D$9),总览!$E$9,总览!$B$9)))))) | I28: =IF(AND(总览!$L$11<>"",B28*100+VALUE(LEFT(C28,LEN(C28)-1))>=总览!$L$11),总览!$M$11,IF(AND(总览!$J$11<>"",B28*100+VALUE(LEFT(C28,LEN(C28)-1))>=总览!$J$11),总览!$K$11,IF(AND(总览!$H$11<>"",B28*100+VALUE(LEFT(C28,LEN(C28)-1))>=总览!$H$11),总览!$I$11,IF(AND(总览!$F$11<>"",B28*100+VALUE(LEFT(C28,LEN(C28)-1))>=总览!$F$11),总览!$G$11,IF(AND(总览!$D$11<>"",B28*100+VALUE(LEFT(C28,LEN(C28)-1))>=总览!$D$11),总览!$E$11,总览!$B$11))))) | J28: =IF(OR(B28>2027,AND(B28=2027,VALUE(LEFT(C28,LEN(C28)-1))>=9)),IF(AND(总览!$L$12<>"",B28*100+VALUE(LEFT(C28,LEN(C28)-1))>=总览!$L$12),总览!$M$12,IF(AND(总览!$J$12<>"",B28*100+VALUE(LEFT(C28,LEN(C28)-1))>=总览!$J$12),总览!$K$12,IF(AND(总览!$H$12<>"",B28*100+VALUE(LEFT(C28,LEN(C28)-1))>=总览!$H$12),总览!$I$12,IF(AND(总览!$F$12<>"",B28*100+VALUE(LEFT(C28,LEN(C28)-1))>=总览!$F$12),总览!$G$12,IF(AND(总览!$D$12<>"",B28*100+VALUE(LEFT(C28,LEN(C28)-1))>=总览!$D$12),总览!$E$12,总览!$B$12))))),0) | K28: =IF(AND(B28=2026,C28="5月"),120000,IF(AND(B28=2027,C28="9月"),30000,IF(C28="10月",IF(AND(总览!$L$13<>"",B28*100+VALUE(LEFT(C28,LEN(C28)-1))>=总览!$L$13),总览!$M$13,IF(AND(总览!$J$13<>"",B28*100+VALUE(LEFT(C28,LEN(C28)-1))>=总览!$J$13),总览!$K$13,IF(AND(总览!$H$13<>"",B28*100+VALUE(LEFT(C28,LEN(C28)-1))>=总览!$H$13),总览!$I$13,IF(AND(总览!$F$13<>"",B28*100+VALUE(LEFT(C28,LEN(C28)-1))>=总览!$F$13),总览!$G$13,IF(AND(总览!$D$13<>"",B28*100+VALUE(LEFT(C28,LEN(C28)-1))>=总览!$D$13),总览!$E$13,总览!$B$13))))),0))) | M28: =SUM(H28:K28) | N28: =G28-M28 | O28: =O27+N28
A29: 28 | B29: 2028 | C29: 5月 | D29: =IF(AND(总览!$L$6<>"",B29*100+VALUE(LEFT(C29,LEN(C29)-1))>=总览!$L$6),总览!$M$6,IF(AND(总览!$J$6<>"",B29*100+VALUE(LEFT(C29,LEN(C29)-1))>=总览!$J$6),总览!$K$6,IF(AND(总览!$H$6<>"",B29*100+VALUE(LEFT(C29,LEN(C29)-1))>=总览!$H$6),总览!$I$6,IF(AND(总览!$F$6<>"",B29*100+VALUE(LEFT(C29,LEN(C29)-1))>=总览!$F$6),总览!$G$6,IF(AND(总览!$D$6<>"",B29*100+VALUE(LEFT(C29,LEN(C29)-1))>=总览!$D$6),总览!$E$6,总览!$B$6))))) | E29: =IF(C29="12月",IF(AND(总览!$L$7<>"",B29*100+VALUE(LEFT(C29,LEN(C29)-1))>=总览!$L$7),总览!$M$7,IF(AND(总览!$J$7<>"",B29*100+VALUE(LEFT(C29,LEN(C29)-1))>=总览!$J$7),总览!$K$7,IF(AND(总览!$H$7<>"",B29*100+VALUE(LEFT(C29,LEN(C29)-1))>=总览!$H$7),总览!$I$7,IF(AND(总览!$F$7<>"",B29*100+VALUE(LEFT(C29,LEN(C29)-1))>=总览!$F$7),总览!$G$7,IF(AND(总览!$D$7<>"",B29*100+VALUE(LEFT(C29,LEN(C29)-1))>=总览!$D$7),总览!$E$7,总览!$B$7))))),0) | F29: =ROUND(O28*总览!$B$14/12,0) | G29: =D29+E29+F29 | H29: =IF(OR(B29>2027,AND(B29=2027,VALUE(LEFT(C29,LEN(C29)-1))>=9)),IF(AND(总览!$L$10<>"",B29*100+VALUE(LEFT(C29,LEN(C29)-1))>=总览!$L$10),总览!$M$10,IF(AND(总览!$J$10<>"",B29*100+VALUE(LEFT(C29,LEN(C29)-1))>=总览!$J$10),总览!$K$10,IF(AND(总览!$H$10<>"",B29*100+VALUE(LEFT(C29,LEN(C29)-1))>=总览!$H$10),总览!$I$10,IF(AND(总览!$F$10<>"",B29*100+VALUE(LEFT(C29,LEN(C29)-1))>=总览!$F$10),总览!$G$10,IF(AND(总览!$D$10<>"",B29*100+VALUE(LEFT(C29,LEN(C29)-1))>=总览!$D$10),总览!$E$10,总览!$B$10))))),IF(AND(总览!$L$9<>"",B29*100+VALUE(LEFT(C29,LEN(C29)-1))>=总览!$L$9),总览!$M$9,IF(AND(总览!$J$9<>"",B29*100+VALUE(LEFT(C29,LEN(C29)-1))>=总览!$J$9),总览!$K$9,IF(AND(总览!$H$9<>"",B29*100+VALUE(LEFT(C29,LEN(C29)-1))>=总览!$H$9),总览!$I$9,IF(AND(总览!$F$9<>"",B29*100+VALUE(LEFT(C29,LEN(C29)-1))>=总览!$F$9),总览!$G$9,IF(AND(总览!$D$9<>"",B29*100+VALUE(LEFT(C29,LEN(C29)-1))>=总览!$D$9),总览!$E$9,总览!$B$9)))))) | I29: =IF(AND(总览!$L$11<>"",B29*100+VALUE(LEFT(C29,LEN(C29)-1))>=总览!$L$11),总览!$M$11,IF(AND(总览!$J$11<>"",B29*100+VALUE(LEFT(C29,LEN(C29)-1))>=总览!$J$11),总览!$K$11,IF(AND(总览!$H$11<>"",B29*100+VALUE(LEFT(C29,LEN(C29)-1))>=总览!$H$11),总览!$I$11,IF(AND(总览!$F$11<>"",B29*100+VALUE(LEFT(C29,LEN(C29)-1))>=总览!$F$11),总览!$G$11,IF(AND(总览!$D$11<>"",B29*100+VALUE(LEFT(C29,LEN(C29)-1))>=总览!$D$11),总览!$E$11,总览!$B$11))))) | J29: =IF(OR(B29>2027,AND(B29=2027,VALUE(LEFT(C29,LEN(C29)-1))>=9)),IF(AND(总览!$L$12<>"",B29*100+VALUE(LEFT(C29,LEN(C29)-1))>=总览!$L$12),总览!$M$12,IF(AND(总览!$J$12<>"",B29*100+VALUE(LEFT(C29,LEN(C29)-1))>=总览!$J$12),总览!$K$12,IF(AND(总览!$H$12<>"",B29*100+VALUE(LEFT(C29,LEN(C29)-1))>=总览!$H$12),总览!$I$12,IF(AND(总览!$F$12<>"",B29*100+VALUE(LEFT(C29,LEN(C29)-1))>=总览!$F$12),总览!$G$12,IF(AND(总览!$D$12<>"",B29*100+VALUE(LEFT(C29,LEN(C29)-1))>=总览!$D$12),总览!$E$12,总览!$B$12))))),0) | K29: =IF(AND(B29=2026,C29="5月"),120000,IF(AND(B29=2027,C29="9月"),30000,IF(C29="10月",IF(AND(总览!$L$13<>"",B29*100+VALUE(LEFT(C29,LEN(C29)-1))>=总览!$L$13),总览!$M$13,IF(AND(总览!$J$13<>"",B29*100+VALUE(LEFT(C29,LEN(C29)-1))>=总览!$J$13),总览!$K$13,IF(AND(总览!$H$13<>"",B29*100+VALUE(LEFT(C29,LEN(C29)-1))>=总览!$H$13),总览!$I$13,IF(AND(总览!$F$13<>"",B29*100+VALUE(LEFT(C29,LEN(C29)-1))>=总览!$F$13),总览!$G$13,IF(AND(总览!$D$13<>"",B29*100+VALUE(LEFT(C29,LEN(C29)-1))>=总览!$D$13),总览!$E$13,总览!$B$13))))),0))) | M29: =SUM(H29:K29) | N29: =G29-M29 | O29: =O28+N29
A30: 29 | B30: 2028 | C30: 6月 | D30: =IF(AND(总览!$L$6<>"",B30*100+VALUE(LEFT(C30,LEN(C30)-1))>=总览!$L$6),总览!$M$6,IF(AND(总览!$J$6<>"",B30*100+VALUE(LEFT(C30,LEN(C30)-1))>=总览!$J$6),总览!$K$6,IF(AND(总览!$H$6<>"",B30*100+VALUE(LEFT(C30,LEN(C30)-1))>=总览!$H$6),总览!$I$6,IF(AND(总览!$F$6<>"",B30*100+VALUE(LEFT(C30,LEN(C30)-1))>=总览!$F$6),总览!$G$6,IF(AND(总览!$D$6<>"",B30*100+VALUE(LEFT(C30,LEN(C30)-1))>=总览!$D$6),总览!$E$6,总览!$B$6))))) | E30: =IF(C30="12月",IF(AND(总览!$L$7<>"",B30*100+VALUE(LEFT(C30,LEN(C30)-1))>=总览!$L$7),总览!$M$7,IF(AND(总览!$J$7<>"",B30*100+VALUE(LEFT(C30,LEN(C30)-1))>=总览!$J$7),总览!$K$7,IF(AND(总览!$H$7<>"",B30*100+VALUE(LEFT(C30,LEN(C30)-1))>=总览!$H$7),总览!$I$7,IF(AND(总览!$F$7<>"",B30*100+VALUE(LEFT(C30,LEN(C30)-1))>=总览!$F$7),总览!$G$7,IF(AND(总览!$D$7<>"",B30*100+VALUE(LEFT(C30,LEN(C30)-1))>=总览!$D$7),总览!$E$7,总览!$B$7))))),0) | F30: =ROUND(O29*总览!$B$14/12,0) | G30: =D30+E30+F30 | H30: =IF(OR(B30>2027,AND(B30=2027,VALUE(LEFT(C30,LEN(C30)-1))>=9)),IF(AND(总览!$L$10<>"",B30*100+VALUE(LEFT(C30,LEN(C30)-1))>=总览!$L$10),总览!$M$10,IF(AND(总览!$J$10<>"",B30*100+VALUE(LEFT(C30,LEN(C30)-1))>=总览!$J$10),总览!$K$10,IF(AND(总览!$H$10<>"",B30*100+VALUE(LEFT(C30,LEN(C30)-1))>=总览!$H$10),总览!$I$10,IF(AND(总览!$F$10<>"",B30*100+VALUE(LEFT(C30,LEN(C30)-1))>=总览!$F$10),总览!$G$10,IF(AND(总览!$D$10<>"",B30*100+VALUE(LEFT(C30,LEN(C30)-1))>=总览!$D$10),总览!$E$10,总览!$B$10))))),IF(AND(总览!$L$9<>"",B30*100+VALUE(LEFT(C30,LEN(C30)-1))>=总览!$L$9),总览!$M$9,IF(AND(总览!$J$9<>"",B30*100+VALUE(LEFT(C30,LEN(C30)-1))>=总览!$J$9),总览!$K$9,IF(AND(总览!$H$9<>"",B30*100+VALUE(LEFT(C30,LEN(C30)-1))>=总览!$H$9),总览!$I$9,IF(AND(总览!$F$9<>"",B30*100+VALUE(LEFT(C30,LEN(C30)-1))>=总览!$F$9),总览!$G$9,IF(AND(总览!$D$9<>"",B30*100+VALUE(LEFT(C30,LEN(C30)-1))>=总览!$D$9),总览!$E$9,总览!$B$9)))))) | I30: =IF(AND(总览!$L$11<>"",B30*100+VALUE(LEFT(C30,LEN(C30)-1))>=总览!$L$11),总览!$M$11,IF(AND(总览!$J$11<>"",B30*100+VALUE(LEFT(C30,LEN(C30)-1))>=总览!$J$11),总览!$K$11,IF(AND(总览!$H$11<>"",B30*100+VALUE(LEFT(C30,LEN(C30)-1))>=总览!$H$11),总览!$I$11,IF(AND(总览!$F$11<>"",B30*100+VALUE(LEFT(C30,LEN(C30)-1))>=总览!$F$11),总览!$G$11,IF(AND(总览!$D$11<>"",B30*100+VALUE(LEFT(C30,LEN(C30)-1))>=总览!$D$11),总览!$E$11,总览!$B$11))))) | J30: =IF(OR(B30>2027,AND(B30=2027,VALUE(LEFT(C30,LEN(C30)-1))>=9)),IF(AND(总览!$L$12<>"",B30*100+VALUE(LEFT(C30,LEN(C30)-1))>=总览!$L$12),总览!$M$12,IF(AND(总览!$J$12<>"",B30*100+VALUE(LEFT(C30,LEN(C30)-1))>=总览!$J$12),总览!$K$12,IF(AND(总览!$H$12<>"",B30*100+VALUE(LEFT(C30,LEN(C30)-1))>=总览!$H$12),总览!$I$12,IF(AND(总览!$F$12<>"",B30*100+VALUE(LEFT(C30,LEN(C30)-1))>=总览!$F$12),总览!$G$12,IF(AND(总览!$D$12<>"",B30*100+VALUE(LEFT(C30,LEN(C30)-1))>=总览!$D$12),总览!$E$12,总览!$B$12))))),0) | K30: =IF(AND(B30=2026,C30="5月"),120000,IF(AND(B30=2027,C30="9月"),30000,IF(C30="10月",IF(AND(总览!$L$13<>"",B30*100+VALUE(LEFT(C30,LEN(C30)-1))>=总览!$L$13),总览!$M$13,IF(AND(总览!$J$13<>"",B30*100+VALUE(LEFT(C30,LEN(C30)-1))>=总览!$J$13),总览!$K$13,IF(AND(总览!$H$13<>"",B30*100+VALUE(LEFT(C30,LEN(C30)-1))>=总览!$H$13),总览!$I$13,IF(AND(总览!$F$13<>"",B30*100+VALUE(LEFT(C30,LEN(C30)-1))>=总览!$F$13),总览!$G$13,IF(AND(总览!$D$13<>"",B30*100+VALUE(LEFT(C30,LEN(C30)-1))>=总览!$D$13),总览!$E$13,总览!$B$13))))),0))) | M30: =SUM(H30:K30) | N30: =G30-M30 | O30: =O29+N30
A31: 30 | B31: 2028 | C31: 7月 | D31: =IF(AND(总览!$L$6<>"",B31*100+VALUE(LEFT(C31,LEN(C31)-1))>=总览!$L$6),总览!$M$6,IF(AND(总览!$J$6<>"",B31*100+VALUE(LEFT(C31,LEN(C31)-1))>=总览!$J$6),总览!$K$6,IF(AND(总览!$H$6<>"",B31*100+VALUE(LEFT(C31,LEN(C31)-1))>=总览!$H$6),总览!$I$6,IF(AND(总览!$F$6<>"",B31*100+VALUE(LEFT(C31,LEN(C31)-1))>=总览!$F$6),总览!$G$6,IF(AND(总览!$D$6<>"",B31*100+VALUE(LEFT(C31,LEN(C31)-1))>=总览!$D$6),总览!$E$6,总览!$B$6))))) | E31: =IF(C31="12月",IF(AND(总览!$L$7<>"",B31*100+VALUE(LEFT(C31,LEN(C31)-1))>=总览!$L$7),总览!$M$7,IF(AND(总览!$J$7<>"",B31*100+VALUE(LEFT(C31,LEN(C31)-1))>=总览!$J$7),总览!$K$7,IF(AND(总览!$H$7<>"",B31*100+VALUE(LEFT(C31,LEN(C31)-1))>=总览!$H$7),总览!$I$7,IF(AND(总览!$F$7<>"",B31*100+VALUE(LEFT(C31,LEN(C31)-1))>=总览!$F$7),总览!$G$7,IF(AND(总览!$D$7<>"",B31*100+VALUE(LEFT(C31,LEN(C31)-1))>=总览!$D$7),总览!$E$7,总览!$B$7))))),0) | F31: =ROUND(O30*总览!$B$14/12,0) | G31: =D31+E31+F31 | H31: =IF(OR(B31>2027,AND(B31=2027,VALUE(LEFT(C31,LEN(C31)-1))>=9)),IF(AND(总览!$L$10<>"",B31*100+VALUE(LEFT(C31,LEN(C31)-1))>=总览!$L$10),总览!$M$10,IF(AND(总览!$J$10<>"",B31*100+VALUE(LEFT(C31,LEN(C31)-1))>=总览!$J$10),总览!$K$10,IF(AND(总览!$H$10<>"",B31*100+VALUE(LEFT(C31,LEN(C31)-1))>=总览!$H$10),总览!$I$10,IF(AND(总览!$F$10<>"",B31*100+VALUE(LEFT(C31,LEN(C31)-1))>=总览!$F$10),总览!$G$10,IF(AND(总览!$D$10<>"",B31*100+VALUE(LEFT(C31,LEN(C31)-1))>=总览!$D$10),总览!$E$10,总览!$B$10))))),IF(AND(总览!$L$9<>"",B31*100+VALUE(LEFT(C31,LEN(C31)-1))>=总览!$L$9),总览!$M$9,IF(AND(总览!$J$9<>"",B31*100+VALUE(LEFT(C31,LEN(C31)-1))>=总览!$J$9),总览!$K$9,IF(AND(总览!$H$9<>"",B31*100+VALUE(LEFT(C31,LEN(C31)-1))>=总览!$H$9),总览!$I$9,IF(AND(总览!$F$9<>"",B31*100+VALUE(LEFT(C31,LEN(C31)-1))>=总览!$F$9),总览!$G$9,IF(AND(总览!$D$9<>"",B31*100+VALUE(LEFT(C31,LEN(C31)-1))>=总览!$D$9),总览!$E$9,总览!$B$9)))))) | I31: =IF(AND(总览!$L$11<>"",B31*100+VALUE(LEFT(C31,LEN(C31)-1))>=总览!$L$11),总览!$M$11,IF(AND(总览!$J$11<>"",B31*100+VALUE(LEFT(C31,LEN(C31)-1))>=总览!$J$11),总览!$K$11,IF(AND(总览!$H$11<>"",B31*100+VALUE(LEFT(C31,LEN(C31)-1))>=总览!$H$11),总览!$I$11,IF(AND(总览!$F$11<>"",B31*100+VALUE(LEFT(C31,LEN(C31)-1))>=总览!$F$11),总览!$G$11,IF(AND(总览!$D$11<>"",B31*100+VALUE(LEFT(C31,LEN(C31)-1))>=总览!$D$11),总览!$E$11,总览!$B$11))))) | J31: =IF(OR(B31>2027,AND(B31=2027,VALUE(LEFT(C31,LEN(C31)-1))>=9)),IF(AND(总览!$L$12<>"",B31*100+VALUE(LEFT(C31,LEN(C31)-1))>=总览!$L$12),总览!$M$12,IF(AND(总览!$J$12<>"",B31*100+VALUE(LEFT(C31,LEN(C31)-1))>=总览!$J$12),总览!$K$12,IF(AND(总览!$H$12<>"",B31*100+VALUE(LEFT(C31,LEN(C31)-1))>=总览!$H$12),总览!$I$12,IF(AND(总览!$F$12<>"",B31*100+VALUE(LEFT(C31,LEN(C31)-1))>=总览!$F$12),总览!$G$12,IF(AND(总览!$D$12<>"",B31*100+VALUE(LEFT(C31,LEN(C31)-1))>=总览!$D$12),总览!$E$12,总览!$B$12))))),0) | K31: =IF(AND(B31=2026,C31="5月"),120000,IF(AND(B31=2027,C31="9月"),30000,IF(C31="10月",IF(AND(总览!$L$13<>"",B31*100+VALUE(LEFT(C31,LEN(C31)-1))>=总览!$L$13),总览!$M$13,IF(AND(总览!$J$13<>"",B31*100+VALUE(LEFT(C31,LEN(C31)-1))>=总览!$J$13),总览!$K$13,IF(AND(总览!$H$13<>"",B31*100+VALUE(LEFT(C31,LEN(C31)-1))>=总览!$H$13),总览!$I$13,IF(AND(总览!$F$13<>"",B31*100+VALUE(LEFT(C31,LEN(C31)-1))>=总览!$F$13),总览!$G$13,IF(AND(总览!$D$13<>"",B31*100+VALUE(LEFT(C31,LEN(C31)-1))>=总览!$D$13),总览!$E$13,总览!$B$13))))),0))) | M31: =SUM(H31:K31) | N31: =G31-M31 | O31: =O30+N31
A32: 31 | B32: 2028 | C32: 8月 | D32: =IF(AND(总览!$L$6<>"",B32*100+VALUE(LEFT(C32,LEN(C32)-1))>=总览!$L$6),总览!$M$6,IF(AND(总览!$J$6<>"",B32*100+VALUE(LEFT(C32,LEN(C32)-1))>=总览!$J$6),总览!$K$6,IF(AND(总览!$H$6<>"",B32*100+VALUE(LEFT(C32,LEN(C32)-1))>=总览!$H$6),总览!$I$6,IF(AND(总览!$F$6<>"",B32*100+VALUE(LEFT(C32,LEN(C32)-1))>=总览!$F$6),总览!$G$6,IF(AND(总览!$D$6<>"",B32*100+VALUE(LEFT(C32,LEN(C32)-1))>=总览!$D$6),总览!$E$6,总览!$B$6))))) | E32: =IF(C32="12月",IF(AND(总览!$L$7<>"",B32*100+VALUE(LEFT(C32,LEN(C32)-1))>=总览!$L$7),总览!$M$7,IF(AND(总览!$J$7<>"",B32*100+VALUE(LEFT(C32,LEN(C32)-1))>=总览!$J$7),总览!$K$7,IF(AND(总览!$H$7<>"",B32*100+VALUE(LEFT(C32,LEN(C32)-1))>=总览!$H$7),总览!$I$7,IF(AND(总览!$F$7<>"",B32*100+VALUE(LEFT(C32,LEN(C32)-1))>=总览!$F$7),总览!$G$7,IF(AND(总览!$D$7<>"",B32*100+VALUE(LEFT(C32,LEN(C32)-1))>=总览!$D$7),总览!$E$7,总览!$B$7))))),0) | F32: =ROUND(O31*总览!$B$14/12,0) | G32: =D32+E32+F32 | H32: =IF(OR(B32>2027,AND(B32=2027,VALUE(LEFT(C32,LEN(C32)-1))>=9)),IF(AND(总览!$L$10<>"",B32*100+VALUE(LEFT(C32,LEN(C32)-1))>=总览!$L$10),总览!$M$10,IF(AND(总览!$J$10<>"",B32*100+VALUE(LEFT(C32,LEN(C32)-1))>=总览!$J$10),总览!$K$10,IF(AND(总览!$H$10<>"",B32*100+VALUE(LEFT(C32,LEN(C32)-1))>=总览!$H$10),总览!$I$10,IF(AND(总览!$F$10<>"",B32*100+VALUE(LEFT(C32,LEN(C32)-1))>=总览!$F$10),总览!$G$10,IF(AND(总览!$D$10<>"",B32*100+VALUE(LEFT(C32,LEN(C32)-1))>=总览!$D$10),总览!$E$10,总览!$B$10))))),IF(AND(总览!$L$9<>"",B32*100+VALUE(LEFT(C32,LEN(C32)-1))>=总览!$L$9),总览!$M$9,IF(AND(总览!$J$9<>"",B32*100+VALUE(LEFT(C32,LEN(C32)-1))>=总览!$J$9),总览!$K$9,IF(AND(总览!$H$9<>"",B32*100+VALUE(LEFT(C32,LEN(C32)-1))>=总览!$H$9),总览!$I$9,IF(AND(总览!$F$9<>"",B32*100+VALUE(LEFT(C32,LEN(C32)-1))>=总览!$F$9),总览!$G$9,IF(AND(总览!$D$9<>"",B32*100+VALUE(LEFT(C32,LEN(C32)-1))>=总览!$D$9),总览!$E$9,总览!$B$9)))))) | I32: =IF(AND(总览!$L$11<>"",B32*100+VALUE(LEFT(C32,LEN(C32)-1))>=总览!$L$11),总览!$M$11,IF(AND(总览!$J$11<>"",B32*100+VALUE(LEFT(C32,LEN(C32)-1))>=总览!$J$11),总览!$K$11,IF(AND(总览!$H$11<>"",B32*100+VALUE(LEFT(C32,LEN(C32)-1))>=总览!$H$11),总览!$I$11,IF(AND(总览!$F$11<>"",B32*100+VALUE(LEFT(C32,LEN(C32)-1))>=总览!$F$11),总览!$G$11,IF(AND(总览!$D$11<>"",B32*100+VALUE(LEFT(C32,LEN(C32)-1))>=总览!$D$11),总览!$E$11,总览!$B$11))))) | J32: =IF(OR(B32>2027,AND(B32=2027,VALUE(LEFT(C32,LEN(C32)-1))>=9)),IF(AND(总览!$L$12<>"",B32*100+VALUE(LEFT(C32,LEN(C32)-1))>=总览!$L$12),总览!$M$12,IF(AND(总览!$J$12<>"",B32*100+VALUE(LEFT(C32,LEN(C32)-1))>=总览!$J$12),总览!$K$12,IF(AND(总览!$H$12<>"",B32*100+VALUE(LEFT(C32,LEN(C32)-1))>=总览!$H$12),总览!$I$12,IF(AND(总览!$F$12<>"",B32*100+VALUE(LEFT(C32,LEN(C32)-1))>=总览!$F$12),总览!$G$12,IF(AND(总览!$D$12<>"",B32*100+VALUE(LEFT(C32,LEN(C32)-1))>=总览!$D$12),总览!$E$12,总览!$B$12))))),0) | K32: =IF(AND(B32=2026,C32="5月"),120000,IF(AND(B32=2027,C32="9月"),30000,IF(C32="10月",IF(AND(总览!$L$13<>"",B32*100+VALUE(LEFT(C32,LEN(C32)-1))>=总览!$L$13),总览!$M$13,IF(AND(总览!$J$13<>"",B32*100+VALUE(LEFT(C32,LEN(C32)-1))>=总览!$J$13),总览!$K$13,IF(AND(总览!$H$13<>"",B32*100+VALUE(LEFT(C32,LEN(C32)-1))>=总览!$H$13),总览!$I$13,IF(AND(总览!$F$13<>"",B32*100+VALUE(LEFT(C32,LEN(C32)-1))>=总览!$F$13),总览!$G$13,IF(AND(总览!$D$13<>"",B32*100+VALUE(LEFT(C32,LEN(C32)-1))>=总览!$D$13),总览!$E$13,总览!$B$13))))),0))) | M32: =SUM(H32:K32) | N32: =G32-M32 | O32: =O31+N32
A33: 32 | B33: 2028 | C33: 9月 | D33: =IF(AND(总览!$L$6<>"",B33*100+VALUE(LEFT(C33,LEN(C33)-1))>=总览!$L$6),总览!$M$6,IF(AND(总览!$J$6<>"",B33*100+VALUE(LEFT(C33,LEN(C33)-1))>=总览!$J$6),总览!$K$6,IF(AND(总览!$H$6<>"",B33*100+VALUE(LEFT(C33,LEN(C33)-1))>=总览!$H$6),总览!$I$6,IF(AND(总览!$F$6<>"",B33*100+VALUE(LEFT(C33,LEN(C33)-1))>=总览!$F$6),总览!$G$6,IF(AND(总览!$D$6<>"",B33*100+VALUE(LEFT(C33,LEN(C33)-1))>=总览!$D$6),总览!$E$6,总览!$B$6))))) | E33: =IF(C33="12月",IF(AND(总览!$L$7<>"",B33*100+VALUE(LEFT(C33,LEN(C33)-1))>=总览!$L$7),总览!$M$7,IF(AND(总览!$J$7<>"",B33*100+VALUE(LEFT(C33,LEN(C33)-1))>=总览!$J$7),总览!$K$7,IF(AND(总览!$H$7<>"",B33*100+VALUE(LEFT(C33,LEN(C33)-1))>=总览!$H$7),总览!$I$7,IF(AND(总览!$F$7<>"",B33*100+VALUE(LEFT(C33,LEN(C33)-1))>=总览!$F$7),总览!$G$7,IF(AND(总览!$D$7<>"",B33*100+VALUE(LEFT(C33,LEN(C33)-1))>=总览!$D$7),总览!$E$7,总览!$B$7))))),0) | F33: =ROUND(O32*总览!$B$14/12,0) | G33: =D33+E33+F33 | H33: =IF(OR(B33>2027,AND(B33=2027,VALUE(LEFT(C33,LEN(C33)-1))>=9)),IF(AND(总览!$L$10<>"",B33*100+VALUE(LEFT(C33,LEN(C33)-1))>=总览!$L$10),总览!$M$10,IF(AND(总览!$J$10<>"",B33*100+VALUE(LEFT(C33,LEN(C33)-1))>=总览!$J$10),总览!$K$10,IF(AND(总览!$H$10<>"",B33*100+VALUE(LEFT(C33,LEN(C33)-1))>=总览!$H$10),总览!$I$10,IF(AND(总览!$F$10<>"",B33*100+VALUE(LEFT(C33,LEN(C33)-1))>=总览!$F$10),总览!$G$10,IF(AND(总览!$D$10<>"",B33*100+VALUE(LEFT(C33,LEN(C33)-1))>=总览!$D$10),总览!$E$10,总览!$B$10))))),IF(AND(总览!$L$9<>"",B33*100+VALUE(LEFT(C33,LEN(C33)-1))>=总览!$L$9),总览!$M$9,IF(AND(总览!$J$9<>"",B33*100+VALUE(LEFT(C33,LEN(C33)-1))>=总览!$J$9),总览!$K$9,IF(AND(总览!$H$9<>"",B33*100+VALUE(LEFT(C33,LEN(C33)-1))>=总览!$H$9),总览!$I$9,IF(AND(总览!$F$9<>"",B33*100+VALUE(LEFT(C33,LEN(C33)-1))>=总览!$F$9),总览!$G$9,IF(AND(总览!$D$9<>"",B33*100+VALUE(LEFT(C33,LEN(C33)-1))>=总览!$D$9),总览!$E$9,总览!$B$9)))))) | I33: =IF(AND(总览!$L$11<>"",B33*100+VALUE(LEFT(C33,LEN(C33)-1))>=总览!$L$11),总览!$M$11,IF(AND(总览!$J$11<>"",B33*100+VALUE(LEFT(C33,LEN(C33)-1))>=总览!$J$11),总览!$K$11,IF(AND(总览!$H$11<>"",B33*100+VALUE(LEFT(C33,LEN(C33)-1))>=总览!$H$11),总览!$I$11,IF(AND(总览!$F$11<>"",B33*100+VALUE(LEFT(C33,LEN(C33)-1))>=总览!$F$11),总览!$G$11,IF(AND(总览!$D$11<>"",B33*100+VALUE(LEFT(C33,LEN(C33)-1))>=总览!$D$11),总览!$E$11,总览!$B$11))))) | J33: =IF(OR(B33>2027,AND(B33=2027,VALUE(LEFT(C33,LEN(C33)-1))>=9)),IF(AND(总览!$L$12<>"",B33*100+VALUE(LEFT(C33,LEN(C33)-1))>=总览!$L$12),总览!$M$12,IF(AND(总览!$J$12<>"",B33*100+VALUE(LEFT(C33,LEN(C33)-1))>=总览!$J$12),总览!$K$12,IF(AND(总览!$H$12<>"",B33*100+VALUE(LEFT(C33,LEN(C33)-1))>=总览!$H$12),总览!$I$12,IF(AND(总览!$F$12<>"",B33*100+VALUE(LEFT(C33,LEN(C33)-1))>=总览!$F$12),总览!$G$12,IF(AND(总览!$D$12<>"",B33*100+VALUE(LEFT(C33,LEN(C33)-1))>=总览!$D$12),总览!$E$12,总览!$B$12))))),0) | K33: =IF(AND(B33=2026,C33="5月"),120000,IF(AND(B33=2027,C33="9月"),30000,IF(C33="10月",IF(AND(总览!$L$13<>"",B33*100+VALUE(LEFT(C33,LEN(C33)-1))>=总览!$L$13),总览!$M$13,IF(AND(总览!$J$13<>"",B33*100+VALUE(LEFT(C33,LEN(C33)-1))>=总览!$J$13),总览!$K$13,IF(AND(总览!$H$13<>"",B33*100+VALUE(LEFT(C33,LEN(C33)-1))>=总览!$H$13),总览!$I$13,IF(AND(总览!$F$13<>"",B33*100+VALUE(LEFT(C33,LEN(C33)-1))>=总览!$F$13),总览!$G$13,IF(AND(总览!$D$13<>"",B33*100+VALUE(LEFT(C33,LEN(C33)-1))>=总览!$D$13),总览!$E$13,总览!$B$13))))),0))) | M33: =SUM(H33:K33) | N33: =G33-M33 | O33: =O32+N33
A34: 33 | B34: 2028 | C34: 10月 | D34: =IF(AND(总览!$L$6<>"",B34*100+VALUE(LEFT(C34,LEN(C34)-1))>=总览!$L$6),总览!$M$6,IF(AND(总览!$J$6<>"",B34*100+VALUE(LEFT(C34,LEN(C34)-1))>=总览!$J$6),总览!$K$6,IF(AND(总览!$H$6<>"",B34*100+VALUE(LEFT(C34,LEN(C34)-1))>=总览!$H$6),总览!$I$6,IF(AND(总览!$F$6<>"",B34*100+VALUE(LEFT(C34,LEN(C34)-1))>=总览!$F$6),总览!$G$6,IF(AND(总览!$D$6<>"",B34*100+VALUE(LEFT(C34,LEN(C34)-1))>=总览!$D$6),总览!$E$6,总览!$B$6))))) | E34: =IF(C34="12月",IF(AND(总览!$L$7<>"",B34*100+VALUE(LEFT(C34,LEN(C34)-1))>=总览!$L$7),总览!$M$7,IF(AND(总览!$J$7<>"",B34*100+VALUE(LEFT(C34,LEN(C34)-1))>=总览!$J$7),总览!$K$7,IF(AND(总览!$H$7<>"",B34*100+VALUE(LEFT(C34,LEN(C34)-1))>=总览!$H$7),总览!$I$7,IF(AND(总览!$F$7<>"",B34*100+VALUE(LEFT(C34,LEN(C34)-1))>=总览!$F$7),总览!$G$7,IF(AND(总览!$D$7<>"",B34*100+VALUE(LEFT(C34,LEN(C34)-1))>=总览!$D$7),总览!$E$7,总览!$B$7))))),0) | F34: =ROUND(O33*总览!$B$14/12,0) | G34: =D34+E34+F34 | H34: =IF(OR(B34>2027,AND(B34=2027,VALUE(LEFT(C34,LEN(C34)-1))>=9)),IF(AND(总览!$L$10<>"",B34*100+VALUE(LEFT(C34,LEN(C34)-1))>=总览!$L$10),总览!$M$10,IF(AND(总览!$J$10<>"",B34*100+VALUE(LEFT(C34,LEN(C34)-1))>=总览!$J$10),总览!$K$10,IF(AND(总览!$H$10<>"",B34*100+VALUE(LEFT(C34,LEN(C34)-1))>=总览!$H$10),总览!$I$10,IF(AND(总览!$F$10<>"",B34*100+VALUE(LEFT(C34,LEN(C34)-1))>=总览!$F$10),总览!$G$10,IF(AND(总览!$D$10<>"",B34*100+VALUE(LEFT(C34,LEN(C34)-1))>=总览!$D$10),总览!$E$10,总览!$B$10))))),IF(AND(总览!$L$9<>"",B34*100+VALUE(LEFT(C34,LEN(C34)-1))>=总览!$L$9),总览!$M$9,IF(AND(总览!$J$9<>"",B34*100+VALUE(LEFT(C34,LEN(C34)-1))>=总览!$J$9),总览!$K$9,IF(AND(总览!$H$9<>"",B34*100+VALUE(LEFT(C34,LEN(C34)-1))>=总览!$H$9),总览!$I$9,IF(AND(总览!$F$9<>"",B34*100+VALUE(LEFT(C34,LEN(C34)-1))>=总览!$F$9),总览!$G$9,IF(AND(总览!$D$9<>"",B34*100+VALUE(LEFT(C34,LEN(C34)-1))>=总览!$D$9),总览!$E$9,总览!$B$9)))))) | I34: =IF(AND(总览!$L$11<>"",B34*100+VALUE(LEFT(C34,LEN(C34)-1))>=总览!$L$11),总览!$M$11,IF(AND(总览!$J$11<>"",B34*100+VALUE(LEFT(C34,LEN(C34)-1))>=总览!$J$11),总览!$K$11,IF(AND(总览!$H$11<>"",B34*100+VALUE(LEFT(C34,LEN(C34)-1))>=总览!$H$11),总览!$I$11,IF(AND(总览!$F$11<>"",B34*100+VALUE(LEFT(C34,LEN(C34)-1))>=总览!$F$11),总览!$G$11,IF(AND(总览!$D$11<>"",B34*100+VALUE(LEFT(C34,LEN(C34)-1))>=总览!$D$11),总览!$E$11,总览!$B$11))))) | J34: =IF(OR(B34>2027,AND(B34=2027,VALUE(LEFT(C34,LEN(C34)-1))>=9)),IF(AND(总览!$L$12<>"",B34*100+VALUE(LEFT(C34,LEN(C34)-1))>=总览!$L$12),总览!$M$12,IF(AND(总览!$J$12<>"",B34*100+VALUE(LEFT(C34,LEN(C34)-1))>=总览!$J$12),总览!$K$12,IF(AND(总览!$H$12<>"",B34*100+VALUE(LEFT(C34,LEN(C34)-1))>=总览!$H$12),总览!$I$12,IF(AND(总览!$F$12<>"",B34*100+VALUE(LEFT(C34,LEN(C34)-1))>=总览!$F$12),总览!$G$12,IF(AND(总览!$D$12<>"",B34*100+VALUE(LEFT(C34,LEN(C34)-1))>=总览!$D$12),总览!$E$12,总览!$B$12))))),0) | K34: =IF(AND(B34=2026,C34="5月"),120000,IF(AND(B34=2027,C34="9月"),30000,IF(C34="10月",IF(AND(总览!$L$13<>"",B34*100+VALUE(LEFT(C34,LEN(C34)-1))>=总览!$L$13),总览!$M$13,IF(AND(总览!$J$13<>"",B34*100+VALUE(LEFT(C34,LEN(C34)-1))>=总览!$J$13),总览!$K$13,IF(AND(总览!$H$13<>"",B34*100+VALUE(LEFT(C34,LEN(C34)-1))>=总览!$H$13),总览!$I$13,IF(AND(总览!$F$13<>"",B34*100+VALUE(LEFT(C34,LEN(C34)-1))>=总览!$F$13),总览!$G$13,IF(AND(总览!$D$13<>"",B34*100+VALUE(LEFT(C34,LEN(C34)-1))>=总览!$D$13),总览!$E$13,总览!$B$13))))),0))) | L34: 年度旅游 | M34: =SUM(H34:K34) | N34: =G34-M34 | O34: =O33+N34
A35: 34 | B35: 2028 | C35: 11月 | D35: =IF(AND(总览!$L$6<>"",B35*100+VALUE(LEFT(C35,LEN(C35)-1))>=总览!$L$6),总览!$M$6,IF(AND(总览!$J$6<>"",B35*100+VALUE(LEFT(C35,LEN(C35)-1))>=总览!$J$6),总览!$K$6,IF(AND(总览!$H$6<>"",B35*100+VALUE(LEFT(C35,LEN(C35)-1))>=总览!$H$6),总览!$I$6,IF(AND(总览!$F$6<>"",B35*100+VALUE(LEFT(C35,LEN(C35)-1))>=总览!$F$6),总览!$G$6,IF(AND(总览!$D$6<>"",B35*100+VALUE(LEFT(C35,LEN(C35)-1))>=总览!$D$6),总览!$E$6,总览!$B$6))))) | E35: =IF(C35="12月",IF(AND(总览!$L$7<>"",B35*100+VALUE(LEFT(C35,LEN(C35)-1))>=总览!$L$7),总览!$M$7,IF(AND(总览!$J$7<>"",B35*100+VALUE(LEFT(C35,LEN(C35)-1))>=总览!$J$7),总览!$K$7,IF(AND(总览!$H$7<>"",B35*100+VALUE(LEFT(C35,LEN(C35)-1))>=总览!$H$7),总览!$I$7,IF(AND(总览!$F$7<>"",B35*100+VALUE(LEFT(C35,LEN(C35)-1))>=总览!$F$7),总览!$G$7,IF(AND(总览!$D$7<>"",B35*100+VALUE(LEFT(C35,LEN(C35)-1))>=总览!$D$7),总览!$E$7,总览!$B$7))))),0) | F35: =ROUND(O34*总览!$B$14/12,0) | G35: =D35+E35+F35 | H35: =IF(OR(B35>2027,AND(B35=2027,VALUE(LEFT(C35,LEN(C35)-1))>=9)),IF(AND(总览!$L$10<>"",B35*100+VALUE(LEFT(C35,LEN(C35)-1))>=总览!$L$10),总览!$M$10,IF(AND(总览!$J$10<>"",B35*100+VALUE(LEFT(C35,LEN(C35)-1))>=总览!$J$10),总览!$K$10,IF(AND(总览!$H$10<>"",B35*100+VALUE(LEFT(C35,LEN(C35)-1))>=总览!$H$10),总览!$I$10,IF(AND(总览!$F$10<>"",B35*100+VALUE(LEFT(C35,LEN(C35)-1))>=总览!$F$10),总览!$G$10,IF(AND(总览!$D$10<>"",B35*100+VALUE(LEFT(C35,LEN(C35)-1))>=总览!$D$10),总览!$E$10,总览!$B$10))))),IF(AND(总览!$L$9<>"",B35*100+VALUE(LEFT(C35,LEN(C35)-1))>=总览!$L$9),总览!$M$9,IF(AND(总览!$J$9<>"",B35*100+VALUE(LEFT(C35,LEN(C35)-1))>=总览!$J$9),总览!$K$9,IF(AND(总览!$H$9<>"",B35*100+VALUE(LEFT(C35,LEN(C35)-1))>=总览!$H$9),总览!$I$9,IF(AND(总览!$F$9<>"",B35*100+VALUE(LEFT(C35,LEN(C35)-1))>=总览!$F$9),总览!$G$9,IF(AND(总览!$D$9<>"",B35*100+VALUE(LEFT(C35,LEN(C35)-1))>=总览!$D$9),总览!$E$9,总览!$B$9)))))) | I35: =IF(AND(总览!$L$11<>"",B35*100+VALUE(LEFT(C35,LEN(C35)-1))>=总览!$L$11),总览!$M$11,IF(AND(总览!$J$11<>"",B35*100+VALUE(LEFT(C35,LEN(C35)-1))>=总览!$J$11),总览!$K$11,IF(AND(总览!$H$11<>"",B35*100+VALUE(LEFT(C35,LEN(C35)-1))>=总览!$H$11),总览!$I$11,IF(AND(总览!$F$11<>"",B35*100+VALUE(LEFT(C35,LEN(C35)-1))>=总览!$F$11),总览!$G$11,IF(AND(总览!$D$11<>"",B35*100+VALUE(LEFT(C35,LEN(C35)-1))>=总览!$D$11),总览!$E$11,总览!$B$11))))) | J35: =IF(OR(B35>2027,AND(B35=2027,VALUE(LEFT(C35,LEN(C35)-1))>=9)),IF(AND(总览!$L$12<>"",B35*100+VALUE(LEFT(C35,LEN(C35)-1))>=总览!$L$12),总览!$M$12,IF(AND(总览!$J$12<>"",B35*100+VALUE(LEFT(C35,LEN(C35)-1))>=总览!$J$12),总览!$K$12,IF(AND(总览!$H$12<>"",B35*100+VALUE(LEFT(C35,LEN(C35)-1))>=总览!$H$12),总览!$I$12,IF(AND(总览!$F$12<>"",B35*100+VALUE(LEFT(C35,LEN(C35)-1))>=总览!$F$12),总览!$G$12,IF(AND(总览!$D$12<>"",B35*100+VALUE(LEFT(C35,LEN(C35)-1))>=总览!$D$12),总览!$E$12,总览!$B$12))))),0) | K35: =IF(AND(B35=2026,C35="5月"),120000,IF(AND(B35=2027,C35="9月"),30000,IF(C35="10月",IF(AND(总览!$L$13<>"",B35*100+VALUE(LEFT(C35,LEN(C35)-1))>=总览!$L$13),总览!$M$13,IF(AND(总览!$J$13<>"",B35*100+VALUE(LEFT(C35,LEN(C35)-1))>=总览!$J$13),总览!$K$13,IF(AND(总览!$H$13<>"",B35*100+VALUE(LEFT(C35,LEN(C35)-1))>=总览!$H$13),总览!$I$13,IF(AND(总览!$F$13<>"",B35*100+VALUE(LEFT(C35,LEN(C35)-1))>=总览!$F$13),总览!$G$13,IF(AND(总览!$D$13<>"",B35*100+VALUE(LEFT(C35,LEN(C35)-1))>=总览!$D$13),总览!$E$13,总览!$B$13))))),0))) | M35: =SUM(H35:K35) | N35: =G35-M35 | O35: =O34+N35
A36: 35 | B36: 2028 | C36: 12月 | D36: =IF(AND(总览!$L$6<>"",B36*100+VALUE(LEFT(C36,LEN(C36)-1))>=总览!$L$6),总览!$M$6,IF(AND(总览!$J$6<>"",B36*100+VALUE(LEFT(C36,LEN(C36)-1))>=总览!$J$6),总览!$K$6,IF(AND(总览!$H$6<>"",B36*100+VALUE(LEFT(C36,LEN(C36)-1))>=总览!$H$6),总览!$I$6,IF(AND(总览!$F$6<>"",B36*100+VALUE(LEFT(C36,LEN(C36)-1))>=总览!$F$6),总览!$G$6,IF(AND(总览!$D$6<>"",B36*100+VALUE(LEFT(C36,LEN(C36)-1))>=总览!$D$6),总览!$E$6,总览!$B$6))))) | E36: =IF(C36="12月",IF(AND(总览!$L$7<>"",B36*100+VALUE(LEFT(C36,LEN(C36)-1))>=总览!$L$7),总览!$M$7,IF(AND(总览!$J$7<>"",B36*100+VALUE(LEFT(C36,LEN(C36)-1))>=总览!$J$7),总览!$K$7,IF(AND(总览!$H$7<>"",B36*100+VALUE(LEFT(C36,LEN(C36)-1))>=总览!$H$7),总览!$I$7,IF(AND(总览!$F$7<>"",B36*100+VALUE(LEFT(C36,LEN(C36)-1))>=总览!$F$7),总览!$G$7,IF(AND(总览!$D$7<>"",B36*100+VALUE(LEFT(C36,LEN(C36)-1))>=总览!$D$7),总览!$E$7,总览!$B$7))))),0) | F36: =ROUND(O35*总览!$B$14/12,0) | G36: =D36+E36+F36 | H36: =IF(OR(B36>2027,AND(B36=2027,VALUE(LEFT(C36,LEN(C36)-1))>=9)),IF(AND(总览!$L$10<>"",B36*100+VALUE(LEFT(C36,LEN(C36)-1))>=总览!$L$10),总览!$M$10,IF(AND(总览!$J$10<>"",B36*100+VALUE(LEFT(C36,LEN(C36)-1))>=总览!$J$10),总览!$K$10,IF(AND(总览!$H$10<>"",B36*100+VALUE(LEFT(C36,LEN(C36)-1))>=总览!$H$10),总览!$I$10,IF(AND(总览!$F$10<>"",B36*100+VALUE(LEFT(C36,LEN(C36)-1))>=总览!$F$10),总览!$G$10,IF(AND(总览!$D$10<>"",B36*100+VALUE(LEFT(C36,LEN(C36)-1))>=总览!$D$10),总览!$E$10,总览!$B$10))))),IF(AND(总览!$L$9<>"",B36*100+VALUE(LEFT(C36,LEN(C36)-1))>=总览!$L$9),总览!$M$9,IF(AND(总览!$J$9<>"",B36*100+VALUE(LEFT(C36,LEN(C36)-1))>=总览!$J$9),总览!$K$9,IF(AND(总览!$H$9<>"",B36*100+VALUE(LEFT(C36,LEN(C36)-1))>=总览!$H$9),总览!$I$9,IF(AND(总览!$F$9<>"",B36*100+VALUE(LEFT(C36,LEN(C36)-1))>=总览!$F$9),总览!$G$9,IF(AND(总览!$D$9<>"",B36*100+VALUE(LEFT(C36,LEN(C36)-1))>=总览!$D$9),总览!$E$9,总览!$B$9)))))) | I36: =IF(AND(总览!$L$11<>"",B36*100+VALUE(LEFT(C36,LEN(C36)-1))>=总览!$L$11),总览!$M$11,IF(AND(总览!$J$11<>"",B36*100+VALUE(LEFT(C36,LEN(C36)-1))>=总览!$J$11),总览!$K$11,IF(AND(总览!$H$11<>"",B36*100+VALUE(LEFT(C36,LEN(C36)-1))>=总览!$H$11),总览!$I$11,IF(AND(总览!$F$11<>"",B36*100+VALUE(LEFT(C36,LEN(C36)-1))>=总览!$F$11),总览!$G$11,IF(AND(总览!$D$11<>"",B36*100+VALUE(LEFT(C36,LEN(C36)-1))>=总览!$D$11),总览!$E$11,总览!$B$11))))) | J36: =IF(OR(B36>2027,AND(B36=2027,VALUE(LEFT(C36,LEN(C36)-1))>=9)),IF(AND(总览!$L$12<>"",B36*100+VALUE(LEFT(C36,LEN(C36)-1))>=总览!$L$12),总览!$M$12,IF(AND(总览!$J$12<>"",B36*100+VALUE(LEFT(C36,LEN(C36)-1))>=总览!$J$12),总览!$K$12,IF(AND(总览!$H$12<>"",B36*100+VALUE(LEFT(C36,LEN(C36)-1))>=总览!$H$12),总览!$I$12,IF(AND(总览!$F$12<>"",B36*100+VALUE(LEFT(C36,LEN(C36)-1))>=总览!$F$12),总览!$G$12,IF(AND(总览!$D$12<>"",B36*100+VALUE(LEFT(C36,LEN(C36)-1))>=总览!$D$12),总览!$E$12,总览!$B$12))))),0) | K36: =IF(AND(B36=2026,C36="5月"),120000,IF(AND(B36=2027,C36="9月"),30000,IF(C36="10月",IF(AND(总览!$L$13<>"",B36*100+VALUE(LEFT(C36,LEN(C36)-1))>=总览!$L$13),总览!$M$13,IF(AND(总览!$J$13<>"",B36*100+VALUE(LEFT(C36,LEN(C36)-1))>=总览!$J$13),总览!$K$13,IF(AND(总览!$H$13<>"",B36*100+VALUE(LEFT(C36,LEN(C36)-1))>=总览!$H$13),总览!$I$13,IF(AND(总览!$F$13<>"",B36*100+VALUE(LEFT(C36,LEN(C36)-1))>=总览!$F$13),总览!$G$13,IF(AND(总览!$D$13<>"",B36*100+VALUE(LEFT(C36,LEN(C36)-1))>=总览!$D$13),总览!$E$13,总览!$B$13))))),0))) | M36: =SUM(H36:K36) | N36: =G36-M36 | O36: =O35+N36
A37: 36 | B37: 2029 | C37: 1月 | D37: =IF(AND(总览!$L$6<>"",B37*100+VALUE(LEFT(C37,LEN(C37)-1))>=总览!$L$6),总览!$M$6,IF(AND(总览!$J$6<>"",B37*100+VALUE(LEFT(C37,LEN(C37)-1))>=总览!$J$6),总览!$K$6,IF(AND(总览!$H$6<>"",B37*100+VALUE(LEFT(C37,LEN(C37)-1))>=总览!$H$6),总览!$I$6,IF(AND(总览!$F$6<>"",B37*100+VALUE(LEFT(C37,LEN(C37)-1))>=总览!$F$6),总览!$G$6,IF(AND(总览!$D$6<>"",B37*100+VALUE(LEFT(C37,LEN(C37)-1))>=总览!$D$6),总览!$E$6,总览!$B$6))))) | E37: =IF(C37="12月",IF(AND(总览!$L$7<>"",B37*100+VALUE(LEFT(C37,LEN(C37)-1))>=总览!$L$7),总览!$M$7,IF(AND(总览!$J$7<>"",B37*100+VALUE(LEFT(C37,LEN(C37)-1))>=总览!$J$7),总览!$K$7,IF(AND(总览!$H$7<>"",B37*100+VALUE(LEFT(C37,LEN(C37)-1))>=总览!$H$7),总览!$I$7,IF(AND(总览!$F$7<>"",B37*100+VALUE(LEFT(C37,LEN(C37)-1))>=总览!$F$7),总览!$G$7,IF(AND(总览!$D$7<>"",B37*100+VALUE(LEFT(C37,LEN(C37)-1))>=总览!$D$7),总览!$E$7,总览!$B$7))))),0) | F37: =ROUND(O36*总览!$B$14/12,0) | G37: =D37+E37+F37 | H37: =IF(OR(B37>2027,AND(B37=2027,VALUE(LEFT(C37,LEN(C37)-1))>=9)),IF(AND(总览!$L$10<>"",B37*100+VALUE(LEFT(C37,LEN(C37)-1))>=总览!$L$10),总览!$M$10,IF(AND(总览!$J$10<>"",B37*100+VALUE(LEFT(C37,LEN(C37)-1))>=总览!$J$10),总览!$K$10,IF(AND(总览!$H$10<>"",B37*100+VALUE(LEFT(C37,LEN(C37)-1))>=总览!$H$10),总览!$I$10,IF(AND(总览!$F$10<>"",B37*100+VALUE(LEFT(C37,LEN(C37)-1))>=总览!$F$10),总览!$G$10,IF(AND(总览!$D$10<>"",B37*100+VALUE(LEFT(C37,LEN(C37)-1))>=总览!$D$10),总览!$E$10,总览!$B$10))))),IF(AND(总览!$L$9<>"",B37*100+VALUE(LEFT(C37,LEN(C37)-1))>=总览!$L$9),总览!$M$9,IF(AND(总览!$J$9<>"",B37*100+VALUE(LEFT(C37,LEN(C37)-1))>=总览!$J$9),总览!$K$9,IF(AND(总览!$H$9<>"",B37*100+VALUE(LEFT(C37,LEN(C37)-1))>=总览!$H$9),总览!$I$9,IF(AND(总览!$F$9<>"",B37*100+VALUE(LEFT(C37,LEN(C37)-1))>=总览!$F$9),总览!$G$9,IF(AND(总览!$D$9<>"",B37*100+VALUE(LEFT(C37,LEN(C37)-1))>=总览!$D$9),总览!$E$9,总览!$B$9)))))) | I37: =IF(AND(总览!$L$11<>"",B37*100+VALUE(LEFT(C37,LEN(C37)-1))>=总览!$L$11),总览!$M$11,IF(AND(总览!$J$11<>"",B37*100+VALUE(LEFT(C37,LEN(C37)-1))>=总览!$J$11),总览!$K$11,IF(AND(总览!$H$11<>"",B37*100+VALUE(LEFT(C37,LEN(C37)-1))>=总览!$H$11),总览!$I$11,IF(AND(总览!$F$11<>"",B37*100+VALUE(LEFT(C37,LEN(C37)-1))>=总览!$F$11),总览!$G$11,IF(AND(总览!$D$11<>"",B37*100+VALUE(LEFT(C37,LEN(C37)-1))>=总览!$D$11),总览!$E$11,总览!$B$11))))) | J37: =IF(OR(B37>2027,AND(B37=2027,VALUE(LEFT(C37,LEN(C37)-1))>=9)),IF(AND(总览!$L$12<>"",B37*100+VALUE(LEFT(C37,LEN(C37)-1))>=总览!$L$12),总览!$M$12,IF(AND(总览!$J$12<>"",B37*100+VALUE(LEFT(C37,LEN(C37)-1))>=总览!$J$12),总览!$K$12,IF(AND(总览!$H$12<>"",B37*100+VALUE(LEFT(C37,LEN(C37)-1))>=总览!$H$12),总览!$I$12,IF(AND(总览!$F$12<>"",B37*100+VALUE(LEFT(C37,LEN(C37)-1))>=总览!$F$12),总览!$G$12,IF(AND(总览!$D$12<>"",B37*100+VALUE(LEFT(C37,LEN(C37)-1))>=总览!$D$12),总览!$E$12,总览!$B$12))))),0) | K37: =IF(AND(B37=2026,C37="5月"),120000,IF(AND(B37=2027,C37="9月"),30000,IF(C37="10月",IF(AND(总览!$L$13<>"",B37*100+VALUE(LEFT(C37,LEN(C37)-1))>=总览!$L$13),总览!$M$13,IF(AND(总览!$J$13<>"",B37*100+VALUE(LEFT(C37,LEN(C37)-1))>=总览!$J$13),总览!$K$13,IF(AND(总览!$H$13<>"",B37*100+VALUE(LEFT(C37,LEN(C37)-1))>=总览!$H$13),总览!$I$13,IF(AND(总览!$F$13<>"",B37*100+VALUE(LEFT(C37,LEN(C37)-1))>=总览!$F$13),总览!$G$13,IF(AND(总览!$D$13<>"",B37*100+VALUE(LEFT(C37,LEN(C37)-1))>=总览!$D$13),总览!$E$13,总览!$B$13))))),0))) | M37: =SUM(H37:K37) | N37: =G37-M37 | O37: =O36+N37
A38: 37 | B38: 2029 | C38: 2月 | D38: =IF(AND(总览!$L$6<>"",B38*100+VALUE(LEFT(C38,LEN(C38)-1))>=总览!$L$6),总览!$M$6,IF(AND(总览!$J$6<>"",B38*100+VALUE(LEFT(C38,LEN(C38)-1))>=总览!$J$6),总览!$K$6,IF(AND(总览!$H$6<>"",B38*100+VALUE(LEFT(C38,LEN(C38)-1))>=总览!$H$6),总览!$I$6,IF(AND(总览!$F$6<>"",B38*100+VALUE(LEFT(C38,LEN(C38)-1))>=总览!$F$6),总览!$G$6,IF(AND(总览!$D$6<>"",B38*100+VALUE(LEFT(C38,LEN(C38)-1))>=总览!$D$6),总览!$E$6,总览!$B$6))))) | E38: =IF(C38="12月",IF(AND(总览!$L$7<>"",B38*100+VALUE(LEFT(C38,LEN(C38)-1))>=总览!$L$7),总览!$M$7,IF(AND(总览!$J$7<>"",B38*100+VALUE(LEFT(C38,LEN(C38)-1))>=总览!$J$7),总览!$K$7,IF(AND(总览!$H$7<>"",B38*100+VALUE(LEFT(C38,LEN(C38)-1))>=总览!$H$7),总览!$I$7,IF(AND(总览!$F$7<>"",B38*100+VALUE(LEFT(C38,LEN(C38)-1))>=总览!$F$7),总览!$G$7,IF(AND(总览!$D$7<>"",B38*100+VALUE(LEFT(C38,LEN(C38)-1))>=总览!$D$7),总览!$E$7,总览!$B$7))))),0) | F38: =ROUND(O37*总览!$B$14/12,0) | G38: =D38+E38+F38 | H38: =IF(OR(B38>2027,AND(B38=2027,VALUE(LEFT(C38,LEN(C38)-1))>=9)),IF(AND(总览!$L$10<>"",B38*100+VALUE(LEFT(C38,LEN(C38)-1))>=总览!$L$10),总览!$M$10,IF(AND(总览!$J$10<>"",B38*100+VALUE(LEFT(C38,LEN(C38)-1))>=总览!$J$10),总览!$K$10,IF(AND(总览!$H$10<>"",B38*100+VALUE(LEFT(C38,LEN(C38)-1))>=总览!$H$10),总览!$I$10,IF(AND(总览!$F$10<>"",B38*100+VALUE(LEFT(C38,LEN(C38)-1))>=总览!$F$10),总览!$G$10,IF(AND(总览!$D$10<>"",B38*100+VALUE(LEFT(C38,LEN(C38)-1))>=总览!$D$10),总览!$E$10,总览!$B$10))))),IF(AND(总览!$L$9<>"",B38*100+VALUE(LEFT(C38,LEN(C38)-1))>=总览!$L$9),总览!$M$9,IF(AND(总览!$J$9<>"",B38*100+VALUE(LEFT(C38,LEN(C38)-1))>=总览!$J$9),总览!$K$9,IF(AND(总览!$H$9<>"",B38*100+VALUE(LEFT(C38,LEN(C38)-1))>=总览!$H$9),总览!$I$9,IF(AND(总览!$F$9<>"",B38*100+VALUE(LEFT(C38,LEN(C38)-1))>=总览!$F$9),总览!$G$9,IF(AND(总览!$D$9<>"",B38*100+VALUE(LEFT(C38,LEN(C38)-1))>=总览!$D$9),总览!$E$9,总览!$B$9)))))) | I38: =IF(AND(总览!$L$11<>"",B38*100+VALUE(LEFT(C38,LEN(C38)-1))>=总览!$L$11),总览!$M$11,IF(AND(总览!$J$11<>"",B38*100+VALUE(LEFT(C38,LEN(C38)-1))>=总览!$J$11),总览!$K$11,IF(AND(总览!$H$11<>"",B38*100+VALUE(LEFT(C38,LEN(C38)-1))>=总览!$H$11),总览!$I$11,IF(AND(总览!$F$11<>"",B38*100+VALUE(LEFT(C38,LEN(C38)-1))>=总览!$F$11),总览!$G$11,IF(AND(总览!$D$11<>"",B38*100+VALUE(LEFT(C38,LEN(C38)-1))>=总览!$D$11),总览!$E$11,总览!$B$11))))) | J38: =IF(OR(B38>2027,AND(B38=2027,VALUE(LEFT(C38,LEN(C38)-1))>=9)),IF(AND(总览!$L$12<>"",B38*100+VALUE(LEFT(C38,LEN(C38)-1))>=总览!$L$12),总览!$M$12,IF(AND(总览!$J$12<>"",B38*100+VALUE(LEFT(C38,LEN(C38)-1))>=总览!$J$12),总览!$K$12,IF(AND(总览!$H$12<>"",B38*100+VALUE(LEFT(C38,LEN(C38)-1))>=总览!$H$12),总览!$I$12,IF(AND(总览!$F$12<>"",B38*100+VALUE(LEFT(C38,LEN(C38)-1))>=总览!$F$12),总览!$G$12,IF(AND(总览!$D$12<>"",B38*100+VALUE(LEFT(C38,LEN(C38)-1))>=总览!$D$12),总览!$E$12,总览!$B$12))))),0) | K38: =IF(AND(B38=2026,C38="5月"),120000,IF(AND(B38=2027,C38="9月"),30000,IF(C38="10月",IF(AND(总览!$L$13<>"",B38*100+VALUE(LEFT(C38,LEN(C38)-1))>=总览!$L$13),总览!$M$13,IF(AND(总览!$J$13<>"",B38*100+VALUE(LEFT(C38,LEN(C38)-1))>=总览!$J$13),总览!$K$13,IF(AND(总览!$H$13<>"",B38*100+VALUE(LEFT(C38,LEN(C38)-1))>=总览!$H$13),总览!$I$13,IF(AND(总览!$F$13<>"",B38*100+VALUE(LEFT(C38,LEN(C38)-1))>=总览!$F$13),总览!$G$13,IF(AND(总览!$D$13<>"",B38*100+VALUE(LEFT(C38,LEN(C38)-1))>=总览!$D$13),总览!$E$13,总览!$B$13))))),0))) | M38: =SUM(H38:K38) | N38: =G38-M38 | O38: =O37+N38
A39: 38 | B39: 2029 | C39: 3月 | D39: =IF(AND(总览!$L$6<>"",B39*100+VALUE(LEFT(C39,LEN(C39)-1))>=总览!$L$6),总览!$M$6,IF(AND(总览!$J$6<>"",B39*100+VALUE(LEFT(C39,LEN(C39)-1))>=总览!$J$6),总览!$K$6,IF(AND(总览!$H$6<>"",B39*100+VALUE(LEFT(C39,LEN(C39)-1))>=总览!$H$6),总览!$I$6,IF(AND(总览!$F$6<>"",B39*100+VALUE(LEFT(C39,LEN(C39)-1))>=总览!$F$6),总览!$G$6,IF(AND(总览!$D$6<>"",B39*100+VALUE(LEFT(C39,LEN(C39)-1))>=总览!$D$6),总览!$E$6,总览!$B$6))))) | E39: =IF(C39="12月",IF(AND(总览!$L$7<>"",B39*100+VALUE(LEFT(C39,LEN(C39)-1))>=总览!$L$7),总览!$M$7,IF(AND(总览!$J$7<>"",B39*100+VALUE(LEFT(C39,LEN(C39)-1))>=总览!$J$7),总览!$K$7,IF(AND(总览!$H$7<>"",B39*100+VALUE(LEFT(C39,LEN(C39)-1))>=总览!$H$7),总览!$I$7,IF(AND(总览!$F$7<>"",B39*100+VALUE(LEFT(C39,LEN(C39)-1))>=总览!$F$7),总览!$G$7,IF(AND(总览!$D$7<>"",B39*100+VALUE(LEFT(C39,LEN(C39)-1))>=总览!$D$7),总览!$E$7,总览!$B$7))))),0) | F39: =ROUND(O38*总览!$B$14/12,0) | G39: =D39+E39+F39 | H39: =IF(OR(B39>2027,AND(B39=2027,VALUE(LEFT(C39,LEN(C39)-1))>=9)),IF(AND(总览!$L$10<>"",B39*100+VALUE(LEFT(C39,LEN(C39)-1))>=总览!$L$10),总览!$M$10,IF(AND(总览!$J$10<>"",B39*100+VALUE(LEFT(C39,LEN(C39)-1))>=总览!$J$10),总览!$K$10,IF(AND(总览!$H$10<>"",B39*100+VALUE(LEFT(C39,LEN(C39)-1))>=总览!$H$10),总览!$I$10,IF(AND(总览!$F$10<>"",B39*100+VALUE(LEFT(C39,LEN(C39)-1))>=总览!$F$10),总览!$G$10,IF(AND(总览!$D$10<>"",B39*100+VALUE(LEFT(C39,LEN(C39)-1))>=总览!$D$10),总览!$E$10,总览!$B$10))))),IF(AND(总览!$L$9<>"",B39*100+VALUE(LEFT(C39,LEN(C39)-1))>=总览!$L$9),总览!$M$9,IF(AND(总览!$J$9<>"",B39*100+VALUE(LEFT(C39,LEN(C39)-1))>=总览!$J$9),总览!$K$9,IF(AND(总览!$H$9<>"",B39*100+VALUE(LEFT(C39,LEN(C39)-1))>=总览!$H$9),总览!$I$9,IF(AND(总览!$F$9<>"",B39*100+VALUE(LEFT(C39,LEN(C39)-1))>=总览!$F$9),总览!$G$9,IF(AND(总览!$D$9<>"",B39*100+VALUE(LEFT(C39,LEN(C39)-1))>=总览!$D$9),总览!$E$9,总览!$B$9)))))) | I39: =IF(AND(总览!$L$11<>"",B39*100+VALUE(LEFT(C39,LEN(C39)-1))>=总览!$L$11),总览!$M$11,IF(AND(总览!$J$11<>"",B39*100+VALUE(LEFT(C39,LEN(C39)-1))>=总览!$J$11),总览!$K$11,IF(AND(总览!$H$11<>"",B39*100+VALUE(LEFT(C39,LEN(C39)-1))>=总览!$H$11),总览!$I$11,IF(AND(总览!$F$11<>"",B39*100+VALUE(LEFT(C39,LEN(C39)-1))>=总览!$F$11),总览!$G$11,IF(AND(总览!$D$11<>"",B39*100+VALUE(LEFT(C39,LEN(C39)-1))>=总览!$D$11),总览!$E$11,总览!$B$11))))) | J39: =IF(OR(B39>2027,AND(B39=2027,VALUE(LEFT(C39,LEN(C39)-1))>=9)),IF(AND(总览!$L$12<>"",B39*100+VALUE(LEFT(C39,LEN(C39)-1))>=总览!$L$12),总览!$M$12,IF(AND(总览!$J$12<>"",B39*100+VALUE(LEFT(C39,LEN(C39)-1))>=总览!$J$12),总览!$K$12,IF(AND(总览!$H$12<>"",B39*100+VALUE(LEFT(C39,LEN(C39)-1))>=总览!$H$12),总览!$I$12,IF(AND(总览!$F$12<>"",B39*100+VALUE(LEFT(C39,LEN(C39)-1))>=总览!$F$12),总览!$G$12,IF(AND(总览!$D$12<>"",B39*100+VALUE(LEFT(C39,LEN(C39)-1))>=总览!$D$12),总览!$E$12,总览!$B$12))))),0) | K39: =IF(AND(B39=2026,C39="5月"),120000,IF(AND(B39=2027,C39="9月"),30000,IF(C39="10月",IF(AND(总览!$L$13<>"",B39*100+VALUE(LEFT(C39,LEN(C39)-1))>=总览!$L$13),总览!$M$13,IF(AND(总览!$J$13<>"",B39*100+VALUE(LEFT(C39,LEN(C39)-1))>=总览!$J$13),总览!$K$13,IF(AND(总览!$H$13<>"",B39*100+VALUE(LEFT(C39,LEN(C39)-1))>=总览!$H$13),总览!$I$13,IF(AND(总览!$F$13<>"",B39*100+VALUE(LEFT(C39,LEN(C39)-1))>=总览!$F$13),总览!$G$13,IF(AND(总览!$D$13<>"",B39*100+VALUE(LEFT(C39,LEN(C39)-1))>=总览!$D$13),总览!$E$13,总览!$B$13))))),0))) | M39: =SUM(H39:K39) | N39: =G39-M39 | O39: =O38+N39
A40: 39 | B40: 2029 | C40: 4月 | D40: =IF(AND(总览!$L$6<>"",B40*100+VALUE(LEFT(C40,LEN(C40)-1))>=总览!$L$6),总览!$M$6,IF(AND(总览!$J$6<>"",B40*100+VALUE(LEFT(C40,LEN(C40)-1))>=总览!$J$6),总览!$K$6,IF(AND(总览!$H$6<>"",B40*100+VALUE(LEFT(C40,LEN(C40)-1))>=总览!$H$6),总览!$I$6,IF(AND(总览!$F$6<>"",B40*100+VALUE(LEFT(C40,LEN(C40)-1))>=总览!$F$6),总览!$G$6,IF(AND(总览!$D$6<>"",B40*100+VALUE(LEFT(C40,LEN(C40)-1))>=总览!$D$6),总览!$E$6,总览!$B$6))))) | E40: =IF(C40="12月",IF(AND(总览!$L$7<>"",B40*100+VALUE(LEFT(C40,LEN(C40)-1))>=总览!$L$7),总览!$M$7,IF(AND(总览!$J$7<>"",B40*100+VALUE(LEFT(C40,LEN(C40)-1))>=总览!$J$7),总览!$K$7,IF(AND(总览!$H$7<>"",B40*100+VALUE(LEFT(C40,LEN(C40)-1))>=总览!$H$7),总览!$I$7,IF(AND(总览!$F$7<>"",B40*100+VALUE(LEFT(C40,LEN(C40)-1))>=总览!$F$7),总览!$G$7,IF(AND(总览!$D$7<>"",B40*100+VALUE(LEFT(C40,LEN(C40)-1))>=总览!$D$7),总览!$E$7,总览!$B$7))))),0) | F40: =ROUND(O39*总览!$B$14/12,0) | G40: =D40+E40+F40 | H40: =IF(OR(B40>2027,AND(B40=2027,VALUE(LEFT(C40,LEN(C40)-1))>=9)),IF(AND(总览!$L$10<>"",B40*100+VALUE(LEFT(C40,LEN(C40)-1))>=总览!$L$10),总览!$M$10,IF(AND(总览!$J$10<>"",B40*100+VALUE(LEFT(C40,LEN(C40)-1))>=总览!$J$10),总览!$K$10,IF(AND(总览!$H$10<>"",B40*100+VALUE(LEFT(C40,LEN(C40)-1))>=总览!$H$10),总览!$I$10,IF(AND(总览!$F$10<>"",B40*100+VALUE(LEFT(C40,LEN(C40)-1))>=总览!$F$10),总览!$G$10,IF(AND(总览!$D$10<>"",B40*100+VALUE(LEFT(C40,LEN(C40)-1))>=总览!$D$10),总览!$E$10,总览!$B$10))))),IF(AND(总览!$L$9<>"",B40*100+VALUE(LEFT(C40,LEN(C40)-1))>=总览!$L$9),总览!$M$9,IF(AND(总览!$J$9<>"",B40*100+VALUE(LEFT(C40,LEN(C40)-1))>=总览!$J$9),总览!$K$9,IF(AND(总览!$H$9<>"",B40*100+VALUE(LEFT(C40,LEN(C40)-1))>=总览!$H$9),总览!$I$9,IF(AND(总览!$F$9<>"",B40*100+VALUE(LEFT(C40,LEN(C40)-1))>=总览!$F$9),总览!$G$9,IF(AND(总览!$D$9<>"",B40*100+VALUE(LEFT(C40,LEN(C40)-1))>=总览!$D$9),总览!$E$9,总览!$B$9)))))) | I40: =IF(AND(总览!$L$11<>"",B40*100+VALUE(LEFT(C40,LEN(C40)-1))>=总览!$L$11),总览!$M$11,IF(AND(总览!$J$11<>"",B40*100+VALUE(LEFT(C40,LEN(C40)-1))>=总览!$J$11),总览!$K$11,IF(AND(总览!$H$11<>"",B40*100+VALUE(LEFT(C40,LEN(C40)-1))>=总览!$H$11),总览!$I$11,IF(AND(总览!$F$11<>"",B40*100+VALUE(LEFT(C40,LEN(C40)-1))>=总览!$F$11),总览!$G$11,IF(AND(总览!$D$11<>"",B40*100+VALUE(LEFT(C40,LEN(C40)-1))>=总览!$D$11),总览!$E$11,总览!$B$11))))) | J40: =IF(OR(B40>2027,AND(B40=2027,VALUE(LEFT(C40,LEN(C40)-1))>=9)),IF(AND(总览!$L$12<>"",B40*100+VALUE(LEFT(C40,LEN(C40)-1))>=总览!$L$12),总览!$M$12,IF(AND(总览!$J$12<>"",B40*100+VALUE(LEFT(C40,LEN(C40)-1))>=总览!$J$12),总览!$K$12,IF(AND(总览!$H$12<>"",B40*100+VALUE(LEFT(C40,LEN(C40)-1))>=总览!$H$12),总览!$I$12,IF(AND(总览!$F$12<>"",B40*100+VALUE(LEFT(C40,LEN(C40)-1))>=总览!$F$12),总览!$G$12,IF(AND(总览!$D$12<>"",B40*100+VALUE(LEFT(C40,LEN(C40)-1))>=总览!$D$12),总览!$E$12,总览!$B$12))))),0) | K40: =IF(AND(B40=2026,C40="5月"),120000,IF(AND(B40=2027,C40="9月"),30000,IF(C40="10月",IF(AND(总览!$L$13<>"",B40*100+VALUE(LEFT(C40,LEN(C40)-1))>=总览!$L$13),总览!$M$13,IF(AND(总览!$J$13<>"",B40*100+VALUE(LEFT(C40,LEN(C40)-1))>=总览!$J$13),总览!$K$13,IF(AND(总览!$H$13<>"",B40*100+VALUE(LEFT(C40,LEN(C40)-1))>=总览!$H$13),总览!$I$13,IF(AND(总览!$F$13<>"",B40*100+VALUE(LEFT(C40,LEN(C40)-1))>=总览!$F$13),总览!$G$13,IF(AND(总览!$D$13<>"",B40*100+VALUE(LEFT(C40,LEN(C40)-1))>=总览!$D$13),总览!$E$13,总览!$B$13))))),0))) | M40: =SUM(H40:K40) | N40: =G40-M40 | O40: =O39+N40
A41: 40 | B41: 2029 | C41: 5月 | D41: =IF(AND(总览!$L$6<>"",B41*100+VALUE(LEFT(C41,LEN(C41)-1))>=总览!$L$6),总览!$M$6,IF(AND(总览!$J$6<>"",B41*100+VALUE(LEFT(C41,LEN(C41)-1))>=总览!$J$6),总览!$K$6,IF(AND(总览!$H$6<>"",B41*100+VALUE(LEFT(C41,LEN(C41)-1))>=总览!$H$6),总览!$I$6,IF(AND(总览!$F$6<>"",B41*100+VALUE(LEFT(C41,LEN(C41)-1))>=总览!$F$6),总览!$G$6,IF(AND(总览!$D$6<>"",B41*100+VALUE(LEFT(C41,LEN(C41)-1))>=总览!$D$6),总览!$E$6,总览!$B$6))))) | E41: =IF(C41="12月",IF(AND(总览!$L$7<>"",B41*100+VALUE(LEFT(C41,LEN(C41)-1))>=总览!$L$7),总览!$M$7,IF(AND(总览!$J$7<>"",B41*100+VALUE(LEFT(C41,LEN(C41)-1))>=总览!$J$7),总览!$K$7,IF(AND(总览!$H$7<>"",B41*100+VALUE(LEFT(C41,LEN(C41)-1))>=总览!$H$7),总览!$I$7,IF(AND(总览!$F$7<>"",B41*100+VALUE(LEFT(C41,LEN(C41)-1))>=总览!$F$7),总览!$G$7,IF(AND(总览!$D$7<>"",B41*100+VALUE(LEFT(C41,LEN(C41)-1))>=总览!$D$7),总览!$E$7,总览!$B$7))))),0) | F41: =ROUND(O40*总览!$B$14/12,0) | G41: =D41+E41+F41 | H41: =IF(OR(B41>2027,AND(B41=2027,VALUE(LEFT(C41,LEN(C41)-1))>=9)),IF(AND(总览!$L$10<>"",B41*100+VALUE(LEFT(C41,LEN(C41)-1))>=总览!$L$10),总览!$M$10,IF(AND(总览!$J$10<>"",B41*100+VALUE(LEFT(C41,LEN(C41)-1))>=总览!$J$10),总览!$K$10,IF(AND(总览!$H$10<>"",B41*100+VALUE(LEFT(C41,LEN(C41)-1))>=总览!$H$10),总览!$I$10,IF(AND(总览!$F$10<>"",B41*100+VALUE(LEFT(C41,LEN(C41)-1))>=总览!$F$10),总览!$G$10,IF(AND(总览!$D$10<>"",B41*100+VALUE(LEFT(C41,LEN(C41)-1))>=总览!$D$10),总览!$E$10,总览!$B$10))))),IF(AND(总览!$L$9<>"",B41*100+VALUE(LEFT(C41,LEN(C41)-1))>=总览!$L$9),总览!$M$9,IF(AND(总览!$J$9<>"",B41*100+VALUE(LEFT(C41,LEN(C41)-1))>=总览!$J$9),总览!$K$9,IF(AND(总览!$H$9<>"",B41*100+VALUE(LEFT(C41,LEN(C41)-1))>=总览!$H$9),总览!$I$9,IF(AND(总览!$F$9<>"",B41*100+VALUE(LEFT(C41,LEN(C41)-1))>=总览!$F$9),总览!$G$9,IF(AND(总览!$D$9<>"",B41*100+VALUE(LEFT(C41,LEN(C41)-1))>=总览!$D$9),总览!$E$9,总览!$B$9)))))) | I41: =IF(AND(总览!$L$11<>"",B41*100+VALUE(LEFT(C41,LEN(C41)-1))>=总览!$L$11),总览!$M$11,IF(AND(总览!$J$11<>"",B41*100+VALUE(LEFT(C41,LEN(C41)-1))>=总览!$J$11),总览!$K$11,IF(AND(总览!$H$11<>"",B41*100+VALUE(LEFT(C41,LEN(C41)-1))>=总览!$H$11),总览!$I$11,IF(AND(总览!$F$11<>"",B41*100+VALUE(LEFT(C41,LEN(C41)-1))>=总览!$F$11),总览!$G$11,IF(AND(总览!$D$11<>"",B41*100+VALUE(LEFT(C41,LEN(C41)-1))>=总览!$D$11),总览!$E$11,总览!$B$11))))) | J41: =IF(OR(B41>2027,AND(B41=2027,VALUE(LEFT(C41,LEN(C41)-1))>=9)),IF(AND(总览!$L$12<>"",B41*100+VALUE(LEFT(C41,LEN(C41)-1))>=总览!$L$12),总览!$M$12,IF(AND(总览!$J$12<>"",B41*100+VALUE(LEFT(C41,LEN(C41)-1))>=总览!$J$12),总览!$K$12,IF(AND(总览!$H$12<>"",B41*100+VALUE(LEFT(C41,LEN(C41)-1))>=总览!$H$12),总览!$I$12,IF(AND(总览!$F$12<>"",B41*100+VALUE(LEFT(C41,LEN(C41)-1))>=总览!$F$12),总览!$G$12,IF(AND(总览!$D$12<>"",B41*100+VALUE(LEFT(C41,LEN(C41)-1))>=总览!$D$12),总览!$E$12,总览!$B$12))))),0) | K41: =IF(AND(B41=2026,C41="5月"),120000,IF(AND(B41=2027,C41="9月"),30000,IF(C41="10月",IF(AND(总览!$L$13<>"",B41*100+VALUE(LEFT(C41,LEN(C41)-1))>=总览!$L$13),总览!$M$13,IF(AND(总览!$J$13<>"",B41*100+VALUE(LEFT(C41,LEN(C41)-1))>=总览!$J$13),总览!$K$13,IF(AND(总览!$H$13<>"",B41*100+VALUE(LEFT(C41,LEN(C41)-1))>=总览!$H$13),总览!$I$13,IF(AND(总览!$F$13<>"",B41*100+VALUE(LEFT(C41,LEN(C41)-1))>=总览!$F$13),总览!$G$13,IF(AND(总览!$D$13<>"",B41*100+VALUE(LEFT(C41,LEN(C41)-1))>=总览!$D$13),总览!$E$13,总览!$B$13))))),0))) | M41: =SUM(H41:K41) | N41: =G41-M41 | O41: =O40+N41
A42: 41 | B42: 2029 | C42: 6月 | D42: =IF(AND(总览!$L$6<>"",B42*100+VALUE(LEFT(C42,LEN(C42)-1))>=总览!$L$6),总览!$M$6,IF(AND(总览!$J$6<>"",B42*100+VALUE(LEFT(C42,LEN(C42)-1))>=总览!$J$6),总览!$K$6,IF(AND(总览!$H$6<>"",B42*100+VALUE(LEFT(C42,LEN(C42)-1))>=总览!$H$6),总览!$I$6,IF(AND(总览!$F$6<>"",B42*100+VALUE(LEFT(C42,LEN(C42)-1))>=总览!$F$6),总览!$G$6,IF(AND(总览!$D$6<>"",B42*100+VALUE(LEFT(C42,LEN(C42)-1))>=总览!$D$6),总览!$E$6,总览!$B$6))))) | E42: =IF(C42="12月",IF(AND(总览!$L$7<>"",B42*100+VALUE(LEFT(C42,LEN(C42)-1))>=总览!$L$7),总览!$M$7,IF(AND(总览!$J$7<>"",B42*100+VALUE(LEFT(C42,LEN(C42)-1))>=总览!$J$7),总览!$K$7,IF(AND(总览!$H$7<>"",B42*100+VALUE(LEFT(C42,LEN(C42)-1))>=总览!$H$7),总览!$I$7,IF(AND(总览!$F$7<>"",B42*100+VALUE(LEFT(C42,LEN(C42)-1))>=总览!$F$7),总览!$G$7,IF(AND(总览!$D$7<>"",B42*100+VALUE(LEFT(C42,LEN(C42)-1))>=总览!$D$7),总览!$E$7,总览!$B$7))))),0) | F42: =ROUND(O41*总览!$B$14/12,0) | G42: =D42+E42+F42 | H42: =IF(OR(B42>2027,AND(B42=2027,VALUE(LEFT(C42,LEN(C42)-1))>=9)),IF(AND(总览!$L$10<>"",B42*100+VALUE(LEFT(C42,LEN(C42)-1))>=总览!$L$10),总览!$M$10,IF(AND(总览!$J$10<>"",B42*100+VALUE(LEFT(C42,LEN(C42)-1))>=总览!$J$10),总览!$K$10,IF(AND(总览!$H$10<>"",B42*100+VALUE(LEFT(C42,LEN(C42)-1))>=总览!$H$10),总览!$I$10,IF(AND(总览!$F$10<>"",B42*100+VALUE(LEFT(C42,LEN(C42)-1))>=总览!$F$10),总览!$G$10,IF(AND(总览!$D$10<>"",B42*100+VALUE(LEFT(C42,LEN(C42)-1))>=总览!$D$10),总览!$E$10,总览!$B$10))))),IF(AND(总览!$L$9<>"",B42*100+VALUE(LEFT(C42,LEN(C42)-1))>=总览!$L$9),总览!$M$9,IF(AND(总览!$J$9<>"",B42*100+VALUE(LEFT(C42,LEN(C42)-1))>=总览!$J$9),总览!$K$9,IF(AND(总览!$H$9<>"",B42*100+VALUE(LEFT(C42,LEN(C42)-1))>=总览!$H$9),总览!$I$9,IF(AND(总览!$F$9<>"",B42*100+VALUE(LEFT(C42,LEN(C42)-1))>=总览!$F$9),总览!$G$9,IF(AND(总览!$D$9<>"",B42*100+VALUE(LEFT(C42,LEN(C42)-1))>=总览!$D$9),总览!$E$9,总览!$B$9)))))) | I42: =IF(AND(总览!$L$11<>"",B42*100+VALUE(LEFT(C42,LEN(C42)-1))>=总览!$L$11),总览!$M$11,IF(AND(总览!$J$11<>"",B42*100+VALUE(LEFT(C42,LEN(C42)-1))>=总览!$J$11),总览!$K$11,IF(AND(总览!$H$11<>"",B42*100+VALUE(LEFT(C42,LEN(C42)-1))>=总览!$H$11),总览!$I$11,IF(AND(总览!$F$11<>"",B42*100+VALUE(LEFT(C42,LEN(C42)-1))>=总览!$F$11),总览!$G$11,IF(AND(总览!$D$11<>"",B42*100+VALUE(LEFT(C42,LEN(C42)-1))>=总览!$D$11),总览!$E$11,总览!$B$11))))) | J42: =IF(OR(B42>2027,AND(B42=2027,VALUE(LEFT(C42,LEN(C42)-1))>=9)),IF(AND(总览!$L$12<>"",B42*100+VALUE(LEFT(C42,LEN(C42)-1))>=总览!$L$12),总览!$M$12,IF(AND(总览!$J$12<>"",B42*100+VALUE(LEFT(C42,LEN(C42)-1))>=总览!$J$12),总览!$K$12,IF(AND(总览!$H$12<>"",B42*100+VALUE(LEFT(C42,LEN(C42)-1))>=总览!$H$12),总览!$I$12,IF(AND(总览!$F$12<>"",B42*100+VALUE(LEFT(C42,LEN(C42)-1))>=总览!$F$12),总览!$G$12,IF(AND(总览!$D$12<>"",B42*100+VALUE(LEFT(C42,LEN(C42)-1))>=总览!$D$12),总览!$E$12,总览!$B$12))))),0) | K42: =IF(AND(B42=2026,C42="5月"),120000,IF(AND(B42=2027,C42="9月"),30000,IF(C42="10月",IF(AND(总览!$L$13<>"",B42*100+VALUE(LEFT(C42,LEN(C42)-1))>=总览!$L$13),总览!$M$13,IF(AND(总览!$J$13<>"",B42*100+VALUE(LEFT(C42,LEN(C42)-1))>=总览!$J$13),总览!$K$13,IF(AND(总览!$H$13<>"",B42*100+VALUE(LEFT(C42,LEN(C42)-1))>=总览!$H$13),总览!$I$13,IF(AND(总览!$F$13<>"",B42*100+VALUE(LEFT(C42,LEN(C42)-1))>=总览!$F$13),总览!$G$13,IF(AND(总览!$D$13<>"",B42*100+VALUE(LEFT(C42,LEN(C42)-1))>=总览!$D$13),总览!$E$13,总览!$B$13))))),0))) | M42: =SUM(H42:K42) | N42: =G42-M42 | O42: =O41+N42
A43: 42 | B43: 2029 | C43: 7月 | D43: =IF(AND(总览!$L$6<>"",B43*100+VALUE(LEFT(C43,LEN(C43)-1))>=总览!$L$6),总览!$M$6,IF(AND(总览!$J$6<>"",B43*100+VALUE(LEFT(C43,LEN(C43)-1))>=总览!$J$6),总览!$K$6,IF(AND(总览!$H$6<>"",B43*100+VALUE(LEFT(C43,LEN(C43)-1))>=总览!$H$6),总览!$I$6,IF(AND(总览!$F$6<>"",B43*100+VALUE(LEFT(C43,LEN(C43)-1))>=总览!$F$6),总览!$G$6,IF(AND(总览!$D$6<>"",B43*100+VALUE(LEFT(C43,LEN(C43)-1))>=总览!$D$6),总览!$E$6,总览!$B$6))))) | E43: =IF(C43="12月",IF(AND(总览!$L$7<>"",B43*100+VALUE(LEFT(C43,LEN(C43)-1))>=总览!$L$7),总览!$M$7,IF(AND(总览!$J$7<>"",B43*100+VALUE(LEFT(C43,LEN(C43)-1))>=总览!$J$7),总览!$K$7,IF(AND(总览!$H$7<>"",B43*100+VALUE(LEFT(C43,LEN(C43)-1))>=总览!$H$7),总览!$I$7,IF(AND(总览!$F$7<>"",B43*100+VALUE(LEFT(C43,LEN(C43)-1))>=总览!$F$7),总览!$G$7,IF(AND(总览!$D$7<>"",B43*100+VALUE(LEFT(C43,LEN(C43)-1))>=总览!$D$7),总览!$E$7,总览!$B$7))))),0) | F43: =ROUND(O42*总览!$B$14/12,0) | G43: =D43+E43+F43 | H43: =IF(OR(B43>2027,AND(B43=2027,VALUE(LEFT(C43,LEN(C43)-1))>=9)),IF(AND(总览!$L$10<>"",B43*100+VALUE(LEFT(C43,LEN(C43)-1))>=总览!$L$10),总览!$M$10,IF(AND(总览!$J$10<>"",B43*100+VALUE(LEFT(C43,LEN(C43)-1))>=总览!$J$10),总览!$K$10,IF(AND(总览!$H$10<>"",B43*100+VALUE(LEFT(C43,LEN(C43)-1))>=总览!$H$10),总览!$I$10,IF(AND(总览!$F$10<>"",B43*100+VALUE(LEFT(C43,LEN(C43)-1))>=总览!$F$10),总览!$G$10,IF(AND(总览!$D$10<>"",B43*100+VALUE(LEFT(C43,LEN(C43)-1))>=总览!$D$10),总览!$E$10,总览!$B$10))))),IF(AND(总览!$L$9<>"",B43*100+VALUE(LEFT(C43,LEN(C43)-1))>=总览!$L$9),总览!$M$9,IF(AND(总览!$J$9<>"",B43*100+VALUE(LEFT(C43,LEN(C43)-1))>=总览!$J$9),总览!$K$9,IF(AND(总览!$H$9<>"",B43*100+VALUE(LEFT(C43,LEN(C43)-1))>=总览!$H$9),总览!$I$9,IF(AND(总览!$F$9<>"",B43*100+VALUE(LEFT(C43,LEN(C43)-1))>=总览!$F$9),总览!$G$9,IF(AND(总览!$D$9<>"",B43*100+VALUE(LEFT(C43,LEN(C43)-1))>=总览!$D$9),总览!$E$9,总览!$B$9)))))) | I43: =IF(AND(总览!$L$11<>"",B43*100+VALUE(LEFT(C43,LEN(C43)-1))>=总览!$L$11),总览!$M$11,IF(AND(总览!$J$11<>"",B43*100+VALUE(LEFT(C43,LEN(C43)-1))>=总览!$J$11),总览!$K$11,IF(AND(总览!$H$11<>"",B43*100+VALUE(LEFT(C43,LEN(C43)-1))>=总览!$H$11),总览!$I$11,IF(AND(总览!$F$11<>"",B43*100+VALUE(LEFT(C43,LEN(C43)-1))>=总览!$F$11),总览!$G$11,IF(AND(总览!$D$11<>"",B43*100+VALUE(LEFT(C43,LEN(C43)-1))>=总览!$D$11),总览!$E$11,总览!$B$11))))) | J43: =IF(OR(B43>2027,AND(B43=2027,VALUE(LEFT(C43,LEN(C43)-1))>=9)),IF(AND(总览!$L$12<>"",B43*100+VALUE(LEFT(C43,LEN(C43)-1))>=总览!$L$12),总览!$M$12,IF(AND(总览!$J$12<>"",B43*100+VALUE(LEFT(C43,LEN(C43)-1))>=总览!$J$12),总览!$K$12,IF(AND(总览!$H$12<>"",B43*100+VALUE(LEFT(C43,LEN(C43)-1))>=总览!$H$12),总览!$I$12,IF(AND(总览!$F$12<>"",B43*100+VALUE(LEFT(C43,LEN(C43)-1))>=总览!$F$12),总览!$G$12,IF(AND(总览!$D$12<>"",B43*100+VALUE(LEFT(C43,LEN(C43)-1))>=总览!$D$12),总览!$E$12,总览!$B$12))))),0) | K43: =IF(AND(B43=2026,C43="5月"),120000,IF(AND(B43=2027,C43="9月"),30000,IF(C43="10月",IF(AND(总览!$L$13<>"",B43*100+VALUE(LEFT(C43,LEN(C43)-1))>=总览!$L$13),总览!$M$13,IF(AND(总览!$J$13<>"",B43*100+VALUE(LEFT(C43,LEN(C43)-1))>=总览!$J$13),总览!$K$13,IF(AND(总览!$H$13<>"",B43*100+VALUE(LEFT(C43,LEN(C43)-1))>=总览!$H$13),总览!$I$13,IF(AND(总览!$F$13<>"",B43*100+VALUE(LEFT(C43,LEN(C43)-1))>=总览!$F$13),总览!$G$13,IF(AND(总览!$D$13<>"",B43*100+VALUE(LEFT(C43,LEN(C43)-1))>=总览!$D$13),总览!$E$13,总览!$B$13))))),0))) | M43: =SUM(H43:K43) | N43: =G43-M43 | O43: =O42+N43
A44: 43 | B44: 2029 | C44: 8月 | D44: =IF(AND(总览!$L$6<>"",B44*100+VALUE(LEFT(C44,LEN(C44)-1))>=总览!$L$6),总览!$M$6,IF(AND(总览!$J$6<>"",B44*100+VALUE(LEFT(C44,LEN(C44)-1))>=总览!$J$6),总览!$K$6,IF(AND(总览!$H$6<>"",B44*100+VALUE(LEFT(C44,LEN(C44)-1))>=总览!$H$6),总览!$I$6,IF(AND(总览!$F$6<>"",B44*100+VALUE(LEFT(C44,LEN(C44)-1))>=总览!$F$6),总览!$G$6,IF(AND(总览!$D$6<>"",B44*100+VALUE(LEFT(C44,LEN(C44)-1))>=总览!$D$6),总览!$E$6,总览!$B$6))))) | E44: =IF(C44="12月",IF(AND(总览!$L$7<>"",B44*100+VALUE(LEFT(C44,LEN(C44)-1))>=总览!$L$7),总览!$M$7,IF(AND(总览!$J$7<>"",B44*100+VALUE(LEFT(C44,LEN(C44)-1))>=总览!$J$7),总览!$K$7,IF(AND(总览!$H$7<>"",B44*100+VALUE(LEFT(C44,LEN(C44)-1))>=总览!$H$7),总览!$I$7,IF(AND(总览!$F$7<>"",B44*100+VALUE(LEFT(C44,LEN(C44)-1))>=总览!$F$7),总览!$G$7,IF(AND(总览!$D$7<>"",B44*100+VALUE(LEFT(C44,LEN(C44)-1))>=总览!$D$7),总览!$E$7,总览!$B$7))))),0) | F44: =ROUND(O43*总览!$B$14/12,0) | G44: =D44+E44+F44 | H44: =IF(OR(B44>2027,AND(B44=2027,VALUE(LEFT(C44,LEN(C44)-1))>=9)),IF(AND(总览!$L$10<>"",B44*100+VALUE(LEFT(C44,LEN(C44)-1))>=总览!$L$10),总览!$M$10,IF(AND(总览!$J$10<>"",B44*100+VALUE(LEFT(C44,LEN(C44)-1))>=总览!$J$10),总览!$K$10,IF(AND(总览!$H$10<>"",B44*100+VALUE(LEFT(C44,LEN(C44)-1))>=总览!$H$10),总览!$I$10,IF(AND(总览!$F$10<>"",B44*100+VALUE(LEFT(C44,LEN(C44)-1))>=总览!$F$10),总览!$G$10,IF(AND(总览!$D$10<>"",B44*100+VALUE(LEFT(C44,LEN(C44)-1))>=总览!$D$10),总览!$E$10,总览!$B$10))))),IF(AND(总览!$L$9<>"",B44*100+VALUE(LEFT(C44,LEN(C44)-1))>=总览!$L$9),总览!$M$9,IF(AND(总览!$J$9<>"",B44*100+VALUE(LEFT(C44,LEN(C44)-1))>=总览!$J$9),总览!$K$9,IF(AND(总览!$H$9<>"",B44*100+VALUE(LEFT(C44,LEN(C44)-1))>=总览!$H$9),总览!$I$9,IF(AND(总览!$F$9<>"",B44*100+VALUE(LEFT(C44,LEN(C44)-1))>=总览!$F$9),总览!$G$9,IF(AND(总览!$D$9<>"",B44*100+VALUE(LEFT(C44,LEN(C44)-1))>=总览!$D$9),总览!$E$9,总览!$B$9)))))) | I44: =IF(AND(总览!$L$11<>"",B44*100+VALUE(LEFT(C44,LEN(C44)-1))>=总览!$L$11),总览!$M$11,IF(AND(总览!$J$11<>"",B44*100+VALUE(LEFT(C44,LEN(C44)-1))>=总览!$J$11),总览!$K$11,IF(AND(总览!$H$11<>"",B44*100+VALUE(LEFT(C44,LEN(C44)-1))>=总览!$H$11),总览!$I$11,IF(AND(总览!$F$11<>"",B44*100+VALUE(LEFT(C44,LEN(C44)-1))>=总览!$F$11),总览!$G$11,IF(AND(总览!$D$11<>"",B44*100+VALUE(LEFT(C44,LEN(C44)-1))>=总览!$D$11),总览!$E$11,总览!$B$11))))) | J44: =IF(OR(B44>2027,AND(B44=2027,VALUE(LEFT(C44,LEN(C44)-1))>=9)),IF(AND(总览!$L$12<>"",B44*100+VALUE(LEFT(C44,LEN(C44)-1))>=总览!$L$12),总览!$M$12,IF(AND(总览!$J$12<>"",B44*100+VALUE(LEFT(C44,LEN(C44)-1))>=总览!$J$12),总览!$K$12,IF(AND(总览!$H$12<>"",B44*100+VALUE(LEFT(C44,LEN(C44)-1))>=总览!$H$12),总览!$I$12,IF(AND(总览!$F$12<>"",B44*100+VALUE(LEFT(C44,LEN(C44)-1))>=总览!$F$12),总览!$G$12,IF(AND(总览!$D$12<>"",B44*100+VALUE(LEFT(C44,LEN(C44)-1))>=总览!$D$12),总览!$E$12,总览!$B$12))))),0) | K44: =IF(AND(B44=2026,C44="5月"),120000,IF(AND(B44=2027,C44="9月"),30000,IF(C44="10月",IF(AND(总览!$L$13<>"",B44*100+VALUE(LEFT(C44,LEN(C44)-1))>=总览!$L$13),总览!$M$13,IF(AND(总览!$J$13<>"",B44*100+VALUE(LEFT(C44,LEN(C44)-1))>=总览!$J$13),总览!$K$13,IF(AND(总览!$H$13<>"",B44*100+VALUE(LEFT(C44,LEN(C44)-1))>=总览!$H$13),总览!$I$13,IF(AND(总览!$F$13<>"",B44*100+VALUE(LEFT(C44,LEN(C44)-1))>=总览!$F$13),总览!$G$13,IF(AND(总览!$D$13<>"",B44*100+VALUE(LEFT(C44,LEN(C44)-1))>=总览!$D$13),总览!$E$13,总览!$B$13))))),0))) | M44: =SUM(H44:K44) | N44: =G44-M44 | O44: =O43+N44
A45: 44 | B45: 2029 | C45: 9月 | D45: =IF(AND(总览!$L$6<>"",B45*100+VALUE(LEFT(C45,LEN(C45)-1))>=总览!$L$6),总览!$M$6,IF(AND(总览!$J$6<>"",B45*100+VALUE(LEFT(C45,LEN(C45)-1))>=总览!$J$6),总览!$K$6,IF(AND(总览!$H$6<>"",B45*100+VALUE(LEFT(C45,LEN(C45)-1))>=总览!$H$6),总览!$I$6,IF(AND(总览!$F$6<>"",B45*100+VALUE(LEFT(C45,LEN(C45)-1))>=总览!$F$6),总览!$G$6,IF(AND(总览!$D$6<>"",B45*100+VALUE(LEFT(C45,LEN(C45)-1))>=总览!$D$6),总览!$E$6,总览!$B$6))))) | E45: =IF(C45="12月",IF(AND(总览!$L$7<>"",B45*100+VALUE(LEFT(C45,LEN(C45)-1))>=总览!$L$7),总览!$M$7,IF(AND(总览!$J$7<>"",B45*100+VALUE(LEFT(C45,LEN(C45)-1))>=总览!$J$7),总览!$K$7,IF(AND(总览!$H$7<>"",B45*100+VALUE(LEFT(C45,LEN(C45)-1))>=总览!$H$7),总览!$I$7,IF(AND(总览!$F$7<>"",B45*100+VALUE(LEFT(C45,LEN(C45)-1))>=总览!$F$7),总览!$G$7,IF(AND(总览!$D$7<>"",B45*100+VALUE(LEFT(C45,LEN(C45)-1))>=总览!$D$7),总览!$E$7,总览!$B$7))))),0) | F45: =ROUND(O44*总览!$B$14/12,0) | G45: =D45+E45+F45 | H45: =IF(OR(B45>2027,AND(B45=2027,VALUE(LEFT(C45,LEN(C45)-1))>=9)),IF(AND(总览!$L$10<>"",B45*100+VALUE(LEFT(C45,LEN(C45)-1))>=总览!$L$10),总览!$M$10,IF(AND(总览!$J$10<>"",B45*100+VALUE(LEFT(C45,LEN(C45)-1))>=总览!$J$10),总览!$K$10,IF(AND(总览!$H$10<>"",B45*100+VALUE(LEFT(C45,LEN(C45)-1))>=总览!$H$10),总览!$I$10,IF(AND(总览!$F$10<>"",B45*100+VALUE(LEFT(C45,LEN(C45)-1))>=总览!$F$10),总览!$G$10,IF(AND(总览!$D$10<>"",B45*100+VALUE(LEFT(C45,LEN(C45)-1))>=总览!$D$10),总览!$E$10,总览!$B$10))))),IF(AND(总览!$L$9<>"",B45*100+VALUE(LEFT(C45,LEN(C45)-1))>=总览!$L$9),总览!$M$9,IF(AND(总览!$J$9<>"",B45*100+VALUE(LEFT(C45,LEN(C45)-1))>=总览!$J$9),总览!$K$9,IF(AND(总览!$H$9<>"",B45*100+VALUE(LEFT(C45,LEN(C45)-1))>=总览!$H$9),总览!$I$9,IF(AND(总览!$F$9<>"",B45*100+VALUE(LEFT(C45,LEN(C45)-1))>=总览!$F$9),总览!$G$9,IF(AND(总览!$D$9<>"",B45*100+VALUE(LEFT(C45,LEN(C45)-1))>=总览!$D$9),总览!$E$9,总览!$B$9)))))) | I45: =IF(AND(总览!$L$11<>"",B45*100+VALUE(LEFT(C45,LEN(C45)-1))>=总览!$L$11),总览!$M$11,IF(AND(总览!$J$11<>"",B45*100+VALUE(LEFT(C45,LEN(C45)-1))>=总览!$J$11),总览!$K$11,IF(AND(总览!$H$11<>"",B45*100+VALUE(LEFT(C45,LEN(C45)-1))>=总览!$H$11),总览!$I$11,IF(AND(总览!$F$11<>"",B45*100+VALUE(LEFT(C45,LEN(C45)-1))>=总览!$F$11),总览!$G$11,IF(AND(总览!$D$11<>"",B45*100+VALUE(LEFT(C45,LEN(C45)-1))>=总览!$D$11),总览!$E$11,总览!$B$11))))) | J45: =IF(OR(B45>2027,AND(B45=2027,VALUE(LEFT(C45,LEN(C45)-1))>=9)),IF(AND(总览!$L$12<>"",B45*100+VALUE(LEFT(C45,LEN(C45)-1))>=总览!$L$12),总览!$M$12,IF(AND(总览!$J$12<>"",B45*100+VALUE(LEFT(C45,LEN(C45)-1))>=总览!$J$12),总览!$K$12,IF(AND(总览!$H$12<>"",B45*100+VALUE(LEFT(C45,LEN(C45)-1))>=总览!$H$12),总览!$I$12,IF(AND(总览!$F$12<>"",B45*100+VALUE(LEFT(C45,LEN(C45)-1))>=总览!$F$12),总览!$G$12,IF(AND(总览!$D$12<>"",B45*100+VALUE(LEFT(C45,LEN(C45)-1))>=总览!$D$12),总览!$E$12,总览!$B$12))))),0) | K45: =IF(AND(B45=2026,C45="5月"),120000,IF(AND(B45=2027,C45="9月"),30000,IF(C45="10月",IF(AND(总览!$L$13<>"",B45*100+VALUE(LEFT(C45,LEN(C45)-1))>=总览!$L$13),总览!$M$13,IF(AND(总览!$J$13<>"",B45*100+VALUE(LEFT(C45,LEN(C45)-1))>=总览!$J$13),总览!$K$13,IF(AND(总览!$H$13<>"",B45*100+VALUE(LEFT(C45,LEN(C45)-1))>=总览!$H$13),总览!$I$13,IF(AND(总览!$F$13<>"",B45*100+VALUE(LEFT(C45,LEN(C45)-1))>=总览!$F$13),总览!$G$13,IF(AND(总览!$D$13<>"",B45*100+VALUE(LEFT(C45,LEN(C45)-1))>=总览!$D$13),总览!$E$13,总览!$B$13))))),0))) | M45: =SUM(H45:K45) | N45: =G45-M45 | O45: =O44+N45
A46: 45 | B46: 2029 | C46: 10月 | D46: =IF(AND(总览!$L$6<>"",B46*100+VALUE(LEFT(C46,LEN(C46)-1))>=总览!$L$6),总览!$M$6,IF(AND(总览!$J$6<>"",B46*100+VALUE(LEFT(C46,LEN(C46)-1))>=总览!$J$6),总览!$K$6,IF(AND(总览!$H$6<>"",B46*100+VALUE(LEFT(C46,LEN(C46)-1))>=总览!$H$6),总览!$I$6,IF(AND(总览!$F$6<>"",B46*100+VALUE(LEFT(C46,LEN(C46)-1))>=总览!$F$6),总览!$G$6,IF(AND(总览!$D$6<>"",B46*100+VALUE(LEFT(C46,LEN(C46)-1))>=总览!$D$6),总览!$E$6,总览!$B$6))))) | E46: =IF(C46="12月",IF(AND(总览!$L$7<>"",B46*100+VALUE(LEFT(C46,LEN(C46)-1))>=总览!$L$7),总览!$M$7,IF(AND(总览!$J$7<>"",B46*100+VALUE(LEFT(C46,LEN(C46)-1))>=总览!$J$7),总览!$K$7,IF(AND(总览!$H$7<>"",B46*100+VALUE(LEFT(C46,LEN(C46)-1))>=总览!$H$7),总览!$I$7,IF(AND(总览!$F$7<>"",B46*100+VALUE(LEFT(C46,LEN(C46)-1))>=总览!$F$7),总览!$G$7,IF(AND(总览!$D$7<>"",B46*100+VALUE(LEFT(C46,LEN(C46)-1))>=总览!$D$7),总览!$E$7,总览!$B$7))))),0) | F46: =ROUND(O45*总览!$B$14/12,0) | G46: =D46+E46+F46 | H46: =IF(OR(B46>2027,AND(B46=2027,VALUE(LEFT(C46,LEN(C46)-1))>=9)),IF(AND(总览!$L$10<>"",B46*100+VALUE(LEFT(C46,LEN(C46)-1))>=总览!$L$10),总览!$M$10,IF(AND(总览!$J$10<>"",B46*100+VALUE(LEFT(C46,LEN(C46)-1))>=总览!$J$10),总览!$K$10,IF(AND(总览!$H$10<>"",B46*100+VALUE(LEFT(C46,LEN(C46)-1))>=总览!$H$10),总览!$I$10,IF(AND(总览!$F$10<>"",B46*100+VALUE(LEFT(C46,LEN(C46)-1))>=总览!$F$10),总览!$G$10,IF(AND(总览!$D$10<>"",B46*100+VALUE(LEFT(C46,LEN(C46)-1))>=总览!$D$10),总览!$E$10,总览!$B$10))))),IF(AND(总览!$L$9<>"",B46*100+VALUE(LEFT(C46,LEN(C46)-1))>=总览!$L$9),总览!$M$9,IF(AND(总览!$J$9<>"",B46*100+VALUE(LEFT(C46,LEN(C46)-1))>=总览!$J$9),总览!$K$9,IF(AND(总览!$H$9<>"",B46*100+VALUE(LEFT(C46,LEN(C46)-1))>=总览!$H$9),总览!$I$9,IF(AND(总览!$F$9<>"",B46*100+VALUE(LEFT(C46,LEN(C46)-1))>=总览!$F$9),总览!$G$9,IF(AND(总览!$D$9<>"",B46*100+VALUE(LEFT(C46,LEN(C46)-1))>=总览!$D$9),总览!$E$9,总览!$B$9)))))) | I46: =IF(AND(总览!$L$11<>"",B46*100+VALUE(LEFT(C46,LEN(C46)-1))>=总览!$L$11),总览!$M$11,IF(AND(总览!$J$11<>"",B46*100+VALUE(LEFT(C46,LEN(C46)-1))>=总览!$J$11),总览!$K$11,IF(AND(总览!$H$11<>"",B46*100+VALUE(LEFT(C46,LEN(C46)-1))>=总览!$H$11),总览!$I$11,IF(AND(总览!$F$11<>"",B46*100+VALUE(LEFT(C46,LEN(C46)-1))>=总览!$F$11),总览!$G$11,IF(AND(总览!$D$11<>"",B46*100+VALUE(LEFT(C46,LEN(C46)-1))>=总览!$D$11),总览!$E$11,总览!$B$11))))) | J46: =IF(OR(B46>2027,AND(B46=2027,VALUE(LEFT(C46,LEN(C46)-1))>=9)),IF(AND(总览!$L$12<>"",B46*100+VALUE(LEFT(C46,LEN(C46)-1))>=总览!$L$12),总览!$M$12,IF(AND(总览!$J$12<>"",B46*100+VALUE(LEFT(C46,LEN(C46)-1))>=总览!$J$12),总览!$K$12,IF(AND(总览!$H$12<>"",B46*100+VALUE(LEFT(C46,LEN(C46)-1))>=总览!$H$12),总览!$I$12,IF(AND(总览!$F$12<>"",B46*100+VALUE(LEFT(C46,LEN(C46)-1))>=总览!$F$12),总览!$G$12,IF(AND(总览!$D$12<>"",B46*100+VALUE(LEFT(C46,LEN(C46)-1))>=总览!$D$12),总览!$E$12,总览!$B$12))))),0) | K46: =IF(AND(B46=2026,C46="5月"),120000,IF(AND(B46=2027,C46="9月"),30000,IF(C46="10月",IF(AND(总览!$L$13<>"",B46*100+VALUE(LEFT(C46,LEN(C46)-1))>=总览!$L$13),总览!$M$13,IF(AND(总览!$J$13<>"",B46*100+VALUE(LEFT(C46,LEN(C46)-1))>=总览!$J$13),总览!$K$13,IF(AND(总览!$H$13<>"",B46*100+VALUE(LEFT(C46,LEN(C46)-1))>=总览!$H$13),总览!$I$13,IF(AND(总览!$F$13<>"",B46*100+VALUE(LEFT(C46,LEN(C46)-1))>=总览!$F$13),总览!$G$13,IF(AND(总览!$D$13<>"",B46*100+VALUE(LEFT(C46,LEN(C46)-1))>=总览!$D$13),总览!$E$13,总览!$B$13))))),0))) | L46: 年度旅游 | M46: =SUM(H46:K46) | N46: =G46-M46 | O46: =O45+N46
A47: 46 | B47: 2029 | C47: 11月 | D47: =IF(AND(总览!$L$6<>"",B47*100+VALUE(LEFT(C47,LEN(C47)-1))>=总览!$L$6),总览!$M$6,IF(AND(总览!$J$6<>"",B47*100+VALUE(LEFT(C47,LEN(C47)-1))>=总览!$J$6),总览!$K$6,IF(AND(总览!$H$6<>"",B47*100+VALUE(LEFT(C47,LEN(C47)-1))>=总览!$H$6),总览!$I$6,IF(AND(总览!$F$6<>"",B47*100+VALUE(LEFT(C47,LEN(C47)-1))>=总览!$F$6),总览!$G$6,IF(AND(总览!$D$6<>"",B47*100+VALUE(LEFT(C47,LEN(C47)-1))>=总览!$D$6),总览!$E$6,总览!$B$6))))) | E47: =IF(C47="12月",IF(AND(总览!$L$7<>"",B47*100+VALUE(LEFT(C47,LEN(C47)-1))>=总览!$L$7),总览!$M$7,IF(AND(总览!$J$7<>"",B47*100+VALUE(LEFT(C47,LEN(C47)-1))>=总览!$J$7),总览!$K$7,IF(AND(总览!$H$7<>"",B47*100+VALUE(LEFT(C47,LEN(C47)-1))>=总览!$H$7),总览!$I$7,IF(AND(总览!$F$7<>"",B47*100+VALUE(LEFT(C47,LEN(C47)-1))>=总览!$F$7),总览!$G$7,IF(AND(总览!$D$7<>"",B47*100+VALUE(LEFT(C47,LEN(C47)-1))>=总览!$D$7),总览!$E$7,总览!$B$7))))),0) | F47: =ROUND(O46*总览!$B$14/12,0) | G47: =D47+E47+F47 | H47: =IF(OR(B47>2027,AND(B47=2027,VALUE(LEFT(C47,LEN(C47)-1))>=9)),IF(AND(总览!$L$10<>"",B47*100+VALUE(LEFT(C47,LEN(C47)-1))>=总览!$L$10),总览!$M$10,IF(AND(总览!$J$10<>"",B47*100+VALUE(LEFT(C47,LEN(C47)-1))>=总览!$J$10),总览!$K$10,IF(AND(总览!$H$10<>"",B47*100+VALUE(LEFT(C47,LEN(C47)-1))>=总览!$H$10),总览!$I$10,IF(AND(总览!$F$10<>"",B47*100+VALUE(LEFT(C47,LEN(C47)-1))>=总览!$F$10),总览!$G$10,IF(AND(总览!$D$10<>"",B47*100+VALUE(LEFT(C47,LEN(C47)-1))>=总览!$D$10),总览!$E$10,总览!$B$10))))),IF(AND(总览!$L$9<>"",B47*100+VALUE(LEFT(C47,LEN(C47)-1))>=总览!$L$9),总览!$M$9,IF(AND(总览!$J$9<>"",B47*100+VALUE(LEFT(C47,LEN(C47)-1))>=总览!$J$9),总览!$K$9,IF(AND(总览!$H$9<>"",B47*100+VALUE(LEFT(C47,LEN(C47)-1))>=总览!$H$9),总览!$I$9,IF(AND(总览!$F$9<>"",B47*100+VALUE(LEFT(C47,LEN(C47)-1))>=总览!$F$9),总览!$G$9,IF(AND(总览!$D$9<>"",B47*100+VALUE(LEFT(C47,LEN(C47)-1))>=总览!$D$9),总览!$E$9,总览!$B$9)))))) | I47: =IF(AND(总览!$L$11<>"",B47*100+VALUE(LEFT(C47,LEN(C47)-1))>=总览!$L$11),总览!$M$11,IF(AND(总览!$J$11<>"",B47*100+VALUE(LEFT(C47,LEN(C47)-1))>=总览!$J$11),总览!$K$11,IF(AND(总览!$H$11<>"",B47*100+VALUE(LEFT(C47,LEN(C47)-1))>=总览!$H$11),总览!$I$11,IF(AND(总览!$F$11<>"",B47*100+VALUE(LEFT(C47,LEN(C47)-1))>=总览!$F$11),总览!$G$11,IF(AND(总览!$D$11<>"",B47*100+VALUE(LEFT(C47,LEN(C47)-1))>=总览!$D$11),总览!$E$11,总览!$B$11))))) | J47: =IF(OR(B47>2027,AND(B47=2027,VALUE(LEFT(C47,LEN(C47)-1))>=9)),IF(AND(总览!$L$12<>"",B47*100+VALUE(LEFT(C47,LEN(C47)-1))>=总览!$L$12),总览!$M$12,IF(AND(总览!$J$12<>"",B47*100+VALUE(LEFT(C47,LEN(C47)-1))>=总览!$J$12),总览!$K$12,IF(AND(总览!$H$12<>"",B47*100+VALUE(LEFT(C47,LEN(C47)-1))>=总览!$H$12),总览!$I$12,IF(AND(总览!$F$12<>"",B47*100+VALUE(LEFT(C47,LEN(C47)-1))>=总览!$F$12),总览!$G$12,IF(AND(总览!$D$12<>"",B47*100+VALUE(LEFT(C47,LEN(C47)-1))>=总览!$D$12),总览!$E$12,总览!$B$12))))),0) | K47: =IF(AND(B47=2026,C47="5月"),120000,IF(AND(B47=2027,C47="9月"),30000,IF(C47="10月",IF(AND(总览!$L$13<>"",B47*100+VALUE(LEFT(C47,LEN(C47)-1))>=总览!$L$13),总览!$M$13,IF(AND(总览!$J$13<>"",B47*100+VALUE(LEFT(C47,LEN(C47)-1))>=总览!$J$13),总览!$K$13,IF(AND(总览!$H$13<>"",B47*100+VALUE(LEFT(C47,LEN(C47)-1))>=总览!$H$13),总览!$I$13,IF(AND(总览!$F$13<>"",B47*100+VALUE(LEFT(C47,LEN(C47)-1))>=总览!$F$13),总览!$G$13,IF(AND(总览!$D$13<>"",B47*100+VALUE(LEFT(C47,LEN(C47)-1))>=总览!$D$13),总览!$E$13,总览!$B$13))))),0))) | M47: =SUM(H47:K47) | N47: =G47-M47 | O47: =O46+N47
A48: 47 | B48: 2029 | C48: 12月 | D48: =IF(AND(总览!$L$6<>"",B48*100+VALUE(LEFT(C48,LEN(C48)-1))>=总览!$L$6),总览!$M$6,IF(AND(总览!$J$6<>"",B48*100+VALUE(LEFT(C48,LEN(C48)-1))>=总览!$J$6),总览!$K$6,IF(AND(总览!$H$6<>"",B48*100+VALUE(LEFT(C48,LEN(C48)-1))>=总览!$H$6),总览!$I$6,IF(AND(总览!$F$6<>"",B48*100+VALUE(LEFT(C48,LEN(C48)-1))>=总览!$F$6),总览!$G$6,IF(AND(总览!$D$6<>"",B48*100+VALUE(LEFT(C48,LEN(C48)-1))>=总览!$D$6),总览!$E$6,总览!$B$6))))) | E48: =IF(C48="12月",IF(AND(总览!$L$7<>"",B48*100+VALUE(LEFT(C48,LEN(C48)-1))>=总览!$L$7),总览!$M$7,IF(AND(总览!$J$7<>"",B48*100+VALUE(LEFT(C48,LEN(C48)-1))>=总览!$J$7),总览!$K$7,IF(AND(总览!$H$7<>"",B48*100+VALUE(LEFT(C48,LEN(C48)-1))>=总览!$H$7),总览!$I$7,IF(AND(总览!$F$7<>"",B48*100+VALUE(LEFT(C48,LEN(C48)-1))>=总览!$F$7),总览!$G$7,IF(AND(总览!$D$7<>"",B48*100+VALUE(LEFT(C48,LEN(C48)-1))>=总览!$D$7),总览!$E$7,总览!$B$7))))),0) | F48: =ROUND(O47*总览!$B$14/12,0) | G48: =D48+E48+F48 | H48: =IF(OR(B48>2027,AND(B48=2027,VALUE(LEFT(C48,LEN(C48)-1))>=9)),IF(AND(总览!$L$10<>"",B48*100+VALUE(LEFT(C48,LEN(C48)-1))>=总览!$L$10),总览!$M$10,IF(AND(总览!$J$10<>"",B48*100+VALUE(LEFT(C48,LEN(C48)-1))>=总览!$J$10),总览!$K$10,IF(AND(总览!$H$10<>"",B48*100+VALUE(LEFT(C48,LEN(C48)-1))>=总览!$H$10),总览!$I$10,IF(AND(总览!$F$10<>"",B48*100+VALUE(LEFT(C48,LEN(C48)-1))>=总览!$F$10),总览!$G$10,IF(AND(总览!$D$10<>"",B48*100+VALUE(LEFT(C48,LEN(C48)-1))>=总览!$D$10),总览!$E$10,总览!$B$10))))),IF(AND(总览!$L$9<>"",B48*100+VALUE(LEFT(C48,LEN(C48)-1))>=总览!$L$9),总览!$M$9,IF(AND(总览!$J$9<>"",B48*100+VALUE(LEFT(C48,LEN(C48)-1))>=总览!$J$9),总览!$K$9,IF(AND(总览!$H$9<>"",B48*100+VALUE(LEFT(C48,LEN(C48)-1))>=总览!$H$9),总览!$I$9,IF(AND(总览!$F$9<>"",B48*100+VALUE(LEFT(C48,LEN(C48)-1))>=总览!$F$9),总览!$G$9,IF(AND(总览!$D$9<>"",B48*100+VALUE(LEFT(C48,LEN(C48)-1))>=总览!$D$9),总览!$E$9,总览!$B$9)))))) | I48: =IF(AND(总览!$L$11<>"",B48*100+VALUE(LEFT(C48,LEN(C48)-1))>=总览!$L$11),总览!$M$11,IF(AND(总览!$J$11<>"",B48*100+VALUE(LEFT(C48,LEN(C48)-1))>=总览!$J$11),总览!$K$11,IF(AND(总览!$H$11<>"",B48*100+VALUE(LEFT(C48,LEN(C48)-1))>=总览!$H$11),总览!$I$11,IF(AND(总览!$F$11<>"",B48*100+VALUE(LEFT(C48,LEN(C48)-1))>=总览!$F$11),总览!$G$11,IF(AND(总览!$D$11<>"",B48*100+VALUE(LEFT(C48,LEN(C48)-1))>=总览!$D$11),总览!$E$11,总览!$B$11))))) | J48: =IF(OR(B48>2027,AND(B48=2027,VALUE(LEFT(C48,LEN(C48)-1))>=9)),IF(AND(总览!$L$12<>"",B48*100+VALUE(LEFT(C48,LEN(C48)-1))>=总览!$L$12),总览!$M$12,IF(AND(总览!$J$12<>"",B48*100+VALUE(LEFT(C48,LEN(C48)-1))>=总览!$J$12),总览!$K$12,IF(AND(总览!$H$12<>"",B48*100+VALUE(LEFT(C48,LEN(C48)-1))>=总览!$H$12),总览!$I$12,IF(AND(总览!$F$12<>"",B48*100+VALUE(LEFT(C48,LEN(C48)-1))>=总览!$F$12),总览!$G$12,IF(AND(总览!$D$12<>"",B48*100+VALUE(LEFT(C48,LEN(C48)-1))>=总览!$D$12),总览!$E$12,总览!$B$12))))),0) | K48: =IF(AND(B48=2026,C48="5月"),120000,IF(AND(B48=2027,C48="9月"),30000,IF(C48="10月",IF(AND(总览!$L$13<>"",B48*100+VALUE(LEFT(C48,LEN(C48)-1))>=总览!$L$13),总览!$M$13,IF(AND(总览!$J$13<>"",B48*100+VALUE(LEFT(C48,LEN(C48)-1))>=总览!$J$13),总览!$K$13,IF(AND(总览!$H$13<>"",B48*100+VALUE(LEFT(C48,LEN(C48)-1))>=总览!$H$13),总览!$I$13,IF(AND(总览!$F$13<>"",B48*100+VALUE(LEFT(C48,LEN(C48)-1))>=总览!$F$13),总览!$G$13,IF(AND(总览!$D$13<>"",B48*100+VALUE(LEFT(C48,LEN(C48)-1))>=总览!$D$13),总览!$E$13,总览!$B$13))))),0))) | M48: =SUM(H48:K48) | N48: =G48-M48 | O48: =O47+N48
A49: 48 | B49: 2030 | C49: 1月 | D49: =IF(AND(总览!$L$6<>"",B49*100+VALUE(LEFT(C49,LEN(C49)-1))>=总览!$L$6),总览!$M$6,IF(AND(总览!$J$6<>"",B49*100+VALUE(LEFT(C49,LEN(C49)-1))>=总览!$J$6),总览!$K$6,IF(AND(总览!$H$6<>"",B49*100+VALUE(LEFT(C49,LEN(C49)-1))>=总览!$H$6),总览!$I$6,IF(AND(总览!$F$6<>"",B49*100+VALUE(LEFT(C49,LEN(C49)-1))>=总览!$F$6),总览!$G$6,IF(AND(总览!$D$6<>"",B49*100+VALUE(LEFT(C49,LEN(C49)-1))>=总览!$D$6),总览!$E$6,总览!$B$6))))) | E49: =IF(C49="12月",IF(AND(总览!$L$7<>"",B49*100+VALUE(LEFT(C49,LEN(C49)-1))>=总览!$L$7),总览!$M$7,IF(AND(总览!$J$7<>"",B49*100+VALUE(LEFT(C49,LEN(C49)-1))>=总览!$J$7),总览!$K$7,IF(AND(总览!$H$7<>"",B49*100+VALUE(LEFT(C49,LEN(C49)-1))>=总览!$H$7),总览!$I$7,IF(AND(总览!$F$7<>"",B49*100+VALUE(LEFT(C49,LEN(C49)-1))>=总览!$F$7),总览!$G$7,IF(AND(总览!$D$7<>"",B49*100+VALUE(LEFT(C49,LEN(C49)-1))>=总览!$D$7),总览!$E$7,总览!$B$7))))),0) | F49: =ROUND(O48*总览!$B$14/12,0) | G49: =D49+E49+F49 | H49: =IF(OR(B49>2027,AND(B49=2027,VALUE(LEFT(C49,LEN(C49)-1))>=9)),IF(AND(总览!$L$10<>"",B49*100+VALUE(LEFT(C49,LEN(C49)-1))>=总览!$L$10),总览!$M$10,IF(AND(总览!$J$10<>"",B49*100+VALUE(LEFT(C49,LEN(C49)-1))>=总览!$J$10),总览!$K$10,IF(AND(总览!$H$10<>"",B49*100+VALUE(LEFT(C49,LEN(C49)-1))>=总览!$H$10),总览!$I$10,IF(AND(总览!$F$10<>"",B49*100+VALUE(LEFT(C49,LEN(C49)-1))>=总览!$F$10),总览!$G$10,IF(AND(总览!$D$10<>"",B49*100+VALUE(LEFT(C49,LEN(C49)-1))>=总览!$D$10),总览!$E$10,总览!$B$10))))),IF(AND(总览!$L$9<>"",B49*100+VALUE(LEFT(C49,LEN(C49)-1))>=总览!$L$9),总览!$M$9,IF(AND(总览!$J$9<>"",B49*100+VALUE(LEFT(C49,LEN(C49)-1))>=总览!$J$9),总览!$K$9,IF(AND(总览!$H$9<>"",B49*100+VALUE(LEFT(C49,LEN(C49)-1))>=总览!$H$9),总览!$I$9,IF(AND(总览!$F$9<>"",B49*100+VALUE(LEFT(C49,LEN(C49)-1))>=总览!$F$9),总览!$G$9,IF(AND(总览!$D$9<>"",B49*100+VALUE(LEFT(C49,LEN(C49)-1))>=总览!$D$9),总览!$E$9,总览!$B$9)))))) | I49: =IF(AND(总览!$L$11<>"",B49*100+VALUE(LEFT(C49,LEN(C49)-1))>=总览!$L$11),总览!$M$11,IF(AND(总览!$J$11<>"",B49*100+VALUE(LEFT(C49,LEN(C49)-1))>=总览!$J$11),总览!$K$11,IF(AND(总览!$H$11<>"",B49*100+VALUE(LEFT(C49,LEN(C49)-1))>=总览!$H$11),总览!$I$11,IF(AND(总览!$F$11<>"",B49*100+VALUE(LEFT(C49,LEN(C49)-1))>=总览!$F$11),总览!$G$11,IF(AND(总览!$D$11<>"",B49*100+VALUE(LEFT(C49,LEN(C49)-1))>=总览!$D$11),总览!$E$11,总览!$B$11))))) | J49: =IF(OR(B49>2027,AND(B49=2027,VALUE(LEFT(C49,LEN(C49)-1))>=9)),IF(AND(总览!$L$12<>"",B49*100+VALUE(LEFT(C49,LEN(C49)-1))>=总览!$L$12),总览!$M$12,IF(AND(总览!$J$12<>"",B49*100+VALUE(LEFT(C49,LEN(C49)-1))>=总览!$J$12),总览!$K$12,IF(AND(总览!$H$12<>"",B49*100+VALUE(LEFT(C49,LEN(C49)-1))>=总览!$H$12),总览!$I$12,IF(AND(总览!$F$12<>"",B49*100+VALUE(LEFT(C49,LEN(C49)-1))>=总览!$F$12),总览!$G$12,IF(AND(总览!$D$12<>"",B49*100+VALUE(LEFT(C49,LEN(C49)-1))>=总览!$D$12),总览!$E$12,总览!$B$12))))),0) | K49: =IF(AND(B49=2026,C49="5月"),120000,IF(AND(B49=2027,C49="9月"),30000,IF(C49="10月",IF(AND(总览!$L$13<>"",B49*100+VALUE(LEFT(C49,LEN(C49)-1))>=总览!$L$13),总览!$M$13,IF(AND(总览!$J$13<>"",B49*100+VALUE(LEFT(C49,LEN(C49)-1))>=总览!$J$13),总览!$K$13,IF(AND(总览!$H$13<>"",B49*100+VALUE(LEFT(C49,LEN(C49)-1))>=总览!$H$13),总览!$I$13,IF(AND(总览!$F$13<>"",B49*100+VALUE(LEFT(C49,LEN(C49)-1))>=总览!$F$13),总览!$G$13,IF(AND(总览!$D$13<>"",B49*100+VALUE(LEFT(C49,LEN(C49)-1))>=总览!$D$13),总览!$E$13,总览!$B$13))))),0))) | M49: =SUM(H49:K49) | N49: =G49-M49 | O49: =O48+N49
A50: 49 | B50: 2030 | C50: 2月 | D50: =IF(AND(总览!$L$6<>"",B50*100+VALUE(LEFT(C50,LEN(C50)-1))>=总览!$L$6),总览!$M$6,IF(AND(总览!$J$6<>"",B50*100+VALUE(LEFT(C50,LEN(C50)-1))>=总览!$J$6),总览!$K$6,IF(AND(总览!$H$6<>"",B50*100+VALUE(LEFT(C50,LEN(C50)-1))>=总览!$H$6),总览!$I$6,IF(AND(总览!$F$6<>"",B50*100+VALUE(LEFT(C50,LEN(C50)-1))>=总览!$F$6),总览!$G$6,IF(AND(总览!$D$6<>"",B50*100+VALUE(LEFT(C50,LEN(C50)-1))>=总览!$D$6),总览!$E$6,总览!$B$6))))) | E50: =IF(C50="12月",IF(AND(总览!$L$7<>"",B50*100+VALUE(LEFT(C50,LEN(C50)-1))>=总览!$L$7),总览!$M$7,IF(AND(总览!$J$7<>"",B50*100+VALUE(LEFT(C50,LEN(C50)-1))>=总览!$J$7),总览!$K$7,IF(AND(总览!$H$7<>"",B50*100+VALUE(LEFT(C50,LEN(C50)-1))>=总览!$H$7),总览!$I$7,IF(AND(总览!$F$7<>"",B50*100+VALUE(LEFT(C50,LEN(C50)-1))>=总览!$F$7),总览!$G$7,IF(AND(总览!$D$7<>"",B50*100+VALUE(LEFT(C50,LEN(C50)-1))>=总览!$D$7),总览!$E$7,总览!$B$7))))),0) | F50: =ROUND(O49*总览!$B$14/12,0) | G50: =D50+E50+F50 | H50: =IF(OR(B50>2027,AND(B50=2027,VALUE(LEFT(C50,LEN(C50)-1))>=9)),IF(AND(总览!$L$10<>"",B50*100+VALUE(LEFT(C50,LEN(C50)-1))>=总览!$L$10),总览!$M$10,IF(AND(总览!$J$10<>"",B50*100+VALUE(LEFT(C50,LEN(C50)-1))>=总览!$J$10),总览!$K$10,IF(AND(总览!$H$10<>"",B50*100+VALUE(LEFT(C50,LEN(C50)-1))>=总览!$H$10),总览!$I$10,IF(AND(总览!$F$10<>"",B50*100+VALUE(LEFT(C50,LEN(C50)-1))>=总览!$F$10),总览!$G$10,IF(AND(总览!$D$10<>"",B50*100+VALUE(LEFT(C50,LEN(C50)-1))>=总览!$D$10),总览!$E$10,总览!$B$10))))),IF(AND(总览!$L$9<>"",B50*100+VALUE(LEFT(C50,LEN(C50)-1))>=总览!$L$9),总览!$M$9,IF(AND(总览!$J$9<>"",B50*100+VALUE(LEFT(C50,LEN(C50)-1))>=总览!$J$9),总览!$K$9,IF(AND(总览!$H$9<>"",B50*100+VALUE(LEFT(C50,LEN(C50)-1))>=总览!$H$9),总览!$I$9,IF(AND(总览!$F$9<>"",B50*100+VALUE(LEFT(C50,LEN(C50)-1))>=总览!$F$9),总览!$G$9,IF(AND(总览!$D$9<>"",B50*100+VALUE(LEFT(C50,LEN(C50)-1))>=总览!$D$9),总览!$E$9,总览!$B$9)))))) | I50: =IF(AND(总览!$L$11<>"",B50*100+VALUE(LEFT(C50,LEN(C50)-1))>=总览!$L$11),总览!$M$11,IF(AND(总览!$J$11<>"",B50*100+VALUE(LEFT(C50,LEN(C50)-1))>=总览!$J$11),总览!$K$11,IF(AND(总览!$H$11<>"",B50*100+VALUE(LEFT(C50,LEN(C50)-1))>=总览!$H$11),总览!$I$11,IF(AND(总览!$F$11<>"",B50*100+VALUE(LEFT(C50,LEN(C50)-1))>=总览!$F$11),总览!$G$11,IF(AND(总览!$D$11<>"",B50*100+VALUE(LEFT(C50,LEN(C50)-1))>=总览!$D$11),总览!$E$11,总览!$B$11))))) | J50: =IF(OR(B50>2027,AND(B50=2027,VALUE(LEFT(C50,LEN(C50)-1))>=9)),IF(AND(总览!$L$12<>"",B50*100+VALUE(LEFT(C50,LEN(C50)-1))>=总览!$L$12),总览!$M$12,IF(AND(总览!$J$12<>"",B50*100+VALUE(LEFT(C50,LEN(C50)-1))>=总览!$J$12),总览!$K$12,IF(AND(总览!$H$12<>"",B50*100+VALUE(LEFT(C50,LEN(C50)-1))>=总览!$H$12),总览!$I$12,IF(AND(总览!$F$12<>"",B50*100+VALUE(LEFT(C50,LEN(C50)-1))>=总览!$F$12),总览!$G$12,IF(AND(总览!$D$12<>"",B50*100+VALUE(LEFT(C50,LEN(C50)-1))>=总览!$D$12),总览!$E$12,总览!$B$12))))),0) | K50: =IF(AND(B50=2026,C50="5月"),120000,IF(AND(B50=2027,C50="9月"),30000,IF(C50="10月",IF(AND(总览!$L$13<>"",B50*100+VALUE(LEFT(C50,LEN(C50)-1))>=总览!$L$13),总览!$M$13,IF(AND(总览!$J$13<>"",B50*100+VALUE(LEFT(C50,LEN(C50)-1))>=总览!$J$13),总览!$K$13,IF(AND(总览!$H$13<>"",B50*100+VALUE(LEFT(C50,LEN(C50)-1))>=总览!$H$13),总览!$I$13,IF(AND(总览!$F$13<>"",B50*100+VALUE(LEFT(C50,LEN(C50)-1))>=总览!$F$13),总览!$G$13,IF(AND(总览!$D$13<>"",B50*100+VALUE(LEFT(C50,LEN(C50)-1))>=总览!$D$13),总览!$E$13,总览!$B$13))))),0))) | M50: =SUM(H50:K50) | N50: =G50-M50 | O50: =O49+N50
A51: 50 | B51: 2030 | C51: 3月 | D51: =IF(AND(总览!$L$6<>"",B51*100+VALUE(LEFT(C51,LEN(C51)-1))>=总览!$L$6),总览!$M$6,IF(AND(总览!$J$6<>"",B51*100+VALUE(LEFT(C51,LEN(C51)-1))>=总览!$J$6),总览!$K$6,IF(AND(总览!$H$6<>"",B51*100+VALUE(LEFT(C51,LEN(C51)-1))>=总览!$H$6),总览!$I$6,IF(AND(总览!$F$6<>"",B51*100+VALUE(LEFT(C51,LEN(C51)-1))>=总览!$F$6),总览!$G$6,IF(AND(总览!$D$6<>"",B51*100+VALUE(LEFT(C51,LEN(C51)-1))>=总览!$D$6),总览!$E$6,总览!$B$6))))) | E51: =IF(C51="12月",IF(AND(总览!$L$7<>"",B51*100+VALUE(LEFT(C51,LEN(C51)-1))>=总览!$L$7),总览!$M$7,IF(AND(总览!$J$7<>"",B51*100+VALUE(LEFT(C51,LEN(C51)-1))>=总览!$J$7),总览!$K$7,IF(AND(总览!$H$7<>"",B51*100+VALUE(LEFT(C51,LEN(C51)-1))>=总览!$H$7),总览!$I$7,IF(AND(总览!$F$7<>"",B51*100+VALUE(LEFT(C51,LEN(C51)-1))>=总览!$F$7),总览!$G$7,IF(AND(总览!$D$7<>"",B51*100+VALUE(LEFT(C51,LEN(C51)-1))>=总览!$D$7),总览!$E$7,总览!$B$7))))),0) | F51: =ROUND(O50*总览!$B$14/12,0) | G51: =D51+E51+F51 | H51: =IF(OR(B51>2027,AND(B51=2027,VALUE(LEFT(C51,LEN(C51)-1))>=9)),IF(AND(总览!$L$10<>"",B51*100+VALUE(LEFT(C51,LEN(C51)-1))>=总览!$L$10),总览!$M$10,IF(AND(总览!$J$10<>"",B51*100+VALUE(LEFT(C51,LEN(C51)-1))>=总览!$J$10),总览!$K$10,IF(AND(总览!$H$10<>"",B51*100+VALUE(LEFT(C51,LEN(C51)-1))>=总览!$H$10),总览!$I$10,IF(AND(总览!$F$10<>"",B51*100+VALUE(LEFT(C51,LEN(C51)-1))>=总览!$F$10),总览!$G$10,IF(AND(总览!$D$10<>"",B51*100+VALUE(LEFT(C51,LEN(C51)-1))>=总览!$D$10),总览!$E$10,总览!$B$10))))),IF(AND(总览!$L$9<>"",B51*100+VALUE(LEFT(C51,LEN(C51)-1))>=总览!$L$9),总览!$M$9,IF(AND(总览!$J$9<>"",B51*100+VALUE(LEFT(C51,LEN(C51)-1))>=总览!$J$9),总览!$K$9,IF(AND(总览!$H$9<>"",B51*100+VALUE(LEFT(C51,LEN(C51)-1))>=总览!$H$9),总览!$I$9,IF(AND(总览!$F$9<>"",B51*100+VALUE(LEFT(C51,LEN(C51)-1))>=总览!$F$9),总览!$G$9,IF(AND(总览!$D$9<>"",B51*100+VALUE(LEFT(C51,LEN(C51)-1))>=总览!$D$9),总览!$E$9,总览!$B$9)))))) | I51: =IF(AND(总览!$L$11<>"",B51*100+VALUE(LEFT(C51,LEN(C51)-1))>=总览!$L$11),总览!$M$11,IF(AND(总览!$J$11<>"",B51*100+VALUE(LEFT(C51,LEN(C51)-1))>=总览!$J$11),总览!$K$11,IF(AND(总览!$H$11<>"",B51*100+VALUE(LEFT(C51,LEN(C51)-1))>=总览!$H$11),总览!$I$11,IF(AND(总览!$F$11<>"",B51*100+VALUE(LEFT(C51,LEN(C51)-1))>=总览!$F$11),总览!$G$11,IF(AND(总览!$D$11<>"",B51*100+VALUE(LEFT(C51,LEN(C51)-1))>=总览!$D$11),总览!$E$11,总览!$B$11))))) | J51: =IF(OR(B51>2027,AND(B51=2027,VALUE(LEFT(C51,LEN(C51)-1))>=9)),IF(AND(总览!$L$12<>"",B51*100+VALUE(LEFT(C51,LEN(C51)-1))>=总览!$L$12),总览!$M$12,IF(AND(总览!$J$12<>"",B51*100+VALUE(LEFT(C51,LEN(C51)-1))>=总览!$J$12),总览!$K$12,IF(AND(总览!$H$12<>"",B51*100+VALUE(LEFT(C51,LEN(C51)-1))>=总览!$H$12),总览!$I$12,IF(AND(总览!$F$12<>"",B51*100+VALUE(LEFT(C51,LEN(C51)-1))>=总览!$F$12),总览!$G$12,IF(AND(总览!$D$12<>"",B51*100+VALUE(LEFT(C51,LEN(C51)-1))>=总览!$D$12),总览!$E$12,总览!$B$12))))),0) | K51: =IF(AND(B51=2026,C51="5月"),120000,IF(AND(B51=2027,C51="9月"),30000,IF(C51="10月",IF(AND(总览!$L$13<>"",B51*100+VALUE(LEFT(C51,LEN(C51)-1))>=总览!$L$13),总览!$M$13,IF(AND(总览!$J$13<>"",B51*100+VALUE(LEFT(C51,LEN(C51)-1))>=总览!$J$13),总览!$K$13,IF(AND(总览!$H$13<>"",B51*100+VALUE(LEFT(C51,LEN(C51)-1))>=总览!$H$13),总览!$I$13,IF(AND(总览!$F$13<>"",B51*100+VALUE(LEFT(C51,LEN(C51)-1))>=总览!$F$13),总览!$G$13,IF(AND(总览!$D$13<>"",B51*100+VALUE(LEFT(C51,LEN(C51)-1))>=总览!$D$13),总览!$E$13,总览!$B$13))))),0))) | M51: =SUM(H51:K51) | N51: =G51-M51 | O51: =O50+N51
A52: 51 | B52: 2030 | C52: 4月 | D52: =IF(AND(总览!$L$6<>"",B52*100+VALUE(LEFT(C52,LEN(C52)-1))>=总览!$L$6),总览!$M$6,IF(AND(总览!$J$6<>"",B52*100+VALUE(LEFT(C52,LEN(C52)-1))>=总览!$J$6),总览!$K$6,IF(AND(总览!$H$6<>"",B52*100+VALUE(LEFT(C52,LEN(C52)-1))>=总览!$H$6),总览!$I$6,IF(AND(总览!$F$6<>"",B52*100+VALUE(LEFT(C52,LEN(C52)-1))>=总览!$F$6),总览!$G$6,IF(AND(总览!$D$6<>"",B52*100+VALUE(LEFT(C52,LEN(C52)-1))>=总览!$D$6),总览!$E$6,总览!$B$6))))) | E52: =IF(C52="12月",IF(AND(总览!$L$7<>"",B52*100+VALUE(LEFT(C52,LEN(C52)-1))>=总览!$L$7),总览!$M$7,IF(AND(总览!$J$7<>"",B52*100+VALUE(LEFT(C52,LEN(C52)-1))>=总览!$J$7),总览!$K$7,IF(AND(总览!$H$7<>"",B52*100+VALUE(LEFT(C52,LEN(C52)-1))>=总览!$H$7),总览!$I$7,IF(AND(总览!$F$7<>"",B52*100+VALUE(LEFT(C52,LEN(C52)-1))>=总览!$F$7),总览!$G$7,IF(AND(总览!$D$7<>"",B52*100+VALUE(LEFT(C52,LEN(C52)-1))>=总览!$D$7),总览!$E$7,总览!$B$7))))),0) | F52: =ROUND(O51*总览!$B$14/12,0) | G52: =D52+E52+F52 | H52: =IF(OR(B52>2027,AND(B52=2027,VALUE(LEFT(C52,LEN(C52)-1))>=9)),IF(AND(总览!$L$10<>"",B52*100+VALUE(LEFT(C52,LEN(C52)-1))>=总览!$L$10),总览!$M$10,IF(AND(总览!$J$10<>"",B52*100+VALUE(LEFT(C52,LEN(C52)-1))>=总览!$J$10),总览!$K$10,IF(AND(总览!$H$10<>"",B52*100+VALUE(LEFT(C52,LEN(C52)-1))>=总览!$H$10),总览!$I$10,IF(AND(总览!$F$10<>"",B52*100+VALUE(LEFT(C52,LEN(C52)-1))>=总览!$F$10),总览!$G$10,IF(AND(总览!$D$10<>"",B52*100+VALUE(LEFT(C52,LEN(C52)-1))>=总览!$D$10),总览!$E$10,总览!$B$10))))),IF(AND(总览!$L$9<>"",B52*100+VALUE(LEFT(C52,LEN(C52)-1))>=总览!$L$9),总览!$M$9,IF(AND(总览!$J$9<>"",B52*100+VALUE(LEFT(C52,LEN(C52)-1))>=总览!$J$9),总览!$K$9,IF(AND(总览!$H$9<>"",B52*100+VALUE(LEFT(C52,LEN(C52)-1))>=总览!$H$9),总览!$I$9,IF(AND(总览!$F$9<>"",B52*100+VALUE(LEFT(C52,LEN(C52)-1))>=总览!$F$9),总览!$G$9,IF(AND(总览!$D$9<>"",B52*100+VALUE(LEFT(C52,LEN(C52)-1))>=总览!$D$9),总览!$E$9,总览!$B$9)))))) | I52: =IF(AND(总览!$L$11<>"",B52*100+VALUE(LEFT(C52,LEN(C52)-1))>=总览!$L$11),总览!$M$11,IF(AND(总览!$J$11<>"",B52*100+VALUE(LEFT(C52,LEN(C52)-1))>=总览!$J$11),总览!$K$11,IF(AND(总览!$H$11<>"",B52*100+VALUE(LEFT(C52,LEN(C52)-1))>=总览!$H$11),总览!$I$11,IF(AND(总览!$F$11<>"",B52*100+VALUE(LEFT(C52,LEN(C52)-1))>=总览!$F$11),总览!$G$11,IF(AND(总览!$D$11<>"",B52*100+VALUE(LEFT(C52,LEN(C52)-1))>=总览!$D$11),总览!$E$11,总览!$B$11))))) | J52: =IF(OR(B52>2027,AND(B52=2027,VALUE(LEFT(C52,LEN(C52)-1))>=9)),IF(AND(总览!$L$12<>"",B52*100+VALUE(LEFT(C52,LEN(C52)-1))>=总览!$L$12),总览!$M$12,IF(AND(总览!$J$12<>"",B52*100+VALUE(LEFT(C52,LEN(C52)-1))>=总览!$J$12),总览!$K$12,IF(AND(总览!$H$12<>"",B52*100+VALUE(LEFT(C52,LEN(C52)-1))>=总览!$H$12),总览!$I$12,IF(AND(总览!$F$12<>"",B52*100+VALUE(LEFT(C52,LEN(C52)-1))>=总览!$F$12),总览!$G$12,IF(AND(总览!$D$12<>"",B52*100+VALUE(LEFT(C52,LEN(C52)-1))>=总览!$D$12),总览!$E$12,总览!$B$12))))),0) | K52: =IF(AND(B52=2026,C52="5月"),120000,IF(AND(B52=2027,C52="9月"),30000,IF(C52="10月",IF(AND(总览!$L$13<>"",B52*100+VALUE(LEFT(C52,LEN(C52)-1))>=总览!$L$13),总览!$M$13,IF(AND(总览!$J$13<>"",B52*100+VALUE(LEFT(C52,LEN(C52)-1))>=总览!$J$13),总览!$K$13,IF(AND(总览!$H$13<>"",B52*100+VALUE(LEFT(C52,LEN(C52)-1))>=总览!$H$13),总览!$I$13,IF(AND(总览!$F$13<>"",B52*100+VALUE(LEFT(C52,LEN(C52)-1))>=总览!$F$13),总览!$G$13,IF(AND(总览!$D$13<>"",B52*100+VALUE(LEFT(C52,LEN(C52)-1))>=总览!$D$13),总览!$E$13,总览!$B$13))))),0))) | M52: =SUM(H52:K52) | N52: =G52-M52 | O52: =O51+N52
A53: 52 | B53: 2030 | C53: 5月 | D53: =IF(AND(总览!$L$6<>"",B53*100+VALUE(LEFT(C53,LEN(C53)-1))>=总览!$L$6),总览!$M$6,IF(AND(总览!$J$6<>"",B53*100+VALUE(LEFT(C53,LEN(C53)-1))>=总览!$J$6),总览!$K$6,IF(AND(总览!$H$6<>"",B53*100+VALUE(LEFT(C53,LEN(C53)-1))>=总览!$H$6),总览!$I$6,IF(AND(总览!$F$6<>"",B53*100+VALUE(LEFT(C53,LEN(C53)-1))>=总览!$F$6),总览!$G$6,IF(AND(总览!$D$6<>"",B53*100+VALUE(LEFT(C53,LEN(C53)-1))>=总览!$D$6),总览!$E$6,总览!$B$6))))) | E53: =IF(C53="12月",IF(AND(总览!$L$7<>"",B53*100+VALUE(LEFT(C53,LEN(C53)-1))>=总览!$L$7),总览!$M$7,IF(AND(总览!$J$7<>"",B53*100+VALUE(LEFT(C53,LEN(C53)-1))>=总览!$J$7),总览!$K$7,IF(AND(总览!$H$7<>"",B53*100+VALUE(LEFT(C53,LEN(C53)-1))>=总览!$H$7),总览!$I$7,IF(AND(总览!$F$7<>"",B53*100+VALUE(LEFT(C53,LEN(C53)-1))>=总览!$F$7),总览!$G$7,IF(AND(总览!$D$7<>"",B53*100+VALUE(LEFT(C53,LEN(C53)-1))>=总览!$D$7),总览!$E$7,总览!$B$7))))),0) | F53: =ROUND(O52*总览!$B$14/12,0) | G53: =D53+E53+F53 | H53: =IF(OR(B53>2027,AND(B53=2027,VALUE(LEFT(C53,LEN(C53)-1))>=9)),IF(AND(总览!$L$10<>"",B53*100+VALUE(LEFT(C53,LEN(C53)-1))>=总览!$L$10),总览!$M$10,IF(AND(总览!$J$10<>"",B53*100+VALUE(LEFT(C53,LEN(C53)-1))>=总览!$J$10),总览!$K$10,IF(AND(总览!$H$10<>"",B53*100+VALUE(LEFT(C53,LEN(C53)-1))>=总览!$H$10),总览!$I$10,IF(AND(总览!$F$10<>"",B53*100+VALUE(LEFT(C53,LEN(C53)-1))>=总览!$F$10),总览!$G$10,IF(AND(总览!$D$10<>"",B53*100+VALUE(LEFT(C53,LEN(C53)-1))>=总览!$D$10),总览!$E$10,总览!$B$10))))),IF(AND(总览!$L$9<>"",B53*100+VALUE(LEFT(C53,LEN(C53)-1))>=总览!$L$9),总览!$M$9,IF(AND(总览!$J$9<>"",B53*100+VALUE(LEFT(C53,LEN(C53)-1))>=总览!$J$9),总览!$K$9,IF(AND(总览!$H$9<>"",B53*100+VALUE(LEFT(C53,LEN(C53)-1))>=总览!$H$9),总览!$I$9,IF(AND(总览!$F$9<>"",B53*100+VALUE(LEFT(C53,LEN(C53)-1))>=总览!$F$9),总览!$G$9,IF(AND(总览!$D$9<>"",B53*100+VALUE(LEFT(C53,LEN(C53)-1))>=总览!$D$9),总览!$E$9,总览!$B$9)))))) | I53: =IF(AND(总览!$L$11<>"",B53*100+VALUE(LEFT(C53,LEN(C53)-1))>=总览!$L$11),总览!$M$11,IF(AND(总览!$J$11<>"",B53*100+VALUE(LEFT(C53,LEN(C53)-1))>=总览!$J$11),总览!$K$11,IF(AND(总览!$H$11<>"",B53*100+VALUE(LEFT(C53,LEN(C53)-1))>=总览!$H$11),总览!$I$11,IF(AND(总览!$F$11<>"",B53*100+VALUE(LEFT(C53,LEN(C53)-1))>=总览!$F$11),总览!$G$11,IF(AND(总览!$D$11<>"",B53*100+VALUE(LEFT(C53,LEN(C53)-1))>=总览!$D$11),总览!$E$11,总览!$B$11))))) | J53: =IF(OR(B53>2027,AND(B53=2027,VALUE(LEFT(C53,LEN(C53)-1))>=9)),IF(AND(总览!$L$12<>"",B53*100+VALUE(LEFT(C53,LEN(C53)-1))>=总览!$L$12),总览!$M$12,IF(AND(总览!$J$12<>"",B53*100+VALUE(LEFT(C53,LEN(C53)-1))>=总览!$J$12),总览!$K$12,IF(AND(总览!$H$12<>"",B53*100+VALUE(LEFT(C53,LEN(C53)-1))>=总览!$H$12),总览!$I$12,IF(AND(总览!$F$12<>"",B53*100+VALUE(LEFT(C53,LEN(C53)-1))>=总览!$F$12),总览!$G$12,IF(AND(总览!$D$12<>"",B53*100+VALUE(LEFT(C53,LEN(C53)-1))>=总览!$D$12),总览!$E$12,总览!$B$12))))),0) | K53: =IF(AND(B53=2026,C53="5月"),120000,IF(AND(B53=2027,C53="9月"),30000,IF(C53="10月",IF(AND(总览!$L$13<>"",B53*100+VALUE(LEFT(C53,LEN(C53)-1))>=总览!$L$13),总览!$M$13,IF(AND(总览!$J$13<>"",B53*100+VALUE(LEFT(C53,LEN(C53)-1))>=总览!$J$13),总览!$K$13,IF(AND(总览!$H$13<>"",B53*100+VALUE(LEFT(C53,LEN(C53)-1))>=总览!$H$13),总览!$I$13,IF(AND(总览!$F$13<>"",B53*100+VALUE(LEFT(C53,LEN(C53)-1))>=总览!$F$13),总览!$G$13,IF(AND(总览!$D$13<>"",B53*100+VALUE(LEFT(C53,LEN(C53)-1))>=总览!$D$13),总览!$E$13,总览!$B$13))))),0))) | M53: =SUM(H53:K53) | N53: =G53-M53 | O53: =O52+N53
A54: 53 | B54: 2030 | C54: 6月 | D54: =IF(AND(总览!$L$6<>"",B54*100+VALUE(LEFT(C54,LEN(C54)-1))>=总览!$L$6),总览!$M$6,IF(AND(总览!$J$6<>"",B54*100+VALUE(LEFT(C54,LEN(C54)-1))>=总览!$J$6),总览!$K$6,IF(AND(总览!$H$6<>"",B54*100+VALUE(LEFT(C54,LEN(C54)-1))>=总览!$H$6),总览!$I$6,IF(AND(总览!$F$6<>"",B54*100+VALUE(LEFT(C54,LEN(C54)-1))>=总览!$F$6),总览!$G$6,IF(AND(总览!$D$6<>"",B54*100+VALUE(LEFT(C54,LEN(C54)-1))>=总览!$D$6),总览!$E$6,总览!$B$6))))) | E54: =IF(C54="12月",IF(AND(总览!$L$7<>"",B54*100+VALUE(LEFT(C54,LEN(C54)-1))>=总览!$L$7),总览!$M$7,IF(AND(总览!$J$7<>"",B54*100+VALUE(LEFT(C54,LEN(C54)-1))>=总览!$J$7),总览!$K$7,IF(AND(总览!$H$7<>"",B54*100+VALUE(LEFT(C54,LEN(C54)-1))>=总览!$H$7),总览!$I$7,IF(AND(总览!$F$7<>"",B54*100+VALUE(LEFT(C54,LEN(C54)-1))>=总览!$F$7),总览!$G$7,IF(AND(总览!$D$7<>"",B54*100+VALUE(LEFT(C54,LEN(C54)-1))>=总览!$D$7),总览!$E$7,总览!$B$7))))),0) | F54: =ROUND(O53*总览!$B$14/12,0) | G54: =D54+E54+F54 | H54: =IF(OR(B54>2027,AND(B54=2027,VALUE(LEFT(C54,LEN(C54)-1))>=9)),IF(AND(总览!$L$10<>"",B54*100+VALUE(LEFT(C54,LEN(C54)-1))>=总览!$L$10),总览!$M$10,IF(AND(总览!$J$10<>"",B54*100+VALUE(LEFT(C54,LEN(C54)-1))>=总览!$J$10),总览!$K$10,IF(AND(总览!$H$10<>"",B54*100+VALUE(LEFT(C54,LEN(C54)-1))>=总览!$H$10),总览!$I$10,IF(AND(总览!$F$10<>"",B54*100+VALUE(LEFT(C54,LEN(C54)-1))>=总览!$F$10),总览!$G$10,IF(AND(总览!$D$10<>"",B54*100+VALUE(LEFT(C54,LEN(C54)-1))>=总览!$D$10),总览!$E$10,总览!$B$10))))),IF(AND(总览!$L$9<>"",B54*100+VALUE(LEFT(C54,LEN(C54)-1))>=总览!$L$9),总览!$M$9,IF(AND(总览!$J$9<>"",B54*100+VALUE(LEFT(C54,LEN(C54)-1))>=总览!$J$9),总览!$K$9,IF(AND(总览!$H$9<>"",B54*100+VALUE(LEFT(C54,LEN(C54)-1))>=总览!$H$9),总览!$I$9,IF(AND(总览!$F$9<>"",B54*100+VALUE(LEFT(C54,LEN(C54)-1))>=总览!$F$9),总览!$G$9,IF(AND(总览!$D$9<>"",B54*100+VALUE(LEFT(C54,LEN(C54)-1))>=总览!$D$9),总览!$E$9,总览!$B$9)))))) | I54: =IF(AND(总览!$L$11<>"",B54*100+VALUE(LEFT(C54,LEN(C54)-1))>=总览!$L$11),总览!$M$11,IF(AND(总览!$J$11<>"",B54*100+VALUE(LEFT(C54,LEN(C54)-1))>=总览!$J$11),总览!$K$11,IF(AND(总览!$H$11<>"",B54*100+VALUE(LEFT(C54,LEN(C54)-1))>=总览!$H$11),总览!$I$11,IF(AND(总览!$F$11<>"",B54*100+VALUE(LEFT(C54,LEN(C54)-1))>=总览!$F$11),总览!$G$11,IF(AND(总览!$D$11<>"",B54*100+VALUE(LEFT(C54,LEN(C54)-1))>=总览!$D$11),总览!$E$11,总览!$B$11))))) | J54: =IF(OR(B54>2027,AND(B54=2027,VALUE(LEFT(C54,LEN(C54)-1))>=9)),IF(AND(总览!$L$12<>"",B54*100+VALUE(LEFT(C54,LEN(C54)-1))>=总览!$L$12),总览!$M$12,IF(AND(总览!$J$12<>"",B54*100+VALUE(LEFT(C54,LEN(C54)-1))>=总览!$J$12),总览!$K$12,IF(AND(总览!$H$12<>"",B54*100+VALUE(LEFT(C54,LEN(C54)-1))>=总览!$H$12),总览!$I$12,IF(AND(总览!$F$12<>"",B54*100+VALUE(LEFT(C54,LEN(C54)-1))>=总览!$F$12),总览!$G$12,IF(AND(总览!$D$12<>"",B54*100+VALUE(LEFT(C54,LEN(C54)-1))>=总览!$D$12),总览!$E$12,总览!$B$12))))),0) | K54: =IF(AND(B54=2026,C54="5月"),120000,IF(AND(B54=2027,C54="9月"),30000,IF(C54="10月",IF(AND(总览!$L$13<>"",B54*100+VALUE(LEFT(C54,LEN(C54)-1))>=总览!$L$13),总览!$M$13,IF(AND(总览!$J$13<>"",B54*100+VALUE(LEFT(C54,LEN(C54)-1))>=总览!$J$13),总览!$K$13,IF(AND(总览!$H$13<>"",B54*100+VALUE(LEFT(C54,LEN(C54)-1))>=总览!$H$13),总览!$I$13,IF(AND(总览!$F$13<>"",B54*100+VALUE(LEFT(C54,LEN(C54)-1))>=总览!$F$13),总览!$G$13,IF(AND(总览!$D$13<>"",B54*100+VALUE(LEFT(C54,LEN(C54)-1))>=总览!$D$13),总览!$E$13,总览!$B$13))))),0))) | M54: =SUM(H54:K54) | N54: =G54-M54 | O54: =O53+N54
A55: 54 | B55: 2030 | C55: 7月 | D55: =IF(AND(总览!$L$6<>"",B55*100+VALUE(LEFT(C55,LEN(C55)-1))>=总览!$L$6),总览!$M$6,IF(AND(总览!$J$6<>"",B55*100+VALUE(LEFT(C55,LEN(C55)-1))>=总览!$J$6),总览!$K$6,IF(AND(总览!$H$6<>"",B55*100+VALUE(LEFT(C55,LEN(C55)-1))>=总览!$H$6),总览!$I$6,IF(AND(总览!$F$6<>"",B55*100+VALUE(LEFT(C55,LEN(C55)-1))>=总览!$F$6),总览!$G$6,IF(AND(总览!$D$6<>"",B55*100+VALUE(LEFT(C55,LEN(C55)-1))>=总览!$D$6),总览!$E$6,总览!$B$6))))) | E55: =IF(C55="12月",IF(AND(总览!$L$7<>"",B55*100+VALUE(LEFT(C55,LEN(C55)-1))>=总览!$L$7),总览!$M$7,IF(AND(总览!$J$7<>"",B55*100+VALUE(LEFT(C55,LEN(C55)-1))>=总览!$J$7),总览!$K$7,IF(AND(总览!$H$7<>"",B55*100+VALUE(LEFT(C55,LEN(C55)-1))>=总览!$H$7),总览!$I$7,IF(AND(总览!$F$7<>"",B55*100+VALUE(LEFT(C55,LEN(C55)-1))>=总览!$F$7),总览!$G$7,IF(AND(总览!$D$7<>"",B55*100+VALUE(LEFT(C55,LEN(C55)-1))>=总览!$D$7),总览!$E$7,总览!$B$7))))),0) | F55: =ROUND(O54*总览!$B$14/12,0) | G55: =D55+E55+F55 | H55: =IF(OR(B55>2027,AND(B55=2027,VALUE(LEFT(C55,LEN(C55)-1))>=9)),IF(AND(总览!$L$10<>"",B55*100+VALUE(LEFT(C55,LEN(C55)-1))>=总览!$L$10),总览!$M$10,IF(AND(总览!$J$10<>"",B55*100+VALUE(LEFT(C55,LEN(C55)-1))>=总览!$J$10),总览!$K$10,IF(AND(总览!$H$10<>"",B55*100+VALUE(LEFT(C55,LEN(C55)-1))>=总览!$H$10),总览!$I$10,IF(AND(总览!$F$10<>"",B55*100+VALUE(LEFT(C55,LEN(C55)-1))>=总览!$F$10),总览!$G$10,IF(AND(总览!$D$10<>"",B55*100+VALUE(LEFT(C55,LEN(C55)-1))>=总览!$D$10),总览!$E$10,总览!$B$10))))),IF(AND(总览!$L$9<>"",B55*100+VALUE(LEFT(C55,LEN(C55)-1))>=总览!$L$9),总览!$M$9,IF(AND(总览!$J$9<>"",B55*100+VALUE(LEFT(C55,LEN(C55)-1))>=总览!$J$9),总览!$K$9,IF(AND(总览!$H$9<>"",B55*100+VALUE(LEFT(C55,LEN(C55)-1))>=总览!$H$9),总览!$I$9,IF(AND(总览!$F$9<>"",B55*100+VALUE(LEFT(C55,LEN(C55)-1))>=总览!$F$9),总览!$G$9,IF(AND(总览!$D$9<>"",B55*100+VALUE(LEFT(C55,LEN(C55)-1))>=总览!$D$9),总览!$E$9,总览!$B$9)))))) | I55: =IF(AND(总览!$L$11<>"",B55*100+VALUE(LEFT(C55,LEN(C55)-1))>=总览!$L$11),总览!$M$11,IF(AND(总览!$J$11<>"",B55*100+VALUE(LEFT(C55,LEN(C55)-1))>=总览!$J$11),总览!$K$11,IF(AND(总览!$H$11<>"",B55*100+VALUE(LEFT(C55,LEN(C55)-1))>=总览!$H$11),总览!$I$11,IF(AND(总览!$F$11<>"",B55*100+VALUE(LEFT(C55,LEN(C55)-1))>=总览!$F$11),总览!$G$11,IF(AND(总览!$D$11<>"",B55*100+VALUE(LEFT(C55,LEN(C55)-1))>=总览!$D$11),总览!$E$11,总览!$B$11))))) | J55: =IF(OR(B55>2027,AND(B55=2027,VALUE(LEFT(C55,LEN(C55)-1))>=9)),IF(AND(总览!$L$12<>"",B55*100+VALUE(LEFT(C55,LEN(C55)-1))>=总览!$L$12),总览!$M$12,IF(AND(总览!$J$12<>"",B55*100+VALUE(LEFT(C55,LEN(C55)-1))>=总览!$J$12),总览!$K$12,IF(AND(总览!$H$12<>"",B55*100+VALUE(LEFT(C55,LEN(C55)-1))>=总览!$H$12),总览!$I$12,IF(AND(总览!$F$12<>"",B55*100+VALUE(LEFT(C55,LEN(C55)-1))>=总览!$F$12),总览!$G$12,IF(AND(总览!$D$12<>"",B55*100+VALUE(LEFT(C55,LEN(C55)-1))>=总览!$D$12),总览!$E$12,总览!$B$12))))),0) | K55: =IF(AND(B55=2026,C55="5月"),120000,IF(AND(B55=2027,C55="9月"),30000,IF(C55="10月",IF(AND(总览!$L$13<>"",B55*100+VALUE(LEFT(C55,LEN(C55)-1))>=总览!$L$13),总览!$M$13,IF(AND(总览!$J$13<>"",B55*100+VALUE(LEFT(C55,LEN(C55)-1))>=总览!$J$13),总览!$K$13,IF(AND(总览!$H$13<>"",B55*100+VALUE(LEFT(C55,LEN(C55)-1))>=总览!$H$13),总览!$I$13,IF(AND(总览!$F$13<>"",B55*100+VALUE(LEFT(C55,LEN(C55)-1))>=总览!$F$13),总览!$G$13,IF(AND(总览!$D$13<>"",B55*100+VALUE(LEFT(C55,LEN(C55)-1))>=总览!$D$13),总览!$E$13,总览!$B$13))))),0))) | M55: =SUM(H55:K55) | N55: =G55-M55 | O55: =O54+N55
A56: 55 | B56: 2030 | C56: 8月 | D56: =IF(AND(总览!$L$6<>"",B56*100+VALUE(LEFT(C56,LEN(C56)-1))>=总览!$L$6),总览!$M$6,IF(AND(总览!$J$6<>"",B56*100+VALUE(LEFT(C56,LEN(C56)-1))>=总览!$J$6),总览!$K$6,IF(AND(总览!$H$6<>"",B56*100+VALUE(LEFT(C56,LEN(C56)-1))>=总览!$H$6),总览!$I$6,IF(AND(总览!$F$6<>"",B56*100+VALUE(LEFT(C56,LEN(C56)-1))>=总览!$F$6),总览!$G$6,IF(AND(总览!$D$6<>"",B56*100+VALUE(LEFT(C56,LEN(C56)-1))>=总览!$D$6),总览!$E$6,总览!$B$6))))) | E56: =IF(C56="12月",IF(AND(总览!$L$7<>"",B56*100+VALUE(LEFT(C56,LEN(C56)-1))>=总览!$L$7),总览!$M$7,IF(AND(总览!$J$7<>"",B56*100+VALUE(LEFT(C56,LEN(C56)-1))>=总览!$J$7),总览!$K$7,IF(AND(总览!$H$7<>"",B56*100+VALUE(LEFT(C56,LEN(C56)-1))>=总览!$H$7),总览!$I$7,IF(AND(总览!$F$7<>"",B56*100+VALUE(LEFT(C56,LEN(C56)-1))>=总览!$F$7),总览!$G$7,IF(AND(总览!$D$7<>"",B56*100+VALUE(LEFT(C56,LEN(C56)-1))>=总览!$D$7),总览!$E$7,总览!$B$7))))),0) | F56: =ROUND(O55*总览!$B$14/12,0) | G56: =D56+E56+F56 | H56: =IF(OR(B56>2027,AND(B56=2027,VALUE(LEFT(C56,LEN(C56)-1))>=9)),IF(AND(总览!$L$10<>"",B56*100+VALUE(LEFT(C56,LEN(C56)-1))>=总览!$L$10),总览!$M$10,IF(AND(总览!$J$10<>"",B56*100+VALUE(LEFT(C56,LEN(C56)-1))>=总览!$J$10),总览!$K$10,IF(AND(总览!$H$10<>"",B56*100+VALUE(LEFT(C56,LEN(C56)-1))>=总览!$H$10),总览!$I$10,IF(AND(总览!$F$10<>"",B56*100+VALUE(LEFT(C56,LEN(C56)-1))>=总览!$F$10),总览!$G$10,IF(AND(总览!$D$10<>"",B56*100+VALUE(LEFT(C56,LEN(C56)-1))>=总览!$D$10),总览!$E$10,总览!$B$10))))),IF(AND(总览!$L$9<>"",B56*100+VALUE(LEFT(C56,LEN(C56)-1))>=总览!$L$9),总览!$M$9,IF(AND(总览!$J$9<>"",B56*100+VALUE(LEFT(C56,LEN(C56)-1))>=总览!$J$9),总览!$K$9,IF(AND(总览!$H$9<>"",B56*100+VALUE(LEFT(C56,LEN(C56)-1))>=总览!$H$9),总览!$I$9,IF(AND(总览!$F$9<>"",B56*100+VALUE(LEFT(C56,LEN(C56)-1))>=总览!$F$9),总览!$G$9,IF(AND(总览!$D$9<>"",B56*100+VALUE(LEFT(C56,LEN(C56)-1))>=总览!$D$9),总览!$E$9,总览!$B$9)))))) | I56: =IF(AND(总览!$L$11<>"",B56*100+VALUE(LEFT(C56,LEN(C56)-1))>=总览!$L$11),总览!$M$11,IF(AND(总览!$J$11<>"",B56*100+VALUE(LEFT(C56,LEN(C56)-1))>=总览!$J$11),总览!$K$11,IF(AND(总览!$H$11<>"",B56*100+VALUE(LEFT(C56,LEN(C56)-1))>=总览!$H$11),总览!$I$11,IF(AND(总览!$F$11<>"",B56*100+VALUE(LEFT(C56,LEN(C56)-1))>=总览!$F$11),总览!$G$11,IF(AND(总览!$D$11<>"",B56*100+VALUE(LEFT(C56,LEN(C56)-1))>=总览!$D$11),总览!$E$11,总览!$B$11))))) | J56: =IF(OR(B56>2027,AND(B56=2027,VALUE(LEFT(C56,LEN(C56)-1))>=9)),IF(AND(总览!$L$12<>"",B56*100+VALUE(LEFT(C56,LEN(C56)-1))>=总览!$L$12),总览!$M$12,IF(AND(总览!$J$12<>"",B56*100+VALUE(LEFT(C56,LEN(C56)-1))>=总览!$J$12),总览!$K$12,IF(AND(总览!$H$12<>"",B56*100+VALUE(LEFT(C56,LEN(C56)-1))>=总览!$H$12),总览!$I$12,IF(AND(总览!$F$12<>"",B56*100+VALUE(LEFT(C56,LEN(C56)-1))>=总览!$F$12),总览!$G$12,IF(AND(总览!$D$12<>"",B56*100+VALUE(LEFT(C56,LEN(C56)-1))>=总览!$D$12),总览!$E$12,总览!$B$12))))),0) | K56: =IF(AND(B56=2026,C56="5月"),120000,IF(AND(B56=2027,C56="9月"),30000,IF(C56="10月",IF(AND(总览!$L$13<>"",B56*100+VALUE(LEFT(C56,LEN(C56)-1))>=总览!$L$13),总览!$M$13,IF(AND(总览!$J$13<>"",B56*100+VALUE(LEFT(C56,LEN(C56)-1))>=总览!$J$13),总览!$K$13,IF(AND(总览!$H$13<>"",B56*100+VALUE(LEFT(C56,LEN(C56)-1))>=总览!$H$13),总览!$I$13,IF(AND(总览!$F$13<>"",B56*100+VALUE(LEFT(C56,LEN(C56)-1))>=总览!$F$13),总览!$G$13,IF(AND(总览!$D$13<>"",B56*100+VALUE(LEFT(C56,LEN(C56)-1))>=总览!$D$13),总览!$E$13,总览!$B$13))))),0))) | M56: =SUM(H56:K56) | N56: =G56-M56 | O56: =O55+N56
A57: 56 | B57: 2030 | C57: 9月 | D57: =IF(AND(总览!$L$6<>"",B57*100+VALUE(LEFT(C57,LEN(C57)-1))>=总览!$L$6),总览!$M$6,IF(AND(总览!$J$6<>"",B57*100+VALUE(LEFT(C57,LEN(C57)-1))>=总览!$J$6),总览!$K$6,IF(AND(总览!$H$6<>"",B57*100+VALUE(LEFT(C57,LEN(C57)-1))>=总览!$H$6),总览!$I$6,IF(AND(总览!$F$6<>"",B57*100+VALUE(LEFT(C57,LEN(C57)-1))>=总览!$F$6),总览!$G$6,IF(AND(总览!$D$6<>"",B57*100+VALUE(LEFT(C57,LEN(C57)-1))>=总览!$D$6),总览!$E$6,总览!$B$6))))) | E57: =IF(C57="12月",IF(AND(总览!$L$7<>"",B57*100+VALUE(LEFT(C57,LEN(C57)-1))>=总览!$L$7),总览!$M$7,IF(AND(总览!$J$7<>"",B57*100+VALUE(LEFT(C57,LEN(C57)-1))>=总览!$J$7),总览!$K$7,IF(AND(总览!$H$7<>"",B57*100+VALUE(LEFT(C57,LEN(C57)-1))>=总览!$H$7),总览!$I$7,IF(AND(总览!$F$7<>"",B57*100+VALUE(LEFT(C57,LEN(C57)-1))>=总览!$F$7),总览!$G$7,IF(AND(总览!$D$7<>"",B57*100+VALUE(LEFT(C57,LEN(C57)-1))>=总览!$D$7),总览!$E$7,总览!$B$7))))),0) | F57: =ROUND(O56*总览!$B$14/12,0) | G57: =D57+E57+F57 | H57: =IF(OR(B57>2027,AND(B57=2027,VALUE(LEFT(C57,LEN(C57)-1))>=9)),IF(AND(总览!$L$10<>"",B57*100+VALUE(LEFT(C57,LEN(C57)-1))>=总览!$L$10),总览!$M$10,IF(AND(总览!$J$10<>"",B57*100+VALUE(LEFT(C57,LEN(C57)-1))>=总览!$J$10),总览!$K$10,IF(AND(总览!$H$10<>"",B57*100+VALUE(LEFT(C57,LEN(C57)-1))>=总览!$H$10),总览!$I$10,IF(AND(总览!$F$10<>"",B57*100+VALUE(LEFT(C57,LEN(C57)-1))>=总览!$F$10),总览!$G$10,IF(AND(总览!$D$10<>"",B57*100+VALUE(LEFT(C57,LEN(C57)-1))>=总览!$D$10),总览!$E$10,总览!$B$10))))),IF(AND(总览!$L$9<>"",B57*100+VALUE(LEFT(C57,LEN(C57)-1))>=总览!$L$9),总览!$M$9,IF(AND(总览!$J$9<>"",B57*100+VALUE(LEFT(C57,LEN(C57)-1))>=总览!$J$9),总览!$K$9,IF(AND(总览!$H$9<>"",B57*100+VALUE(LEFT(C57,LEN(C57)-1))>=总览!$H$9),总览!$I$9,IF(AND(总览!$F$9<>"",B57*100+VALUE(LEFT(C57,LEN(C57)-1))>=总览!$F$9),总览!$G$9,IF(AND(总览!$D$9<>"",B57*100+VALUE(LEFT(C57,LEN(C57)-1))>=总览!$D$9),总览!$E$9,总览!$B$9)))))) | I57: =IF(AND(总览!$L$11<>"",B57*100+VALUE(LEFT(C57,LEN(C57)-1))>=总览!$L$11),总览!$M$11,IF(AND(总览!$J$11<>"",B57*100+VALUE(LEFT(C57,LEN(C57)-1))>=总览!$J$11),总览!$K$11,IF(AND(总览!$H$11<>"",B57*100+VALUE(LEFT(C57,LEN(C57)-1))>=总览!$H$11),总览!$I$11,IF(AND(总览!$F$11<>"",B57*100+VALUE(LEFT(C57,LEN(C57)-1))>=总览!$F$11),总览!$G$11,IF(AND(总览!$D$11<>"",B57*100+VALUE(LEFT(C57,LEN(C57)-1))>=总览!$D$11),总览!$E$11,总览!$B$11))))) | J57: =IF(OR(B57>2027,AND(B57=2027,VALUE(LEFT(C57,LEN(C57)-1))>=9)),IF(AND(总览!$L$12<>"",B57*100+VALUE(LEFT(C57,LEN(C57)-1))>=总览!$L$12),总览!$M$12,IF(AND(总览!$J$12<>"",B57*100+VALUE(LEFT(C57,LEN(C57)-1))>=总览!$J$12),总览!$K$12,IF(AND(总览!$H$12<>"",B57*100+VALUE(LEFT(C57,LEN(C57)-1))>=总览!$H$12),总览!$I$12,IF(AND(总览!$F$12<>"",B57*100+VALUE(LEFT(C57,LEN(C57)-1))>=总览!$F$12),总览!$G$12,IF(AND(总览!$D$12<>"",B57*100+VALUE(LEFT(C57,LEN(C57)-1))>=总览!$D$12),总览!$E$12,总览!$B$12))))),0) | K57: =IF(AND(B57=2026,C57="5月"),120000,IF(AND(B57=2027,C57="9月"),30000,IF(C57="10月",IF(AND(总览!$L$13<>"",B57*100+VALUE(LEFT(C57,LEN(C57)-1))>=总览!$L$13),总览!$M$13,IF(AND(总览!$J$13<>"",B57*100+VALUE(LEFT(C57,LEN(C57)-1))>=总览!$J$13),总览!$K$13,IF(AND(总览!$H$13<>"",B57*100+VALUE(LEFT(C57,LEN(C57)-1))>=总览!$H$13),总览!$I$13,IF(AND(总览!$F$13<>"",B57*100+VALUE(LEFT(C57,LEN(C57)-1))>=总览!$F$13),总览!$G$13,IF(AND(总览!$D$13<>"",B57*100+VALUE(LEFT(C57,LEN(C57)-1))>=总览!$D$13),总览!$E$13,总览!$B$13))))),0))) | M57: =SUM(H57:K57) | N57: =G57-M57 | O57: =O56+N57
A58: 57 | B58: 2030 | C58: 10月 | D58: =IF(AND(总览!$L$6<>"",B58*100+VALUE(LEFT(C58,LEN(C58)-1))>=总览!$L$6),总览!$M$6,IF(AND(总览!$J$6<>"",B58*100+VALUE(LEFT(C58,LEN(C58)-1))>=总览!$J$6),总览!$K$6,IF(AND(总览!$H$6<>"",B58*100+VALUE(LEFT(C58,LEN(C58)-1))>=总览!$H$6),总览!$I$6,IF(AND(总览!$F$6<>"",B58*100+VALUE(LEFT(C58,LEN(C58)-1))>=总览!$F$6),总览!$G$6,IF(AND(总览!$D$6<>"",B58*100+VALUE(LEFT(C58,LEN(C58)-1))>=总览!$D$6),总览!$E$6,总览!$B$6))))) | E58: =IF(C58="12月",IF(AND(总览!$L$7<>"",B58*100+VALUE(LEFT(C58,LEN(C58)-1))>=总览!$L$7),总览!$M$7,IF(AND(总览!$J$7<>"",B58*100+VALUE(LEFT(C58,LEN(C58)-1))>=总览!$J$7),总览!$K$7,IF(AND(总览!$H$7<>"",B58*100+VALUE(LEFT(C58,LEN(C58)-1))>=总览!$H$7),总览!$I$7,IF(AND(总览!$F$7<>"",B58*100+VALUE(LEFT(C58,LEN(C58)-1))>=总览!$F$7),总览!$G$7,IF(AND(总览!$D$7<>"",B58*100+VALUE(LEFT(C58,LEN(C58)-1))>=总览!$D$7),总览!$E$7,总览!$B$7))))),0) | F58: =ROUND(O57*总览!$B$14/12,0) | G58: =D58+E58+F58 | H58: =IF(OR(B58>2027,AND(B58=2027,VALUE(LEFT(C58,LEN(C58)-1))>=9)),IF(AND(总览!$L$10<>"",B58*100+VALUE(LEFT(C58,LEN(C58)-1))>=总览!$L$10),总览!$M$10,IF(AND(总览!$J$10<>"",B58*100+VALUE(LEFT(C58,LEN(C58)-1))>=总览!$J$10),总览!$K$10,IF(AND(总览!$H$10<>"",B58*100+VALUE(LEFT(C58,LEN(C58)-1))>=总览!$H$10),总览!$I$10,IF(AND(总览!$F$10<>"",B58*100+VALUE(LEFT(C58,LEN(C58)-1))>=总览!$F$10),总览!$G$10,IF(AND(总览!$D$10<>"",B58*100+VALUE(LEFT(C58,LEN(C58)-1))>=总览!$D$10),总览!$E$10,总览!$B$10))))),IF(AND(总览!$L$9<>"",B58*100+VALUE(LEFT(C58,LEN(C58)-1))>=总览!$L$9),总览!$M$9,IF(AND(总览!$J$9<>"",B58*100+VALUE(LEFT(C58,LEN(C58)-1))>=总览!$J$9),总览!$K$9,IF(AND(总览!$H$9<>"",B58*100+VALUE(LEFT(C58,LEN(C58)-1))>=总览!$H$9),总览!$I$9,IF(AND(总览!$F$9<>"",B58*100+VALUE(LEFT(C58,LEN(C58)-1))>=总览!$F$9),总览!$G$9,IF(AND(总览!$D$9<>"",B58*100+VALUE(LEFT(C58,LEN(C58)-1))>=总览!$D$9),总览!$E$9,总览!$B$9)))))) | I58: =IF(AND(总览!$L$11<>"",B58*100+VALUE(LEFT(C58,LEN(C58)-1))>=总览!$L$11),总览!$M$11,IF(AND(总览!$J$11<>"",B58*100+VALUE(LEFT(C58,LEN(C58)-1))>=总览!$J$11),总览!$K$11,IF(AND(总览!$H$11<>"",B58*100+VALUE(LEFT(C58,LEN(C58)-1))>=总览!$H$11),总览!$I$11,IF(AND(总览!$F$11<>"",B58*100+VALUE(LEFT(C58,LEN(C58)-1))>=总览!$F$11),总览!$G$11,IF(AND(总览!$D$11<>"",B58*100+VALUE(LEFT(C58,LEN(C58)-1))>=总览!$D$11),总览!$E$11,总览!$B$11))))) | J58: =IF(OR(B58>2027,AND(B58=2027,VALUE(LEFT(C58,LEN(C58)-1))>=9)),IF(AND(总览!$L$12<>"",B58*100+VALUE(LEFT(C58,LEN(C58)-1))>=总览!$L$12),总览!$M$12,IF(AND(总览!$J$12<>"",B58*100+VALUE(LEFT(C58,LEN(C58)-1))>=总览!$J$12),总览!$K$12,IF(AND(总览!$H$12<>"",B58*100+VALUE(LEFT(C58,LEN(C58)-1))>=总览!$H$12),总览!$I$12,IF(AND(总览!$F$12<>"",B58*100+VALUE(LEFT(C58,LEN(C58)-1))>=总览!$F$12),总览!$G$12,IF(AND(总览!$D$12<>"",B58*100+VALUE(LEFT(C58,LEN(C58)-1))>=总览!$D$12),总览!$E$12,总览!$B$12))))),0) | K58: =IF(AND(B58=2026,C58="5月"),120000,IF(AND(B58=2027,C58="9月"),30000,IF(C58="10月",IF(AND(总览!$L$13<>"",B58*100+VALUE(LEFT(C58,LEN(C58)-1))>=总览!$L$13),总览!$M$13,IF(AND(总览!$J$13<>"",B58*100+VALUE(LEFT(C58,LEN(C58)-1))>=总览!$J$13),总览!$K$13,IF(AND(总览!$H$13<>"",B58*100+VALUE(LEFT(C58,LEN(C58)-1))>=总览!$H$13),总览!$I$13,IF(AND(总览!$F$13<>"",B58*100+VALUE(LEFT(C58,LEN(C58)-1))>=总览!$F$13),总览!$G$13,IF(AND(总览!$D$13<>"",B58*100+VALUE(LEFT(C58,LEN(C58)-1))>=总览!$D$13),总览!$E$13,总览!$B$13))))),0))) | L58: 年度旅游 | M58: =SUM(H58:K58) | N58: =G58-M58 | O58: =O57+N58
A59: 58 | B59: 2030 | C59: 11月 | D59: =IF(AND(总览!$L$6<>"",B59*100+VALUE(LEFT(C59,LEN(C59)-1))>=总览!$L$6),总览!$M$6,IF(AND(总览!$J$6<>"",B59*100+VALUE(LEFT(C59,LEN(C59)-1))>=总览!$J$6),总览!$K$6,IF(AND(总览!$H$6<>"",B59*100+VALUE(LEFT(C59,LEN(C59)-1))>=总览!$H$6),总览!$I$6,IF(AND(总览!$F$6<>"",B59*100+VALUE(LEFT(C59,LEN(C59)-1))>=总览!$F$6),总览!$G$6,IF(AND(总览!$D$6<>"",B59*100+VALUE(LEFT(C59,LEN(C59)-1))>=总览!$D$6),总览!$E$6,总览!$B$6))))) | E59: =IF(C59="12月",IF(AND(总览!$L$7<>"",B59*100+VALUE(LEFT(C59,LEN(C59)-1))>=总览!$L$7),总览!$M$7,IF(AND(总览!$J$7<>"",B59*100+VALUE(LEFT(C59,LEN(C59)-1))>=总览!$J$7),总览!$K$7,IF(AND(总览!$H$7<>"",B59*100+VALUE(LEFT(C59,LEN(C59)-1))>=总览!$H$7),总览!$I$7,IF(AND(总览!$F$7<>"",B59*100+VALUE(LEFT(C59,LEN(C59)-1))>=总览!$F$7),总览!$G$7,IF(AND(总览!$D$7<>"",B59*100+VALUE(LEFT(C59,LEN(C59)-1))>=总览!$D$7),总览!$E$7,总览!$B$7))))),0) | F59: =ROUND(O58*总览!$B$14/12,0) | G59: =D59+E59+F59 | H59: =IF(OR(B59>2027,AND(B59=2027,VALUE(LEFT(C59,LEN(C59)-1))>=9)),IF(AND(总览!$L$10<>"",B59*100+VALUE(LEFT(C59,LEN(C59)-1))>=总览!$L$10),总览!$M$10,IF(AND(总览!$J$10<>"",B59*100+VALUE(LEFT(C59,LEN(C59)-1))>=总览!$J$10),总览!$K$10,IF(AND(总览!$H$10<>"",B59*100+VALUE(LEFT(C59,LEN(C59)-1))>=总览!$H$10),总览!$I$10,IF(AND(总览!$F$10<>"",B59*100+VALUE(LEFT(C59,LEN(C59)-1))>=总览!$F$10),总览!$G$10,IF(AND(总览!$D$10<>"",B59*100+VALUE(LEFT(C59,LEN(C59)-1))>=总览!$D$10),总览!$E$10,总览!$B$10))))),IF(AND(总览!$L$9<>"",B59*100+VALUE(LEFT(C59,LEN(C59)-1))>=总览!$L$9),总览!$M$9,IF(AND(总览!$J$9<>"",B59*100+VALUE(LEFT(C59,LEN(C59)-1))>=总览!$J$9),总览!$K$9,IF(AND(总览!$H$9<>"",B59*100+VALUE(LEFT(C59,LEN(C59)-1))>=总览!$H$9),总览!$I$9,IF(AND(总览!$F$9<>"",B59*100+VALUE(LEFT(C59,LEN(C59)-1))>=总览!$F$9),总览!$G$9,IF(AND(总览!$D$9<>"",B59*100+VALUE(LEFT(C59,LEN(C59)-1))>=总览!$D$9),总览!$E$9,总览!$B$9)))))) | I59: =IF(AND(总览!$L$11<>"",B59*100+VALUE(LEFT(C59,LEN(C59)-1))>=总览!$L$11),总览!$M$11,IF(AND(总览!$J$11<>"",B59*100+VALUE(LEFT(C59,LEN(C59)-1))>=总览!$J$11),总览!$K$11,IF(AND(总览!$H$11<>"",B59*100+VALUE(LEFT(C59,LEN(C59)-1))>=总览!$H$11),总览!$I$11,IF(AND(总览!$F$11<>"",B59*100+VALUE(LEFT(C59,LEN(C59)-1))>=总览!$F$11),总览!$G$11,IF(AND(总览!$D$11<>"",B59*100+VALUE(LEFT(C59,LEN(C59)-1))>=总览!$D$11),总览!$E$11,总览!$B$11))))) | J59: =IF(OR(B59>2027,AND(B59=2027,VALUE(LEFT(C59,LEN(C59)-1))>=9)),IF(AND(总览!$L$12<>"",B59*100+VALUE(LEFT(C59,LEN(C59)-1))>=总览!$L$12),总览!$M$12,IF(AND(总览!$J$12<>"",B59*100+VALUE(LEFT(C59,LEN(C59)-1))>=总览!$J$12),总览!$K$12,IF(AND(总览!$H$12<>"",B59*100+VALUE(LEFT(C59,LEN(C59)-1))>=总览!$H$12),总览!$I$12,IF(AND(总览!$F$12<>"",B59*100+VALUE(LEFT(C59,LEN(C59)-1))>=总览!$F$12),总览!$G$12,IF(AND(总览!$D$12<>"",B59*100+VALUE(LEFT(C59,LEN(C59)-1))>=总览!$D$12),总览!$E$12,总览!$B$12))))),0) | K59: =IF(AND(B59=2026,C59="5月"),120000,IF(AND(B59=2027,C59="9月"),30000,IF(C59="10月",IF(AND(总览!$L$13<>"",B59*100+VALUE(LEFT(C59,LEN(C59)-1))>=总览!$L$13),总览!$M$13,IF(AND(总览!$J$13<>"",B59*100+VALUE(LEFT(C59,LEN(C59)-1))>=总览!$J$13),总览!$K$13,IF(AND(总览!$H$13<>"",B59*100+VALUE(LEFT(C59,LEN(C59)-1))>=总览!$H$13),总览!$I$13,IF(AND(总览!$F$13<>"",B59*100+VALUE(LEFT(C59,LEN(C59)-1))>=总览!$F$13),总览!$G$13,IF(AND(总览!$D$13<>"",B59*100+VALUE(LEFT(C59,LEN(C59)-1))>=总览!$D$13),总览!$E$13,总览!$B$13))))),0))) | M59: =SUM(H59:K59) | N59: =G59-M59 | O59: =O58+N59
A60: 59 | B60: 2030 | C60: 12月 | D60: =IF(AND(总览!$L$6<>"",B60*100+VALUE(LEFT(C60,LEN(C60)-1))>=总览!$L$6),总览!$M$6,IF(AND(总览!$J$6<>"",B60*100+VALUE(LEFT(C60,LEN(C60)-1))>=总览!$J$6),总览!$K$6,IF(AND(总览!$H$6<>"",B60*100+VALUE(LEFT(C60,LEN(C60)-1))>=总览!$H$6),总览!$I$6,IF(AND(总览!$F$6<>"",B60*100+VALUE(LEFT(C60,LEN(C60)-1))>=总览!$F$6),总览!$G$6,IF(AND(总览!$D$6<>"",B60*100+VALUE(LEFT(C60,LEN(C60)-1))>=总览!$D$6),总览!$E$6,总览!$B$6))))) | E60: =IF(C60="12月",IF(AND(总览!$L$7<>"",B60*100+VALUE(LEFT(C60,LEN(C60)-1))>=总览!$L$7),总览!$M$7,IF(AND(总览!$J$7<>"",B60*100+VALUE(LEFT(C60,LEN(C60)-1))>=总览!$J$7),总览!$K$7,IF(AND(总览!$H$7<>"",B60*100+VALUE(LEFT(C60,LEN(C60)-1))>=总览!$H$7),总览!$I$7,IF(AND(总览!$F$7<>"",B60*100+VALUE(LEFT(C60,LEN(C60)-1))>=总览!$F$7),总览!$G$7,IF(AND(总览!$D$7<>"",B60*100+VALUE(LEFT(C60,LEN(C60)-1))>=总览!$D$7),总览!$E$7,总览!$B$7))))),0) | F60: =ROUND(O59*总览!$B$14/12,0) | G60: =D60+E60+F60 | H60: =IF(OR(B60>2027,AND(B60=2027,VALUE(LEFT(C60,LEN(C60)-1))>=9)),IF(AND(总览!$L$10<>"",B60*100+VALUE(LEFT(C60,LEN(C60)-1))>=总览!$L$10),总览!$M$10,IF(AND(总览!$J$10<>"",B60*100+VALUE(LEFT(C60,LEN(C60)-1))>=总览!$J$10),总览!$K$10,IF(AND(总览!$H$10<>"",B60*100+VALUE(LEFT(C60,LEN(C60)-1))>=总览!$H$10),总览!$I$10,IF(AND(总览!$F$10<>"",B60*100+VALUE(LEFT(C60,LEN(C60)-1))>=总览!$F$10),总览!$G$10,IF(AND(总览!$D$10<>"",B60*100+VALUE(LEFT(C60,LEN(C60)-1))>=总览!$D$10),总览!$E$10,总览!$B$10))))),IF(AND(总览!$L$9<>"",B60*100+VALUE(LEFT(C60,LEN(C60)-1))>=总览!$L$9),总览!$M$9,IF(AND(总览!$J$9<>"",B60*100+VALUE(LEFT(C60,LEN(C60)-1))>=总览!$J$9),总览!$K$9,IF(AND(总览!$H$9<>"",B60*100+VALUE(LEFT(C60,LEN(C60)-1))>=总览!$H$9),总览!$I$9,IF(AND(总览!$F$9<>"",B60*100+VALUE(LEFT(C60,LEN(C60)-1))>=总览!$F$9),总览!$G$9,IF(AND(总览!$D$9<>"",B60*100+VALUE(LEFT(C60,LEN(C60)-1))>=总览!$D$9),总览!$E$9,总览!$B$9)))))) | I60: =IF(AND(总览!$L$11<>"",B60*100+VALUE(LEFT(C60,LEN(C60)-1))>=总览!$L$11),总览!$M$11,IF(AND(总览!$J$11<>"",B60*100+VALUE(LEFT(C60,LEN(C60)-1))>=总览!$J$11),总览!$K$11,IF(AND(总览!$H$11<>"",B60*100+VALUE(LEFT(C60,LEN(C60)-1))>=总览!$H$11),总览!$I$11,IF(AND(总览!$F$11<>"",B60*100+VALUE(LEFT(C60,LEN(C60)-1))>=总览!$F$11),总览!$G$11,IF(AND(总览!$D$11<>"",B60*100+VALUE(LEFT(C60,LEN(C60)-1))>=总览!$D$11),总览!$E$11,总览!$B$11))))) | J60: =IF(OR(B60>2027,AND(B60=2027,VALUE(LEFT(C60,LEN(C60)-1))>=9)),IF(AND(总览!$L$12<>"",B60*100+VALUE(LEFT(C60,LEN(C60)-1))>=总览!$L$12),总览!$M$12,IF(AND(总览!$J$12<>"",B60*100+VALUE(LEFT(C60,LEN(C60)-1))>=总览!$J$12),总览!$K$12,IF(AND(总览!$H$12<>"",B60*100+VALUE(LEFT(C60,LEN(C60)-1))>=总览!$H$12),总览!$I$12,IF(AND(总览!$F$12<>"",B60*100+VALUE(LEFT(C60,LEN(C60)-1))>=总览!$F$12),总览!$G$12,IF(AND(总览!$D$12<>"",B60*100+VALUE(LEFT(C60,LEN(C60)-1))>=总览!$D$12),总览!$E$12,总览!$B$12))))),0) | K60: =IF(AND(B60=2026,C60="5月"),120000,IF(AND(B60=2027,C60="9月"),30000,IF(C60="10月",IF(AND(总览!$L$13<>"",B60*100+VALUE(LEFT(C60,LEN(C60)-1))>=总览!$L$13),总览!$M$13,IF(AND(总览!$J$13<>"",B60*100+VALUE(LEFT(C60,LEN(C60)-1))>=总览!$J$13),总览!$K$13,IF(AND(总览!$H$13<>"",B60*100+VALUE(LEFT(C60,LEN(C60)-1))>=总览!$H$13),总览!$I$13,IF(AND(总览!$F$13<>"",B60*100+VALUE(LEFT(C60,LEN(C60)-1))>=总览!$F$13),总览!$G$13,IF(AND(总览!$D$13<>"",B60*100+VALUE(LEFT(C60,LEN(C60)-1))>=总览!$D$13),总览!$E$13,总览!$B$13))))),0))) | M60: =SUM(H60:K60) | N60: =G60-M60 | O60: =O59+N60
A61: 60 | B61: 2031 | C61: 1月 | D61: =IF(AND(总览!$L$6<>"",B61*100+VALUE(LEFT(C61,LEN(C61)-1))>=总览!$L$6),总览!$M$6,IF(AND(总览!$J$6<>"",B61*100+VALUE(LEFT(C61,LEN(C61)-1))>=总览!$J$6),总览!$K$6,IF(AND(总览!$H$6<>"",B61*100+VALUE(LEFT(C61,LEN(C61)-1))>=总览!$H$6),总览!$I$6,IF(AND(总览!$F$6<>"",B61*100+VALUE(LEFT(C61,LEN(C61)-1))>=总览!$F$6),总览!$G$6,IF(AND(总览!$D$6<>"",B61*100+VALUE(LEFT(C61,LEN(C61)-1))>=总览!$D$6),总览!$E$6,总览!$B$6))))) | E61: =IF(C61="12月",IF(AND(总览!$L$7<>"",B61*100+VALUE(LEFT(C61,LEN(C61)-1))>=总览!$L$7),总览!$M$7,IF(AND(总览!$J$7<>"",B61*100+VALUE(LEFT(C61,LEN(C61)-1))>=总览!$J$7),总览!$K$7,IF(AND(总览!$H$7<>"",B61*100+VALUE(LEFT(C61,LEN(C61)-1))>=总览!$H$7),总览!$I$7,IF(AND(总览!$F$7<>"",B61*100+VALUE(LEFT(C61,LEN(C61)-1))>=总览!$F$7),总览!$G$7,IF(AND(总览!$D$7<>"",B61*100+VALUE(LEFT(C61,LEN(C61)-1))>=总览!$D$7),总览!$E$7,总览!$B$7))))),0) | F61: =ROUND(O60*总览!$B$14/12,0) | G61: =D61+E61+F61 | H61: =IF(OR(B61>2027,AND(B61=2027,VALUE(LEFT(C61,LEN(C61)-1))>=9)),IF(AND(总览!$L$10<>"",B61*100+VALUE(LEFT(C61,LEN(C61)-1))>=总览!$L$10),总览!$M$10,IF(AND(总览!$J$10<>"",B61*100+VALUE(LEFT(C61,LEN(C61)-1))>=总览!$J$10),总览!$K$10,IF(AND(总览!$H$10<>"",B61*100+VALUE(LEFT(C61,LEN(C61)-1))>=总览!$H$10),总览!$I$10,IF(AND(总览!$F$10<>"",B61*100+VALUE(LEFT(C61,LEN(C61)-1))>=总览!$F$10),总览!$G$10,IF(AND(总览!$D$10<>"",B61*100+VALUE(LEFT(C61,LEN(C61)-1))>=总览!$D$10),总览!$E$10,总览!$B$10))))),IF(AND(总览!$L$9<>"",B61*100+VALUE(LEFT(C61,LEN(C61)-1))>=总览!$L$9),总览!$M$9,IF(AND(总览!$J$9<>"",B61*100+VALUE(LEFT(C61,LEN(C61)-1))>=总览!$J$9),总览!$K$9,IF(AND(总览!$H$9<>"",B61*100+VALUE(LEFT(C61,LEN(C61)-1))>=总览!$H$9),总览!$I$9,IF(AND(总览!$F$9<>"",B61*100+VALUE(LEFT(C61,LEN(C61)-1))>=总览!$F$9),总览!$G$9,IF(AND(总览!$D$9<>"",B61*100+VALUE(LEFT(C61,LEN(C61)-1))>=总览!$D$9),总览!$E$9,总览!$B$9)))))) | I61: =IF(AND(总览!$L$11<>"",B61*100+VALUE(LEFT(C61,LEN(C61)-1))>=总览!$L$11),总览!$M$11,IF(AND(总览!$J$11<>"",B61*100+VALUE(LEFT(C61,LEN(C61)-1))>=总览!$J$11),总览!$K$11,IF(AND(总览!$H$11<>"",B61*100+VALUE(LEFT(C61,LEN(C61)-1))>=总览!$H$11),总览!$I$11,IF(AND(总览!$F$11<>"",B61*100+VALUE(LEFT(C61,LEN(C61)-1))>=总览!$F$11),总览!$G$11,IF(AND(总览!$D$11<>"",B61*100+VALUE(LEFT(C61,LEN(C61)-1))>=总览!$D$11),总览!$E$11,总览!$B$11))))) | J61: =IF(OR(B61>2027,AND(B61=2027,VALUE(LEFT(C61,LEN(C61)-1))>=9)),IF(AND(总览!$L$12<>"",B61*100+VALUE(LEFT(C61,LEN(C61)-1))>=总览!$L$12),总览!$M$12,IF(AND(总览!$J$12<>"",B61*100+VALUE(LEFT(C61,LEN(C61)-1))>=总览!$J$12),总览!$K$12,IF(AND(总览!$H$12<>"",B61*100+VALUE(LEFT(C61,LEN(C61)-1))>=总览!$H$12),总览!$I$12,IF(AND(总览!$F$12<>"",B61*100+VALUE(LEFT(C61,LEN(C61)-1))>=总览!$F$12),总览!$G$12,IF(AND(总览!$D$12<>"",B61*100+VALUE(LEFT(C61,LEN(C61)-1))>=总览!$D$12),总览!$E$12,总览!$B$12))))),0) | K61: =IF(AND(B61=2026,C61="5月"),120000,IF(AND(B61=2027,C61="9月"),30000,IF(C61="10月",IF(AND(总览!$L$13<>"",B61*100+VALUE(LEFT(C61,LEN(C61)-1))>=总览!$L$13),总览!$M$13,IF(AND(总览!$J$13<>"",B61*100+VALUE(LEFT(C61,LEN(C61)-1))>=总览!$J$13),总览!$K$13,IF(AND(总览!$H$13<>"",B61*100+VALUE(LEFT(C61,LEN(C61)-1))>=总览!$H$13),总览!$I$13,IF(AND(总览!$F$13<>"",B61*100+VALUE(LEFT(C61,LEN(C61)-1))>=总览!$F$13),总览!$G$13,IF(AND(总览!$D$13<>"",B61*100+VALUE(LEFT(C61,LEN(C61)-1))>=总览!$D$13),总览!$E$13,总览!$B$13))))),0))) | M61: =SUM(H61:K61) | N61: =G61-M61 | O61: =O60+N61
A63: 图例说明： | B63: 蓝色=输入值 | D63: 黄底=重大支出月 | F63: 绿底=年终奖月

Sheet 月度现金流（买房）
A1: 序号 | B1: 年份 | C1: 月份 | D1: 月收入(元) | E1: 年终奖(元) | F1: 理财收益(元) | G1: 总收入(元) | H1: 房租(元) | I1: 日常开销(元) | J1: 孩子开销(元) | K1: 特殊支出(元) | L1: 特殊说明 | M1: 首付支出(元) | N1: 房贷月供(元) | O1: 总支出(元) | P1: 当月净储蓄(元) | Q1: 累计储蓄(元) | R1: 房贷剩余(元)
A2: 1 | B2: 2026 | C2: 2月 | D2: =IF(AND(总览!$L$6<>"",B2*100+VALUE(LEFT(C2,LEN(C2)-1))>=总览!$L$6),总览!$M$6,IF(AND(总览!$J$6<>"",B2*100+VALUE(LEFT(C2,LEN(C2)-1))>=总览!$J$6),总览!$K$6,IF(AND(总览!$H$6<>"",B2*100+VALUE(LEFT(C2,LEN(C2)-1))>=总览!$H$6),总览!$I$6,IF(AND(总览!$F$6<>"",B2*100+VALUE(LEFT(C2,LEN(C2)-1))>=总览!$F$6),总览!$G$6,IF(AND(总览!$D$6<>"",B2*100+VALUE(LEFT(C2,LEN(C2)-1))>=总览!$D$6),总览!$E$6,总览!$B$6))))) | E2: =IF(C2="12月",IF(AND(总览!$L$7<>"",B2*100+VALUE(LEFT(C2,LEN(C2)-1))>=总览!$L$7),总览!$M$7,IF(AND(总览!$J$7<>"",B2*100+VALUE(LEFT(C2,LEN(C2)-1))>=总览!$J$7),总览!$K$7,IF(AND(总览!$H$7<>"",B2*100+VALUE(LEFT(C2,LEN(C2)-1))>=总览!$H$7),总览!$I$7,IF(AND(总览!$F$7<>"",B2*100+VALUE(LEFT(C2,LEN(C2)-1))>=总览!$F$7),总览!$G$7,IF(AND(总览!$D$7<>"",B2*100+VALUE(LEFT(C2,LEN(C2)-1))>=总览!$D$7),总览!$E$7,总览!$B$7))))),0) | F2: =ROUND(总览!$B$8*总览!$B$14/12,0) | G2: =D2+E2+F2 | H2: =IF(OR(B2>2027,AND(B2=2027,VALUE(LEFT(C2,LEN(C2)-1))>=9)),IF(AND(总览!$L$10<>"",B2*100+VALUE(LEFT(C2,LEN(C2)-1))>=总览!$L$10),总览!$M$10,IF(AND(总览!$J$10<>"",B2*100+VALUE(LEFT(C2,LEN(C2)-1))>=总览!$J$10),总览!$K$10,IF(AND(总览!$H$10<>"",B2*100+VALUE(LEFT(C2,LEN(C2)-1))>=总览!$H$10),总览!$I$10,IF(AND(总览!$F$10<>"",B2*100+VALUE(LEFT(C2,LEN(C2)-1))>=总览!$F$10),总览!$G$10,IF(AND(总览!$D$10<>"",B2*100+VALUE(LEFT(C2,LEN(C2)-1))>=总览!$D$10),总览!$E$10,总览!$B$10))))),IF(AND(总览!$L$9<>"",B2*100+VALUE(LEFT(C2,LEN(C2)-1))>=总览!$L$9),总览!$M$9,IF(AND(总览!$J$9<>"",B2*100+VALUE(LEFT(C2,LEN(C2)-1))>=总览!$J$9),总览!$K$9,IF(AND(总览!$H$9<>"",B2*100+VALUE(LEFT(C2,LEN(C2)-1))>=总览!$H$9),总览!$I$9,IF(AND(总览!$F$9<>"",B2*100+VALUE(LEFT(C2,LEN(C2)-1))>=总览!$F$9),总览!$G$9,IF(AND(总览!$D$9<>"",B2*100+VALUE(LEFT(C2,LEN(C2)-1))>=总览!$D$9),总览!$E$9,总览!$B$9)))))) | I2: =IF(AND(总览!$L$11<>"",B2*100+VALUE(LEFT(C2,LEN(C2)-1))>=总览!$L$11),总览!$M$11,IF(AND(总览!$J$11<>"",B2*100+VALUE(LEFT(C2,LEN(C2)-1))>=总览!$J$11),总览!$K$11,IF(AND(总览!$H$11<>"",B2*100+VALUE(LEFT(C2,LEN(C2)-1))>=总览!$H$11),总览!$I$11,IF(AND(总览!$F$11<>"",B2*100+VALUE(LEFT(C2,LEN(C2)-1))>=总览!$F$11),总览!$G$11,IF(AND(总览!$D$11<>"",B2*100+VALUE(LEFT(C2,LEN(C2)-1))>=总览!$D$11),总览!$E$11,总览!$B$11))))) | J2: =IF(OR(B2>2027,AND(B2=2027,VALUE(LEFT(C2,LEN(C2)-1))>=9)),IF(AND(总览!$L$12<>"",B2*100+VALUE(LEFT(C2,LEN(C2)-1))>=总览!$L$12),总览!$M$12,IF(AND(总览!$J$12<>"",B2*100+VALUE(LEFT(C2,LEN(C2)-1))>=总览!$J$12),总览!$K$12,IF(AND(总览!$H$12<>"",B2*100+VALUE(LEFT(C2,LEN(C2)-1))>=总览!$H$12),总览!$I$12,IF(AND(总览!$F$12<>"",B2*100+VALUE(LEFT(C2,LEN(C2)-1))>=总览!$F$12),总览!$G$12,IF(AND(总览!$D$12<>"",B2*100+VALUE(LEFT(C2,LEN(C2)-1))>=总览!$D$12),总览!$E$12,总览!$B$12))))),0) | K2: =IF(AND(B2=2026,C2="5月"),120000,IF(AND(B2=2027,C2="9月"),30000,IF(C2="10月",IF(AND(总览!$L$13<>"",B2*100+VALUE(LEFT(C2,LEN(C2)-1))>=总览!$L$13),总览!$M$13,IF(AND(总览!$J$13<>"",B2*100+VALUE(LEFT(C2,LEN(C2)-1))>=总览!$J$13),总览!$K$13,IF(AND(总览!$H$13<>"",B2*100+VALUE(LEFT(C2,LEN(C2)-1))>=总览!$H$13),总览!$I$13,IF(AND(总览!$F$13<>"",B2*100+VALUE(LEFT(C2,LEN(C2)-1))>=总览!$F$13),总览!$G$13,IF(AND(总览!$D$13<>"",B2*100+VALUE(LEFT(C2,LEN(C2)-1))>=总览!$D$13),总览!$E$13,总览!$B$13))))),0))) | M2: =IF(B2*100+VALUE(LEFT(C2,LEN(C2)-1))=总览!$B$18,总览!$B$23,0) | N2: =IF(B2*100+VALUE(LEFT(C2,LEN(C2)-1))>总览!$B$18,总览!$B$25,0) | O2: =SUM(H2:J2)+K2+M2+N2 | P2: =G2-O2 | Q2: =总览!$B$8+P2 | R2: =IF(B2*100+VALUE(LEFT(C2,LEN(C2)-1))<总览!$B$18,0,IF(B2*100+VALUE(LEFT(C2,LEN(C2)-1))=总览!$B$18,总览!$B$24,总览!$B$24))
